Workbook

Sheet Lists & Settings
A1: Position Status | B1: Recruitment Stage | C1: Interview Status | D1: Client Status | E1: Decision | F1: Priority | G1: Yes / No | H1: Ref Numbers | J1: Must-Have Fit | K1: Definition | M1: Must-Have Fit | N1: Min ATS Match | O1: Calculated Decision | Q1: Decision Rules | S1: Talent Pool Status | T1: Seniority Level | U1: Filled Source
A2: Active | B2: Applied | C2: Not Scheduled | D2: Not Submitted | E2: Priority Shortlist | F2: High | G2: Yes | H2: 001 | J2: Pass | K2: All knockout / mandatory requirements are clearly evidenced. | M2: Pass | N2: 0.75 | O2: Priority Shortlist | Q2: Must-Have Fail overrides ATS Match and results in Reject. | S2: Active | T2: Individual Contributor | U2: Osynix Recruiter
A3: On Hold | B3: HR Screening | C3: Scheduled | D3: Submitted | E3: Shortlist | F3: Medium | G3: No | J3: Partial | K3: Core must-have fit is plausible, but at least one knockout requirement needs validation; no confirmed hard failure. | M3: Pass | N3: 0.6 | O3: Shortlist | Q3: ATS thresholds apply only after the Must-Have gate. | S3: Priority Talent | T3: Senior Professional | U3: Client Direct Hire
A4: Closed | B4: Background Check | C4: Completed | D4: Under Review | E4: Hold | F4: Low | J4: Fail | K4: One or more knockout / mandatory requirements are clearly not met. | M4: Pass | N4: 0 | O4: Hold | Q4: Partial can Shortlist / Hold / Reject, but cannot Priority Shortlist. | S4: Passive | T4: Team Lead / Supervisor | U4: Other
B5: Consider
A6: Filled | B6: Shortlisted | C6: No Show | D6: Client Shortlisted | E6: Reject | J6: Insufficient Evidence | K6: The CV / ATS record does not provide enough evidence to determine must-have fit. | M6: Partial | N6: 0.7 | O6: Shortlist | Q6: Insufficient Evidence never auto-shortlists. | S6: Placed | T6: Manager
A7: Cancelled | B7: Technical Interview | C7: Reschedule Required | D7: Client Rejected | E7: Insufficient Evidence | M7: Partial | N7: 0.55 | O7: Hold | Q7: Recruitment Stage is an operational status; it is synchronized at screening but remains manually moveable afterward. | S7: Archived | T7: Senior Manager
B8: Final Interview | C8: Not Required | D8: Client Interview | M8: Partial | N8: 0 | O8: Reject | S8: Do Not Contact | T8: Head / Director
B9: Client Interview | D9: Offer | M9: Fail | N9: 0 | O9: Reject | T9: Executive / GM
B10: Offer Sent | D10: Hired | M10: Insufficient Evidence | N10: 0 | O10: Insufficient Evidence | T10: Founder / Owner
B11: Hired | T11: Officer / Command
B12: Hold
B13: Rejected

Sheet Positions Master
A1: Ref # | B1: Client | C1: Position | D1: Location | E1: Open Date | F1: Status | G1: Priority | H1: Hiring Target | I1: Profiles Screened | J1: Shortlisted | K1: Client Interviews | L1: Offers | M1: Hired | N1: Average ATS Match | O1: Hiring Manager / Contact | P1: JD / File Link | Q1: Notes | R1: Last Updated | S1: JD File Hash | T1: Assigned Recruiter | U1: Created By | V1: Created Date | W1: Position Closed By | X1: Position Closed Date | Y1: Closure Status | Z1: Last Updated By | AA1: Filled Source | AB1: Hired Candidate ID | AC1: Hired Candidate Name | AD1: Closure Reason
A2: 001 | B2: Nobel Business Solutions | C2: Operations Manager / General Manager (LIMO & Chauffeur Services) | D2: Lahore | E2: 46290 | F2: Active | G2: High | H2: 1 | I2: =COUNTIF(Candidates!$B$2:$B$2000,A2) -> 30 | J2: =COUNTIFS(Candidates!$B$2:$B$2000,A2,Candidates!$S$2:$S$2000,"Priority Shortlist")+COUNTIFS(Candidates!$B$2:$B$2000,A2,Candidates!$S$2:$S$2000,"Shortlist") -> 4 | K2: =COUNTIFS(Candidates!$B$2:$B$2000,A2,Candidates!$T$2:$T$2000,"Client Interview") -> 0 | L2: =COUNTIFS(Candidates!$B$2:$B$2000,A2,Candidates!$T$2:$T$2000,"Offer Sent") -> 0 | M2: =COUNTIFS(Candidates!$B$2:$B$2000,A2,Candidates!$T$2:$T$2000,"Hired") -> 0 | N2: =IFERROR(AVERAGEIF(Candidates!$B$2:$B$2000,A2,Candidates!$M$2:$M$2000),0) -> 0.392 | Q2: Direct LIMO/chauffeur service management and US-customer exposure are high-weight requirements. | R2: 46293.146 | W2: Tauqeer Zahid | X2: 46293 | Y2: Filled | Z2: Tauqeer Zahid
A3: 002 | B3: Baba Bakers | C3: Production Manager (Factory) | D3: Gujranwala | E3: 46292 | F3: Active | G3: High | H3: 1 | I3: 0 | J3: 0 | K3: 0 | L3: 0 | M3: 0 | R3: 46291.564
A4: 003 | B4: Baba Bakers | C4: Export Manager | D4: Lahore | E4: 46292 | F4: Filled | G4: Medium | H4: 1 | I4: 0 | J4: 0 | K4: 0 | L4: 0 | M4: 0 | P4: Export Manager.docx | R4: 46292.186 | S4: d43bc043002d670e98a0106f82a1dc472352261b73bd4103d12d0b2b529a9be0
A5: 004 | B5: Baba Bakers | C5: Procurement Executive (Factory) | D5: Lahore | E5: 46293 | F5: Active | G5: Medium | H5: 1 | I5: 0 | J5: 0 | K5: 0 | L5: 0 | M5: 0 | P5: https://docs.google.com/document/d/1ajXMUauVPWAzTwo9Bg6GJGxwT_KhfKet/edit?usp=drivesdk&ouid=100269677063860344655&rtpof=true&sd=true | R5: 46293.25 | S5: 1dbac5440e423cfeb1b7a95799785e99a4e9c28853b89d9d34c6139cbe6e40df | W5: Tauqeer Zahid | X5: 46293 | Y5: Filled | Z5: Tauqeer Zahid
A6: 005 | B6: HR Ways | C6: B2B Sales Executive – US IT Staffing | D6: Karachi | E6: 46295 | F6: Active | G6: High | H6: 1 | I6: 0 | J6: 0 | K6: 0 | L6: 0 | M6: 0 | P6: https://drive.google.com/file/d/1el2PZ9t_qn36A1jZtAIPx43xNmnkYhai/view?usp=drivesdk | R6: 46295.182 | S6: 0eff71ba095c0c1c18b3e5cee51cd37db5c01751de7724965881f7e5399724aa

Sheet Candidates
A1: Candidate ID | B1: Ref # | C1: Candidate Name | D1: Mobile / Phone Number | E1: Email ID | F1: Current Designation | G1: Current Company | H1: Location | I1: Total Experience (Yrs) | J1: Relevant Industry Experience (Yrs) | K1: Date Screened | L1: Evidence Strength /10 | M1: ATS Match % | N1: Must-Have Fit | O1: Core Role Fit /10 | P1: Key Strengths | Q1: Key Gap / Risk | R1: Executive Assessment | S1: Decision | T1: Recruitment Stage | U1: Interview Status | V1: Client Status | W1: Expected Salary | X1: Availability | Y1: Recruiter Notes | Z1: CV / File Link | AA1: Last Updated | AB1: Criterion Results JSON
A2: CAND-001 | B2: 001 | C2: Zain Abid | D2: +92 328 4582394 | E2: zain199819@gmail.com | F2: Freelance UX/UI Designer / Frontend | G2: Freelancer | H2: Lahore Cantt | K2: 46290 | L2: 6 | M2: 0.15 | N2: Fail | O2: 4 | P2: Creative/technical background with some project-management and leadership exposure. | Q2: No meaningful senior transport operations, LIMO/chauffeur management, US customer operations, dispatch, affiliate/farm-out, or limo systems experience. | R2: Profile does not meet Ref #001 core industry requirements despite some transferable project/marketing exposure. | S2: =IF($C2="","",IF(OR($M2="",$N2=""),'Lists & Settings'!$O$10,IF($N2="Fail",'Lists & Settings'!$O$9,IF($N2="Insufficient Evidence",'Lists & Settings'!$O$10,IF($N2="Pass",IF($M2>='Lists & Settings'!$N$2,'Lists & Settings'!$O$2,IF($M2>='Lists & Settings'!$N$3,'Lists & Settings'!$O$3,'Lists & Settings'!$O$4)),IF($N2="Partial",IF($M2>='Lists & Settings'!$N$6,'Lists & Settings'!$O$6,IF($M2>='Lists & Settings'!$N$7,'Lists & Settings'!$O$7,'Lists & Settings'!$O$8)),'Lists & Settings'!$O$10)))))) -> Reject | T2: Rejected | Y2: Qualitative Must-Have Fit: Fail. Latest recalibrated score under strict LIMO/chauffeur + US-market benchmark. | AA2: 46291
A3: CAND-002 | B3: 001 | C3: Sidra Azam | D3: +92 304 4889746 | E3: sidrafatima03044@gmail.com | F3: Senior Sales Executive | G3: Cresset Technologies | H3: Lahore | I3: 6 | K3: 46290 | L3: 7 | M3: 0.24 | N3: Fail | O3: 7 | P3: 6+ years in sales/revenue growth, client acquisition, team leadership and multi-account operations. | Q3: No chauffeur/limo/ground-transportation operations, dispatch, affiliate/farm-out, US limo service, or limo-platform experience. | R3: Strong commercial profile but materially outside the required LIMO/chauffeur operations domain. | S3: =IF($C3="","",IF(OR($M3="",$N3=""),'Lists & Settings'!$O$10,IF($N3="Fail",'Lists & Settings'!$O$9,IF($N3="Insufficient Evidence",'Lists & Settings'!$O$10,IF($N3="Pass",IF($M3>='Lists & Settings'!$N$2,'Lists & Settings'!$O$2,IF($M3>='Lists & Settings'!$N$3,'Lists & Settings'!$O$3,'Lists & Settings'!$O$4)),IF($N3="Partial",IF($M3>='Lists & Settings'!$N$6,'Lists & Settings'!$O$6,IF($M3>='Lists & Settings'!$N$7,'Lists & Settings'!$O$7,'Lists & Settings'!$O$8)),'Lists & Settings'!$O$10)))))) -> Reject | T3: Rejected | Y3: Qualitative Must-Have Fit: Fail. Latest recalibrated score under strict Ref #001 benchmark. | AA3: 46291
A4: CAND-003 | B4: 001 | C4: Ejaz Mehmood | D4: +92 308 4196749 | E4: emahmood91@gmail.com | F4: Limousine Dispatcher & Operations Manager (Remote) | G4: Abiel Limo Worldwide | H4: Lahore | I4: 8 | J4: 8 | K4: 46290 | L4: 9.5 | M4: 0.89 | N4: Pass | O4: 7.5 | P4: 8+ years direct limousine/chauffeur operations; dispatch, reservations, driver assignment, affiliate coordination, Limo Anywhere; USA/UK/Canada bookings. | Q4: CV does not fully evidence broad GM-level ownership across marketing, SEO, development teams and full P&L. | R4: Best direct domain match: proven limo/chauffeur dispatch and explicit US-market booking exposure. Broader GM scope should be validated in interview. | S4: =IF($C4="","",IF(OR($M4="",$N4=""),'Lists & Settings'!$O$10,IF($N4="Fail",'Lists & Settings'!$O$9,IF($N4="Insufficient Evidence",'Lists & Settings'!$O$10,IF($N4="Pass",IF($M4>='Lists & Settings'!$N$2,'Lists & Settings'!$O$2,IF($M4>='Lists & Settings'!$N$3,'Lists & Settings'!$O$3,'Lists & Settings'!$O$4)),IF($N4="Partial",IF($M4>='Lists & Settings'!$N$6,'Lists & Settings'!$O$6,IF($M4>='Lists & Settings'!$N$7,'Lists & Settings'!$O$7,'Lists & Settings'!$O$8)),'Lists & Settings'!$O$10)))))) -> Priority Shortlist | T4: Final Interview | U4: Completed | V4: Client Rejected | Y4: Qualitative Must-Have Fit: Partial / Strong. Explicit US limo/chauffeur exposure. Priority candidate. | AA4: 46291
A5: CAND-004 | B5: 001 | C5: Mansoor Ahmed Bajwa | D5: 0343-7709958 | E5: mansoorbajwa80@gmail.com | F5: Manager Administration Transport | G5: BIGWAY PVT LTD | H5: Lahore | I5: 26 | J5: 8 | K5: 46290 | L5: 8.5 | M5: 0.43 | N5: Fail | O5: 8.5 | P5: Senior transport/fleet leadership, route planning, driver supervision, budgets, logistics, large-team management and operational control. | Q5: No demonstrated LIMO/chauffeur service model, US customers, chauffeur reservations, affiliate/farm-out operations, or limo booking platforms. | R5: Strong transportation leader but direct client-required limo/chauffeur and US-market experience is missing. | S5: =IF($C5="","",IF(OR($M5="",$N5=""),'Lists & Settings'!$O$10,IF($N5="Fail",'Lists & Settings'!$O$9,IF($N5="Insufficient Evidence",'Lists & Settings'!$O$10,IF($N5="Pass",IF($M5>='Lists & Settings'!$N$2,'Lists & Settings'!$O$2,IF($M5>='Lists & Settings'!$N$3,'Lists & Settings'!$O$3,'Lists & Settings'!$O$4)),IF($N5="Partial",IF($M5>='Lists & Settings'!$N$6,'Lists & Settings'!$O$6,IF($M5>='Lists & Settings'!$N$7,'Lists & Settings'!$O$7,'Lists & Settings'!$O$8)),'Lists & Settings'!$O$10)))))) -> Reject | T5: Rejected | Y5: Original assessment: Hold / Backup. Qualitative Must-Have Fit: Fail on direct LIMO/US requirement. | AA5: 46291
A6: CAND-005 | B6: 001 | C6: Fakhra Sikander | D6: +92 322 4720240 | E6: fakhramunir@hotmail.com | F6: Call Center Manager | G6: 3D Lifestyle | H6: Johar Town, Lahore | K6: 46290 | L6: 7.5 | M6: 0.26 | N6: Fail | O6: 8 | P6: Operations management, KPI leadership, CRM optimization, recruitment/training, QA, escalations and customer-service leadership. | Q6: No direct transportation, LIMO/chauffeur, dispatch-industry, affiliate/farm-out or US limo operations experience. | R6: Good service-operations leader but fails the position's core industry requirement. | S6: =IF($C6="","",IF(OR($M6="",$N6=""),'Lists & Settings'!$O$10,IF($N6="Fail",'Lists & Settings'!$O$9,IF($N6="Insufficient Evidence",'Lists & Settings'!$O$10,IF($N6="Pass",IF($M6>='Lists & Settings'!$N$2,'Lists & Settings'!$O$2,IF($M6>='Lists & Settings'!$N$3,'Lists & Settings'!$O$3,'Lists & Settings'!$O$4)),IF($N6="Partial",IF($M6>='Lists & Settings'!$N$6,'Lists & Settings'!$O$6,IF($M6>='Lists & Settings'!$N$7,'Lists & Settings'!$O$7,'Lists & Settings'!$O$8)),'Lists & Settings'!$O$10)))))) -> Reject | T6: Rejected | Y6: Qualitative Must-Have Fit: Fail. Latest strict Ref #001 decision: Reject. | AA6: 46291
A7: CAND-006 | B7: 001 | C7: Qaisar Khalid | D7: 0321-6517101 | E7: qasir.khalid08@gmail.com | F7: Warehouse & Logistic Operation Lead | G7: SWAT Agro Chemicals | H7: Faisalabad | K7: 46290 | L7: 7.5 | M7: 0.31 | N7: Fail | O7: 7 | P7: Logistics operations, staff supervision, budgets, vendors, warehousing and coordination with truck drivers/dispatchers. | Q7: Background is warehouse/supply-chain logistics, not US LIMO/chauffeur service management; no limo systems or affiliate network evidence. | R7: Transferable operations background only; direct client-required domain fit is weak. | S7: =IF($C7="","",IF(OR($M7="",$N7=""),'Lists & Settings'!$O$10,IF($N7="Fail",'Lists & Settings'!$O$9,IF($N7="Insufficient Evidence",'Lists & Settings'!$O$10,IF($N7="Pass",IF($M7>='Lists & Settings'!$N$2,'Lists & Settings'!$O$2,IF($M7>='Lists & Settings'!$N$3,'Lists & Settings'!$O$3,'Lists & Settings'!$O$4)),IF($N7="Partial",IF($M7>='Lists & Settings'!$N$6,'Lists & Settings'!$O$6,IF($M7>='Lists & Settings'!$N$7,'Lists & Settings'!$O$7,'Lists & Settings'!$O$8)),'Lists & Settings'!$O$10)))))) -> Reject | T7: Rejected | Y7: Original assessment: Not Preferred / Hold. Qualitative Must-Have Fit: Fail / Transferable. | AA7: 46291
A8: CAND-007 | B8: 001 | C8: Shahid Iqbal | D8: +92 345 4480810 / +92 315 9614787 | E8: shahed08@gmail.com | F8: Founder & Operations Manager | G8: Independent Retail & Production Unit | H8: Bahawalnagar | I8: 22 | K8: 46290 | L8: 5 | M8: 0.36 | N8: Fail | O8: 9 | P8: 22+ years operations leadership, P&L ownership, KPI setting, vendor/partner negotiation, multi-department coordination and team management. | Q8: Documented experience is manufacturing, supply chain and retail/production rather than LIMO/chauffeur operations or US customer service. | R8: Highly capable operations leader, but the CV does not prove the mandatory direct limo/chauffeur and US-market experience. | S8: =IF($C8="","",IF(OR($M8="",$N8=""),'Lists & Settings'!$O$10,IF($N8="Fail",'Lists & Settings'!$O$9,IF($N8="Insufficient Evidence",'Lists & Settings'!$O$10,IF($N8="Pass",IF($M8>='Lists & Settings'!$N$2,'Lists & Settings'!$O$2,IF($M8>='Lists & Settings'!$N$3,'Lists & Settings'!$O$3,'Lists & Settings'!$O$4)),IF($N8="Partial",IF($M8>='Lists & Settings'!$N$6,'Lists & Settings'!$O$6,IF($M8>='Lists & Settings'!$N$7,'Lists & Settings'!$O$7,'Lists & Settings'!$O$8)),'Lists & Settings'!$O$10)))))) -> Reject | T8: Rejected | Y8: Original assessment: Hold / Not Preferred. CV headline should not be treated as proof of ground-transport domain experience. | AA8: 46291
A9: CAND-008 | B9: 001 | C9: Ali Mahmood Qureshi | D9: +92 341 4333338 | E9: ali_mahmood22@hotmail.com | F9: Head of Customer Success | H9: Lahore | I9: 10 | K9: 46290 | L9: 8.5 | M9: 0.41 | N9: Fail | O9: 8.5 | P9: 10+ years global B2B customer success, US-market enterprise exposure, 50+ team leadership, SLA/KPI ownership, revenue growth and escalation management. | Q9: No direct chauffeur/limo operating experience, reservations, chauffeur dispatch, affiliate/farm-out network or limo systems. | R9: Strong US customer and service-delivery leadership but lacks the core LIMO/chauffeur operational requirement. | S9: =IF($C9="","",IF(OR($M9="",$N9=""),'Lists & Settings'!$O$10,IF($N9="Fail",'Lists & Settings'!$O$9,IF($N9="Insufficient Evidence",'Lists & Settings'!$O$10,IF($N9="Pass",IF($M9>='Lists & Settings'!$N$2,'Lists & Settings'!$O$2,IF($M9>='Lists & Settings'!$N$3,'Lists & Settings'!$O$3,'Lists & Settings'!$O$4)),IF($N9="Partial",IF($M9>='Lists & Settings'!$N$6,'Lists & Settings'!$O$6,IF($M9>='Lists & Settings'!$N$7,'Lists & Settings'!$O$7,'Lists & Settings'!$O$8)),'Lists & Settings'!$O$10)))))) -> Reject | T9: Rejected | Y9: Last documented employer: IP Global (role ended May 2026). Original assessment: Hold / Backup. | AA9: 46291
A10: CAND-009 | B10: 001 | C10: Hira Iqbal Ghaznavi | D10: 0321-4076912 | E10: hiraiqbal657@gmail.com | F10: Senior Sales Consultant | G10: 60 Minute Limo | I10: 8 | J10: 8 | K10: 46290 | L10: 9 | M10: 0.85 | N10: Partial | O10: 9.5 | P10: Direct premium chauffeured ground-transportation exposure; 8+ years across dispatch/logistics/operations; led 30+ dispatch/customer-support staff; KPI/reporting systems; vendor contracts; corporate-account operations; Limo Anywhere, Moovs, Santa Cruz, GNet and related dispatch platforms. | Q10: Explicit US-customer/US-market responsibility is still not evidenced in the CV. Full GM-level P&L ownership, affiliate rate/margin strategy, and oversight of marketing/SEO/development functions should also be validated. | R10: Strong Ref #001 fit with direct premium chauffeur-industry exposure, dispatch/logistics leadership, 30+ team management and extensive ground-transportation systems knowledge. Must-Have remains Partial only because explicit US-market exposure is not documented; interview validation is required. | S10: =IF($C10="","",IF(OR($M10="",$N10=""),'Lists & Settings'!$O$10,IF($N10="Fail",'Lists & Settings'!$O$9,IF($N10="Insufficient Evidence",'Lists & Settings'!$O$10,IF($N10="Pass",IF($M10>='Lists & Settings'!$N$2,'Lists & Settings'!$O$2,IF($M10>='Lists & Settings'!$N$3,'Lists & Settings'!$O$3,'Lists & Settings'!$O$4)),IF($N10="Partial",IF($M10>='Lists & Settings'!$N$6,'Lists & Settings'!$O$6,IF($M10>='Lists & Settings'!$N$7,'Lists & Settings'!$O$7,'Lists & Settings'!$O$8)),'Lists & Settings'!$O$10)))))) -> Shortlist | T10: Shortlisted | Y10: Assessment reconfirmed against uploaded CV on 2026-09-26. Existing ATS score and Shortlist decision retained; explicit US-market exposure remains the key validation point. | Z10: Hira Iqbal Ghaznavi.pdf | AA10: 46291
A11: CAND-010 | B11: 001 | C11: Ahmad Fraz | D11: +92 318 6088030 | E11: ahmadfraz090802@gmail.com | F11: Operations Associate | G11: EDKASA Pvt. Ltd. | H11: Lahore | I11: 5 | K11: 46290 | L11: 8 | M11: 0.37 | N11: Fail | O11: 7.5 | P11: Fleet dispatch, route optimization, driver incentives, vendor/maintenance coordination, KPI dashboards and team leadership. | Q11: Delivery/logistics fleet experience is transferable but not LIMO/chauffeur service management; no US limo customers, affiliate/farm-out or limo platforms. | R11: Solid logistics operator, but direct client-required limo/chauffeur and US-market evidence is missing. | S11: =IF($C11="","",IF(OR($M11="",$N11=""),'Lists & Settings'!$O$10,IF($N11="Fail",'Lists & Settings'!$O$9,IF($N11="Insufficient Evidence",'Lists & Settings'!$O$10,IF($N11="Pass",IF($M11>='Lists & Settings'!$N$2,'Lists & Settings'!$O$2,IF($M11>='Lists & Settings'!$N$3,'Lists & Settings'!$O$3,'Lists & Settings'!$O$4)),IF($N11="Partial",IF($M11>='Lists & Settings'!$N$6,'Lists & Settings'!$O$6,IF($M11>='Lists & Settings'!$N$7,'Lists & Settings'!$O$7,'Lists & Settings'!$O$8)),'Lists & Settings'!$O$10)))))) -> Reject | T11: Rejected | Y11: Original strict assessment: Hold / Not Preferred. Qualitative Must-Have Fit: Fail / Transferable. | AA11: 46291
A12: CAND-011 | B12: 001 | C12: Engr. Muhammad Arslan Ali | D12: +92-301-4387281 | E12: arslanalite20@gmail.com | F12: Logistics Manager (Logistics & Operations) | G12: Alfatah Shopping Mall - Warehouse Lahore | H12: Lahore | I12: 8 | J12: 8 | K12: 46290 | L12: 8.5 | M12: 0.39 | N12: Fail | O12: 8.5 | P12: 8+ years passenger transport/fleet operations, public transit, SLA/KPI management, outsourced operators, scheduling, vendor coordination and safety. | Q12: No commercial LIMO/chauffeur operations, US customer handling, affiliate/farm-out network, reservations or limo-specific platforms. | R12: Strong passenger-transport professional but not a direct match for the US LIMO/chauffeur service model. | S12: =IF($C12="","",IF(OR($M12="",$N12=""),'Lists & Settings'!$O$10,IF($N12="Fail",'Lists & Settings'!$O$9,IF($N12="Insufficient Evidence",'Lists & Settings'!$O$10,IF($N12="Pass",IF($M12>='Lists & Settings'!$N$2,'Lists & Settings'!$O$2,IF($M12>='Lists & Settings'!$N$3,'Lists & Settings'!$O$3,'Lists & Settings'!$O$4)),IF($N12="Partial",IF($M12>='Lists & Settings'!$N$6,'Lists & Settings'!$O$6,IF($M12>='Lists & Settings'!$N$7,'Lists & Settings'!$O$7,'Lists & Settings'!$O$8)),'Lists & Settings'!$O$10)))))) -> Reject | T12: Rejected | Y12: Re-evaluated under stricter Ref #001 criteria. Qualitative Must-Have Fit: Fail on core requirement. | AA12: 46291
A13: CAND-012 | B13: 001 | C13: Muhammad Ameer Hamza | D13: +92 3000987027 | E13: humzabutt419@yahoo.com | F13: Retired Captain | G13: Pakistan Army (Retired) | H13: Pakistan | I13: 8 | K13: 46290 | L13: 8 | M13: 0.27 | N13: Fail | O13: 8 | P13: Commissioned leadership, logistics, administration, crisis response, workforce planning and management of 700+ personnel. | Q13: No commercial LIMO/chauffeur operations, US customer handling, reservations/dispatch, affiliate/farm-out or limo software. | R13: Strong command and operations background, but not relevant enough to the client-specific chauffeur industry requirement. | S13: =IF($C13="","",IF(OR($M13="",$N13=""),'Lists & Settings'!$O$10,IF($N13="Fail",'Lists & Settings'!$O$9,IF($N13="Insufficient Evidence",'Lists & Settings'!$O$10,IF($N13="Pass",IF($M13>='Lists & Settings'!$N$2,'Lists & Settings'!$O$2,IF($M13>='Lists & Settings'!$N$3,'Lists & Settings'!$O$3,'Lists & Settings'!$O$4)),IF($N13="Partial",IF($M13>='Lists & Settings'!$N$6,'Lists & Settings'!$O$6,IF($M13>='Lists & Settings'!$N$7,'Lists & Settings'!$O$7,'Lists & Settings'!$O$8)),'Lists & Settings'!$O$10)))))) -> Reject | T13: Rejected | Y13: Qualitative Must-Have Fit: Fail. VIP movement experience was security-related, not commercial chauffeur service delivery. | AA13: 46291
A14: CAND-013 | B14: 001 | C14: Muhammad Khalid | D14: 923006231094 | E14: khalidrafiq0088@gmail.com | F14: Factory Manager | G14: Dura Flow Pvt. Ltd. | H14: Chishtian, Bahawalnagar | K14: 46290 | L14: 7.5 | M14: 0.21 | N14: Fail | O14: 7.5 | P14: General management, production planning, budgets, teams, cost control, quality and cross-functional manufacturing operations. | Q14: No LIMO/chauffeur service management, US customer operations, dispatch/reservations, affiliate/farm-out or limo systems. | R14: Credible general manager in manufacturing, but no alignment with the mandatory chauffeur/limo domain. | S14: =IF($C14="","",IF(OR($M14="",$N14=""),'Lists & Settings'!$O$10,IF($N14="Fail",'Lists & Settings'!$O$9,IF($N14="Insufficient Evidence",'Lists & Settings'!$O$10,IF($N14="Pass",IF($M14>='Lists & Settings'!$N$2,'Lists & Settings'!$O$2,IF($M14>='Lists & Settings'!$N$3,'Lists & Settings'!$O$3,'Lists & Settings'!$O$4)),IF($N14="Partial",IF($M14>='Lists & Settings'!$N$6,'Lists & Settings'!$O$6,IF($M14>='Lists & Settings'!$N$7,'Lists & Settings'!$O$7,'Lists & Settings'!$O$8)),'Lists & Settings'!$O$10)))))) -> Reject | T14: Rejected | Y14: Qualitative Must-Have Fit: Fail. Current role stated as Factory Manager. | AA14: 46291
A15: CAND-014 | B15: 001 | C15: Kumail Naqvi | D15: +92 312 044 1931 | E15: syedkaimy@gmail.com | F15: Business Development & Sales Operations Manager | I15: 10 | J15: 3.3 | K15: 46290 | L15: 8.5 | M15: 0.55 | N15: Fail | O15: 8 | P15: US-based freight dispatch experience in Houston; load booking, rate negotiation, driver scheduling, route planning, CRM/load boards and dispatcher supervision. | Q15: Experience is US freight/trucking logistics, not limousine/chauffeur service management; no limo reservations, premium passenger service, affiliate/farm-out or limo platforms. | R15: US dispatch exposure is useful and stronger than generic logistics, but the transportation vertical does not meet the core limo/chauffeur requirement. | S15: =IF($C15="","",IF(OR($M15="",$N15=""),'Lists & Settings'!$O$10,IF($N15="Fail",'Lists & Settings'!$O$9,IF($N15="Insufficient Evidence",'Lists & Settings'!$O$10,IF($N15="Pass",IF($M15>='Lists & Settings'!$N$2,'Lists & Settings'!$O$2,IF($M15>='Lists & Settings'!$N$3,'Lists & Settings'!$O$3,'Lists & Settings'!$O$4)),IF($N15="Partial",IF($M15>='Lists & Settings'!$N$6,'Lists & Settings'!$O$6,IF($M15>='Lists & Settings'!$N$7,'Lists & Settings'!$O$7,'Lists & Settings'!$O$8)),'Lists & Settings'!$O$10)))))) -> Reject | T15: Rejected | Y15: Last documented role: Head of Sales, Communications & Business Operations, LEXTON Logistics LLC (ended Jun 2026). | AA15: 46291
A16: CAND-015 | B16: 001 | C16: Rana Rashid Ali Sadiq | D16: 03207789165 | E16: rashidrana165@gmail.com | F16: Assistant Manager Workshop | G16: Veda Transit Solution (Metro Bus Service) | H16: Township, Lahore | J16: 7.3 | K16: 46291 | L16: 9 | M16: 0.34 | N16: Fail | O16: 7.5 | P16: Fleet/workshop leadership, route and transport management, maintenance strategy, driver performance, public transport and aviation fleet exposure. | Q16: No limousine/chauffeur service operations, US customers, reservations, affiliate/farm-out or limo platforms. | R16: Strong fleet and workshop profile but only transferable to the client-specific limo/chauffeur model. | S16: =IF($C16="","",IF(OR($M16="",$N16=""),'Lists & Settings'!$O$10,IF($N16="Fail",'Lists & Settings'!$O$9,IF($N16="Insufficient Evidence",'Lists & Settings'!$O$10,IF($N16="Pass",IF($M16>='Lists & Settings'!$N$2,'Lists & Settings'!$O$2,IF($M16>='Lists & Settings'!$N$3,'Lists & Settings'!$O$3,'Lists & Settings'!$O$4)),IF($N16="Partial",IF($M16>='Lists & Settings'!$N$6,'Lists & Settings'!$O$6,IF($M16>='Lists & Settings'!$N$7,'Lists & Settings'!$O$7,'Lists & Settings'!$O$8)),'Lists & Settings'!$O$10)))))) -> Reject | T16: Rejected | Y16: Original assessment: Hold / Not Preferred. Qualitative Must-Have Fit: Fail. | AA16: 46291
A17: CAND-016 | B17: 001 | C17: Iftikhar Ahmed | D17: +92 321 2886797 | E17: iftikharahmed0670@gmail.com | F17: Operations Excellence Manager | G17: Orange Line Metro Rail Transit System | H17: Lahore | I17: 23 | J17: 21 | K17: 46291 | L17: 9 | M17: 0.3 | N17: Fail | O17: 8 | P17: 23+ years operational excellence, metro passenger operations, fleet/workshop management, KPIs, vendors, audits, safety and continuous improvement. | Q17: No commercial LIMO/chauffeur operations, US customers, affiliate/farm-out, reservations or limo systems. | R17: Senior operations professional, but industry fit to US chauffeur/limo services is insufficient. | S17: =IF($C17="","",IF(OR($M17="",$N17=""),'Lists & Settings'!$O$10,IF($N17="Fail",'Lists & Settings'!$O$9,IF($N17="Insufficient Evidence",'Lists & Settings'!$O$10,IF($N17="Pass",IF($M17>='Lists & Settings'!$N$2,'Lists & Settings'!$O$2,IF($M17>='Lists & Settings'!$N$3,'Lists & Settings'!$O$3,'Lists & Settings'!$O$4)),IF($N17="Partial",IF($M17>='Lists & Settings'!$N$6,'Lists & Settings'!$O$6,IF($M17>='Lists & Settings'!$N$7,'Lists & Settings'!$O$7,'Lists & Settings'!$O$8)),'Lists & Settings'!$O$10)))))) -> Reject | T17: Rejected | Y17: Original assessment label: Not Preferred. Stored as Hold to preserve non-final rejection status. | AA17: 46291
A18: CAND-017 | B18: 001 | C18: Muhammad Kashif Iqbal | D18: +92 317 7184901 | E18: Kashif.iqbal5987@gmail.com | F18: Manager Operations | G18: Imperial Venture | H18: Gujranwala | J18: 1.8 | K18: 46291 | L18: 8.5 | M18: 0.18 | N18: Fail | O18: 5.5 | P18: Field operations, route management, driver productivity, SOPs, safety/HSE, reporting and waste-transport coordination. | Q18: No chauffeur/limo business, US customer operations, premium passenger service, affiliate/farm-out or limo dispatch systems. | R18: Operational exposure is in waste management/HSE and does not meet Ref #001 core domain requirements. | S18: =IF($C18="","",IF(OR($M18="",$N18=""),'Lists & Settings'!$O$10,IF($N18="Fail",'Lists & Settings'!$O$9,IF($N18="Insufficient Evidence",'Lists & Settings'!$O$10,IF($N18="Pass",IF($M18>='Lists & Settings'!$N$2,'Lists & Settings'!$O$2,IF($M18>='Lists & Settings'!$N$3,'Lists & Settings'!$O$3,'Lists & Settings'!$O$4)),IF($N18="Partial",IF($M18>='Lists & Settings'!$N$6,'Lists & Settings'!$O$6,IF($M18>='Lists & Settings'!$N$7,'Lists & Settings'!$O$7,'Lists & Settings'!$O$8)),'Lists & Settings'!$O$10)))))) -> Reject | T18: Rejected | Y18: Qualitative Must-Have Fit: Fail. | AA18: 46291
A19: CAND-018 | B19: 001 | C19: Nauman Atique | D19: +92 305 8215553 / +92 326 0590127 | E19: rananaumanatique@gmail.com | F19: DM Operations | G19: Sindh Solid Waste Management Board | Endurance Environment | H19: Lahore | I19: 10 | J19: 5.3 | K19: 46291 | L19: 9 | M19: 0.25 | N19: Fail | O19: 7.5 | P19: 10+ years operations/fleet management, route planning, vehicle deployment, vendor/contractor management, cost control and field-team leadership. | Q19: Experience is municipal/healthcare waste and environmental services; no LIMO/chauffeur or US-client operations. | R19: Strong fleet-management capability but the core industry requirement is absent. | S19: =IF($C19="","",IF(OR($M19="",$N19=""),'Lists & Settings'!$O$10,IF($N19="Fail",'Lists & Settings'!$O$9,IF($N19="Insufficient Evidence",'Lists & Settings'!$O$10,IF($N19="Pass",IF($M19>='Lists & Settings'!$N$2,'Lists & Settings'!$O$2,IF($M19>='Lists & Settings'!$N$3,'Lists & Settings'!$O$3,'Lists & Settings'!$O$4)),IF($N19="Partial",IF($M19>='Lists & Settings'!$N$6,'Lists & Settings'!$O$6,IF($M19>='Lists & Settings'!$N$7,'Lists & Settings'!$O$7,'Lists & Settings'!$O$8)),'Lists & Settings'!$O$10)))))) -> Reject | T19: Rejected | Y19: Qualitative Must-Have Fit: Fail. Direct chauffeur/limo evidence absent. | AA19: 46291
A20: CAND-019 | B20: 001 | C20: Razi Abbas | D20: +92-311-7365492 | E20: raziabbas7212@gmail.com | F20: Branch Manager | G20: Food Panda | H20: Multan | J20: 3 | K20: 46291 | L20: 8 | M20: 0.2 | N20: Fail | O20: 5.5 | P20: Branch operations, last-mile delivery, riders, hub dispatch, KPI tracking, inventory and service-quality management. | Q20: Comparatively junior and entirely e-commerce/food-delivery focused; no LIMO/chauffeur, US market or GM-level chauffeur operations. | R20: Useful last-mile exposure but far below the client-specific senior chauffeur/limo requirement. | S20: =IF($C20="","",IF(OR($M20="",$N20=""),'Lists & Settings'!$O$10,IF($N20="Fail",'Lists & Settings'!$O$9,IF($N20="Insufficient Evidence",'Lists & Settings'!$O$10,IF($N20="Pass",IF($M20>='Lists & Settings'!$N$2,'Lists & Settings'!$O$2,IF($M20>='Lists & Settings'!$N$3,'Lists & Settings'!$O$3,'Lists & Settings'!$O$4)),IF($N20="Partial",IF($M20>='Lists & Settings'!$N$6,'Lists & Settings'!$O$6,IF($M20>='Lists & Settings'!$N$7,'Lists & Settings'!$O$7,'Lists & Settings'!$O$8)),'Lists & Settings'!$O$10)))))) -> Reject | T20: Rejected | Y20: Qualitative Must-Have Fit: Fail. | AA20: 46291
A21: CAND-020 | B21: 001 | C21: Salman Khan Magsi | D21: 0300-4337261 | E21: salmanmagsi38@gmail.com | F21: Senior Manager Operations | G21: Secure Logistics Group | H21: Bahria Town, Lahore | I21: 23 | J21: 23 | K21: 46291 | L21: 9 | M21: 0.42 | N21: Fail | O21: 8.5 | P21: 23 years courier/logistics/transportation leadership; centralized dispatch, booking/forwarding, fleet outsourcing, multi-branch operations, costs and teams. | Q21: No limousine/chauffeur service management, US customer exposure, affiliate/farm-out limo network or limo-specific software. | R21: Strongest generic transport/logistics profile among recent batch, but still outside the mandatory US limo/chauffeur domain. | S21: =IF($C21="","",IF(OR($M21="",$N21=""),'Lists & Settings'!$O$10,IF($N21="Fail",'Lists & Settings'!$O$9,IF($N21="Insufficient Evidence",'Lists & Settings'!$O$10,IF($N21="Pass",IF($M21>='Lists & Settings'!$N$2,'Lists & Settings'!$O$2,IF($M21>='Lists & Settings'!$N$3,'Lists & Settings'!$O$3,'Lists & Settings'!$O$4)),IF($N21="Partial",IF($M21>='Lists & Settings'!$N$6,'Lists & Settings'!$O$6,IF($M21>='Lists & Settings'!$N$7,'Lists & Settings'!$O$7,'Lists & Settings'!$O$8)),'Lists & Settings'!$O$10)))))) -> Reject | T21: Rejected | Y21: Original assessment: Hold / Backup Only. Qualitative Must-Have Fit: Fail / Transferable. | AA21: 46291
A22: CAND-021 | B22: 001 | C22: Raza Shahzad | D22: +92-3214007507 | E22: razashahzad52@gmail.com | K22: 46291 | L22: 7.5 | M22: 0.34 | N22: Fail | O22: 7.5 | P22: Operations management, vendors/contractors, target setting, multi-region team supervision, CRM and service-provider coordination. | Q22: No limousine/chauffeur operations, US customer handling, dispatch/reservations, affiliate/farm-out or limo platforms. | R22: General operations experience is relevant only at a transferable level and does not satisfy the core requirement. | S22: =IF($C22="","",IF(OR($M22="",$N22=""),'Lists & Settings'!$O$10,IF($N22="Fail",'Lists & Settings'!$O$9,IF($N22="Insufficient Evidence",'Lists & Settings'!$O$10,IF($N22="Pass",IF($M22>='Lists & Settings'!$N$2,'Lists & Settings'!$O$2,IF($M22>='Lists & Settings'!$N$3,'Lists & Settings'!$O$3,'Lists & Settings'!$O$4)),IF($N22="Partial",IF($M22>='Lists & Settings'!$N$6,'Lists & Settings'!$O$6,IF($M22>='Lists & Settings'!$N$7,'Lists & Settings'!$O$7,'Lists & Settings'!$O$8)),'Lists & Settings'!$O$10)))))) -> Reject | T22: Rejected | Y22: Last documented role: Operations Manager, High Tide Inc (ended Mar 2026). Qualitative Must-Have Fit: Fail. | AA22: 46291
A23: CAND-022 | B23: 001 | C23: Alam Fazal | D23: +92-321-9886773 | E23: alam.fazal@yahoo.com | F23: Incharge Fleet Operations, Maintenance & Logistics | G23: Daewoo Express Bus Service Pakistan | H23: Bahria Orchard, Lahore | J23: 13 | K23: 46291 | L23: 9 | M23: 0.39 | N23: Fail | O23: 8.5 | P23: Passenger-transport fleet operations, depot leadership, 90+ staff supervision, vendors, KPIs, maintenance budgets and cross-functional coordination. | Q23: No LIMO/chauffeur service management, US-based customers, reservations/booking, affiliate/farm-out or limo-specific software. | R23: Credible passenger-transport operator but direct US chauffeur/limo domain fit is unproven. | S23: =IF($C23="","",IF(OR($M23="",$N23=""),'Lists & Settings'!$O$10,IF($N23="Fail",'Lists & Settings'!$O$9,IF($N23="Insufficient Evidence",'Lists & Settings'!$O$10,IF($N23="Pass",IF($M23>='Lists & Settings'!$N$2,'Lists & Settings'!$O$2,IF($M23>='Lists & Settings'!$N$3,'Lists & Settings'!$O$3,'Lists & Settings'!$O$4)),IF($N23="Partial",IF($M23>='Lists & Settings'!$N$6,'Lists & Settings'!$O$6,IF($M23>='Lists & Settings'!$N$7,'Lists & Settings'!$O$7,'Lists & Settings'!$O$8)),'Lists & Settings'!$O$10)))))) -> Reject | T23: Rejected | Y23: Original assessment: Hold / Not Preferred. Qualitative Must-Have Fit: Fail / Transferable. | AA23: 46291
A24: CAND-023 | B24: 001 | C24: Rizwan Khan Bangash | D24: +92 300 6665444 | E24: rizwan6665444@gmail.com | F24: Centralized Warehouse & Inventory Control Manager | G24: AGI Denim | H24: Karachi | I24: 20 | K24: 46291 | L24: 9 | M24: 0.24 | N24: Fail | O24: 7.5 | P24: 20+ years supply-chain, warehouse, inventory, production planning, lean process improvement and global buyer coordination. | Q24: No passenger transportation, LIMO/chauffeur operations, US limo customers, reservations/dispatch, affiliate/farm-out or limo systems. | R24: Strong supply-chain leader but no relevant chauffeur-industry experience for Ref #001. | S24: =IF($C24="","",IF(OR($M24="",$N24=""),'Lists & Settings'!$O$10,IF($N24="Fail",'Lists & Settings'!$O$9,IF($N24="Insufficient Evidence",'Lists & Settings'!$O$10,IF($N24="Pass",IF($M24>='Lists & Settings'!$N$2,'Lists & Settings'!$O$2,IF($M24>='Lists & Settings'!$N$3,'Lists & Settings'!$O$3,'Lists & Settings'!$O$4)),IF($N24="Partial",IF($M24>='Lists & Settings'!$N$6,'Lists & Settings'!$O$6,IF($M24>='Lists & Settings'!$N$7,'Lists & Settings'!$O$7,'Lists & Settings'!$O$8)),'Lists & Settings'!$O$10)))))) -> Reject | T24: Rejected | Y24: Qualitative Must-Have Fit: Fail. | AA24: 46291
A25: CAND-024 | B25: 001 | C25: Waqas Ali | D25: +92 306 7307079 | E25: waqasalisidhu06@gmail.com | F25: Deputy Manager Operations | G25: Faisal Movers Express – Orange Line Metro Bus Project | H25: Bahawalpur | I25: 10 | J25: 10 | K25: 46291 | L25: 8.5 | M25: 0.44 | N25: Fail | O25: 8.5 | P25: 10+ years public passenger transport, dispatch management, fleet scheduling, ITS, route optimization, crisis response and very large workforce management. | Q25: Experience is public bus/transit operations with no documented LIMO/chauffeur business, US customers, affiliate/farm-out, reservations or limo platforms. | R25: Operationally strong transport candidate but only a backup because direct US limo/chauffeur experience is absent. | S25: =IF($C25="","",IF(OR($M25="",$N25=""),'Lists & Settings'!$O$10,IF($N25="Fail",'Lists & Settings'!$O$9,IF($N25="Insufficient Evidence",'Lists & Settings'!$O$10,IF($N25="Pass",IF($M25>='Lists & Settings'!$N$2,'Lists & Settings'!$O$2,IF($M25>='Lists & Settings'!$N$3,'Lists & Settings'!$O$3,'Lists & Settings'!$O$4)),IF($N25="Partial",IF($M25>='Lists & Settings'!$N$6,'Lists & Settings'!$O$6,IF($M25>='Lists & Settings'!$N$7,'Lists & Settings'!$O$7,'Lists & Settings'!$O$8)),'Lists & Settings'!$O$10)))))) -> Reject | T25: Rejected | Y25: Original assessment: Hold / Backup Only. Qualitative Must-Have Fit: Fail / Transferable. | AA25: 46291
A26: CAND-025 | B26: 001 | C26: M. Sohail Shahid | D26: +966 554513158 / +92 307 6261861 | E26: msohailshahid79@gmail.com | F26: Electronics Engineer | G26: Prince Sultan Military Medical City via Binjarallah Group | H26: Riyadh, Saudi Arabia | J26: 5 | K26: 46291 | L26: 9 | M26: 0.33 | N26: Fail | O26: 7 | P26: Five years metro transportation operations, staff/shift supervision, control-room coordination, passenger service, incident response and technical systems. | Q26: No commercial LIMO/chauffeur operations, US customers, reservations, affiliate/farm-out or limo-specific software; current role is technical engineering. | R26: Relevant public-transit operations but not aligned with the commercial US chauffeur/limo service model. | S26: =IF($C26="","",IF(OR($M26="",$N26=""),'Lists & Settings'!$O$10,IF($N26="Fail",'Lists & Settings'!$O$9,IF($N26="Insufficient Evidence",'Lists & Settings'!$O$10,IF($N26="Pass",IF($M26>='Lists & Settings'!$N$2,'Lists & Settings'!$O$2,IF($M26>='Lists & Settings'!$N$3,'Lists & Settings'!$O$3,'Lists & Settings'!$O$4)),IF($N26="Partial",IF($M26>='Lists & Settings'!$N$6,'Lists & Settings'!$O$6,IF($M26>='Lists & Settings'!$N$7,'Lists & Settings'!$O$7,'Lists & Settings'!$O$8)),'Lists & Settings'!$O$10)))))) -> Reject | T26: Rejected | Y26: Qualitative Must-Have Fit: Fail. Relevant Experience field reflects explicitly stated 5 years in transportation operations. | AA26: 46291
A27: CAND-026 | B27: 001 | C27: Inam Ur Rehman | D27: 0307-0150150 | E27: inamu9581@gmail.com | F27: Supply Chain Executive (Logistics) | G27: Gourmet Foods Pakistan (Head Office) | H27: Lahore | I27: 8.6 | J27: 3 | K27: 46291 | L27: 8.5 | M27: 0.27 | N27: Fail | O27: 6.5 | P27: FMCG logistics and dispatch operations; vehicle allocation, route scheduling, shipment monitoring, 3PL/transporter coordination, warehouse operations, KPI reporting, SAP/WMS exposure. | Q27: No direct LIMO/chauffeur service management, no US-customer/market exposure, no premium passenger reservations/affiliate farm-out model, and no limo-specific software. | R27: Strong transferable logistics/dispatch profile, but both Ref #001 knockout requirements are absent and current seniority is below GM-level chauffeur operations. | S27: =IF($C27="","",IF(OR($M27="",$N27=""),'Lists & Settings'!$O$10,IF($N27="Fail",'Lists & Settings'!$O$9,IF($N27="Insufficient Evidence",'Lists & Settings'!$O$10,IF($N27="Pass",IF($M27>='Lists & Settings'!$N$2,'Lists & Settings'!$O$2,IF($M27>='Lists & Settings'!$N$3,'Lists & Settings'!$O$3,'Lists & Settings'!$O$4)),IF($N27="Partial",IF($M27>='Lists & Settings'!$N$6,'Lists & Settings'!$O$6,IF($M27>='Lists & Settings'!$N$7,'Lists & Settings'!$O$7,'Lists & Settings'!$O$8)),'Lists & Settings'!$O$10)))))) -> Reject | T27: Rejected | Y27: Direct LIMO/chauffeur and US-market must-haves are not evidenced. Relevant Industry Experience reflects logistics/dispatch/warehouse operations from Oct 2023 to present; older KPO/NSER roles are not counted as relevant industry experience. | AA27: 46291
A28: CAND-027 | B28: 001 | C28: Habab Bin Ayyaz | D28: +92 (323) 471-7225 | E28: hababbinayyaz@gmail.com | F28: Assistant Operations Manager | G28: Elite Chauffeured Service Inc. | H28: Lahore, Pakistan | I28: 4 | J28: 4 | K28: 46291 | L28: 9.5 | M28: 0.9 | N28: Pass | O28: 8.5 | P28: Direct US chauffeur/limo operations; current Assistant Operations Manager; prior Lead Dispatcher; trip assignment and execution; corporate accounts, travel agencies, DMCs, hotels and affiliate networks; Limo Anywhere, Moovs, GNet and Crewslink. | Q28: Leadership scope, team size, hiring/coaching responsibility, P&L ownership, affiliate rate/margin strategy, and oversight of marketing/SEO/development teams are not evidenced in the CV. | R28: High-alignment candidate with direct US limousine/chauffeur operations across Washington D.C. and New York, plus Canada dispatch exposure. Strong dispatch, affiliate-network and limo-platform evidence; broader GM-level commercial and people leadership should be validated. | S28: =IF($C28="","",IF(OR($M28="",$N28=""),'Lists & Settings'!$O$10,IF($N28="Fail",'Lists & Settings'!$O$9,IF($N28="Insufficient Evidence",'Lists & Settings'!$O$10,IF($N28="Pass",IF($M28>='Lists & Settings'!$N$2,'Lists & Settings'!$O$2,IF($M28>='Lists & Settings'!$N$3,'Lists & Settings'!$O$3,'Lists & Settings'!$O$4)),IF($N28="Partial",IF($M28>='Lists & Settings'!$N$6,'Lists & Settings'!$O$6,IF($M28>='Lists & Settings'!$N$7,'Lists & Settings'!$O$7,'Lists & Settings'!$O$8)),'Lists & Settings'!$O$10)))))) -> Priority Shortlist | T28: Shortlisted | Y28: Must-Have Fit = Pass. Approximately four years of direct luxury ground-transportation experience from 2022 to present, including US chauffeur operations and lead/assistant-management responsibilities. | AA28: 46291
A29: CAND-028 | B29: 002 | C29: Jaffir Iqbal | D29: +92302-9113015 | E29: jaffiriqbal@gmail.com | F29: Assistant Manager Production | G29: Cakes & Bakes Private Limited | H29: Tehsil Kabirwala, District Khanewal, Pakistan | I29: 9 | J29: 9 | K29: 46292 | L29: 8.8 | M29: 0.76 | N29: Pass | O29: 6.2 | P29: Multi-category food, sweets and bakery manufacturing experience: Directly supervised production of biscuits, croissants/cross products, plain cakes, jams, sauces, chocolate and frozen items at Cakes & Bakes. The employer is described as manufacturing snacks, bakery products, chocolate, chips, jam, ketchup and drinks. Additional food-sector experience includes PepsiCo and Bunny’s Limited. Relevant bachelor's degree: Completed BS in Food Science and Technology from Government College University Faisalabad, 2012–2016, with a 3.58/4.0 GPA. Also completed an M.Sc. (Honors) in Food Technology from the University of Agriculture Faisalabad. Minimum five years of production management experience: Assistant Manager Production at Cakes & Bakes from February 2019 to present. Responsibilities include maintaining production flow, meeting production plans, managing overall operations, delivering production targets, supervising multiple product processes, training workers and resolving production problems. | Q29: Dispatch, finished-goods inventory and expiry management: There is transferable inventory and order-fulfillment exposure, but direct responsibility for dispatch accuracy, customer deliveries, finished-goods warehousing, FEFO, shelf-life controls, near-expiry monitoring or returns is not evidenced. | R29: Candidate assessed against 9 live ATS criteria. Weighted ATS Match: 76%. Must-Have Fit: Pass. The result is based on the stored Ref # criteria, weights, knockout rules and documented CV evidence. | S29: Priority Shortlist | T29: Shortlisted | AA29: 46292.096
A30: CAND-029 | B30: 003 | C30: Jawad Ahmed | D30: +92 314-8002002 | E30: jawad4157@yahoo.com | F30: Manager – Export Sales and Marketing | G30: International Steels Limited | H30: Karachi, Sindh, Pakistan | I30: 16.6 | J30: 2 | K30: 46292 | L30: 9.3 | M30: 0.55 | N30: Fail | O30: 7.2 | P30: International market development and export strategy: Developed export strategies for Afghanistan, Sri Lanka, UAE, Oman, Qatar, Jordan and Australia; subsequently assumed responsibility for Saudi Arabia, Kuwait and regions across Africa. Conducted market research, secured entry into Saudi Arabia and Kuwait, facilitated SRIM certification for regulated-market access, converted more than 40 active leads into prospects, increased export revenue from USD 34 million to USD 41 million, and raised export contribution from 8% to 20%. Represented the company at international exhibitions, trade missions and business forums. Commercial negotiations, budgeting and international trade risk: Leads annual export budgeting, revenue forecasting and cost optimization against profit targets. Negotiates contracts, pricing models and payment structures, manages high-value accounts and reports export revenue growth from USD 34 million to USD 41 million. International client, distributor and service-provider relationship management: Manages international B2B and B2C key accounts, develops high-value client relationships, negotiates long-term agreements and reports strong retention and satisfaction. Works across multiple Asian, Middle Eastern, Australian and African markets and generated more than 40 active leads. | Q30: Export management experience and end-to-end ownership: The candidate demonstrates substantial commercial ownership and cross-functional coordination for international orders, but the CV evidences only two completed years of direct export management through July 2025, below the mandatory five-year threshold. It also does not explicitly demonstrate hands-on ownership of documentation, customs clearance, shipment and final delivery. Confectionery and perishable food export domain knowledge: The CV provides no usable evidence of confectionery or comparable perishable-food export knowledge. Steel export experience cannot be treated as direct food-domain experience. Trade compliance, food safety and export documentation: There is credible regulatory and certification exposure, but limited evidence of hands-on export-documentation or customs responsibility. No food-safety, food-labeling or destination-country food compliance experience is evidenced. | R30: Candidate assessed against 8 live ATS criteria. Weighted ATS Match: 55%. Must-Have Fit: Fail. The result is based on the stored Ref # criteria, weights, knockout rules and documented CV evidence. | S30: Reject | T30: Rejected | AA30: 46292.282
A31: CAND-030 | B31: 001 | C31: Muhammad Taskeen | D31: +92 300 6676139 / +92 333 6676139 | E31: muhammadtaskeen@gmai.com / muhammadtaskeen@outlool.com | F31: Security Supervisor | G31: Marine Security Service (Pvt) | H31: Faisalabad, Pakistan | I31: 27.4 | J31: 22.9 | K31: 46292 | L31: 8.9 | M31: 0.34 | N31: Fail | O31: 5.6 | P31: Dispatch / Fleet Operations: Managed daily vehicle movement, fleet availability, driver coordination and duty rosters, maintenance scheduling, fuel and mileage records, vehicle inspections, breakdowns, and transport-related incidents. Operations Management: Supervised daily transport operations, fleet availability, inspections, preventive maintenance, fuel consumption, vehicle records, incident investigations, roadworthiness, spare parts, and operational briefings in the Pakistan Air Force. Leadership & People Management: Served as a Warrant Officer and Mechanical Transport Supervisor; coordinated drivers, monitored attendance and duty rosters, conducted safety briefings and driver training, and completed leadership, command, and MT instructor courses. | Q31: Direct LIMO / Chauffeur Service Management: The VIP driving course and transport background are adjacent, but training and generic fleet management are not equivalent to directly managing a commercial limo or chauffeur operation. The mandatory direct-industry requirement is not met. US Market / US Customer Exposure: The CV only documents employment in Pakistan and provides no explicit international or US-facing operational experience. The mandatory US exposure requirement is not met. Client / Customer Management: Communication and interpersonal skills are listed, but there is no usable evidence of responsibility for customers or client accounts. | R31: Candidate assessed against 7 live ATS criteria. Weighted ATS Match: 34%. Must-Have Fit: Fail. The result is based on the stored Ref # criteria, weights, knockout rules and documented CV evidence. | S31: Reject | T31: Rejected | AA31: 46292.494
A32: CAND-031 | B32: 002 | C32: Husnain Raza Rahat | D32: 0304-0743974 | E32: husnainhadi899@gmail.com | F32: Assistant Manager (Production & Quality) | G32: Merit | H32: Mongi Bangla, Tehsil Gojra, District Toba Tek Singh, Pakistan | I32: 4 | J32: 4 | K32: 46293 | L32: 8.4 | M32: 0.59 | N32: Partial | O32: 5.5 | P32: Relevant bachelor's degree: BS (Hons) Food Science and Technology, Government College University Faisalabad, 2014–2018. Multi-category food, sweets and bakery manufacturing experience: Direct responsibility for multiple production lines covering bread, burgers, buns, rusk and other bakery products. Previous roles include Shift Incharge (Production) at Dawn Bread and Executive (Quality Assurance & Food Safety) in a food business. Skills include testing flour, milk, butter, oil, desi ghee and khoya, finished-goods testing and shelf-life studies. Quality control and health and safety compliance: Current responsibilities include daily and monthly quality and food-safety audits, daily quality-report review, regulatory-standard implementation, GMP and food-safety training, Halal Food Management System, IPM protocol, finished-product checks, preventive actions and complaints handling. Earlier role was Executive (Quality Assurance & Food Safety), 2018–2021. | Q32: Minimum five years of production management experience: The CV demonstrates direct factory-production responsibility, but it does not substantiate at least five years of production management. Only approximately one explicitly dated year is in a production leadership role, while the duration of the current assistant-manager position is not provided. Dispatch, finished-goods inventory and expiry management: The shelf-life and finished-product exposure is adjacent to the requirement, but direct dispatch and expiry-sensitive inventory ownership is not evidenced. Production systems, analytical reporting and decision support: A relevant ERP platform and routine reporting exposure are identified, but the CV does not explain hands-on SAP use for production planning, manufacturing transactions, analysis, MIS preparation or management decision support. | R32: Candidate assessed against 9 live ATS criteria. Weighted ATS Match: 59%. Must-Have Fit: Partial. The result is based on the stored Ref # criteria, weights, knockout rules and documented CV evidence. | S32: Hold | T32: Hold | AA32: 46292.969
A33: CAND-032 | B33: 004 | C33: Zeeshan Tarar | D33: 0345-4914004 | E33: zeeshan_tarar36@yahoo.com | F33: Assistant Manager Procurement | G33: Ajmair Foods | I33: 10 | J33: 6.3 | K33: 46296 | L33: 8.4 | M33: 0.52 | N33: Fail | O33: 6.2 | P33: Supplier sourcing, relationship management and market intelligence: Responsibilities include identifying, evaluating and managing suppliers; maintaining supplier relationships; resolving supplier issues; analyzing supplier performance, market trends and costs; competitive sourcing; and maintaining supplier data. At Thal/Almoiz, the candidate built supplier relationships and reported on supplier performance. Commercial negotiation, contracting and cost optimization: The CV describes negotiating supplier contracts, pricing, delivery terms, quality standards and payment terms; drafting, reviewing and managing contracts; securing favorable terms; developing cost-effective procurement strategies; and contributing to cost-saving initiatives. Procurement systems, reporting and audit-ready records: The candidate managed purchase-order creation, processing and tracking; prepared monthly and annual procurement reports; analyzed costs, volumes and supplier performance; maintained purchase and supplier records; used procurement software and tools; and completed ERP training. | Q33: Minimum experience and manufacturing-domain relevance: The candidate has substantial procurement and food/raw-material exposure, including more than six completed years in fruit procurement at a food company. However, the mandatory five years of production management are not evidenced, so the experience is relevant but does not satisfy the requirement as written. Inventory planning, replenishment and logistics coordination: Delivery and logistics coordination are directly evidenced, but the CV does not show responsibility for stock-level monitoring, reorder points, replenishment planning, shortage prevention or overstock control. Mandatory supply chain education: The CV does not evidence the specifically mandated bachelor's degree in Supply Chain Management. Procurement experience, ERP training and other short courses cannot substitute for the required degree. | R33: Candidate assessed against 8 live ATS criteria. Weighted ATS Match: 52%. Must-Have Fit: Fail. The result is based on the stored Ref # criteria, weights, knockout rules and documented CV evidence. | S33: Reject | T33: Rejected | Z33: https://drive.google.com/file/d/1kZbWCNdECoiACxOlAyOQNhp19dExclI2/view?usp=drivesdk | AA33: 46296.187
A34: CAND-033 | B34: 004 | C34: Abdul Ghaffar | D34: +92 305 4942108 | E34: agmohsinbutt5cwak_5hk@indeedemail.com | F34: Sr. Executive Supply Chain | G34: Quick Food Industries Pvt. Ltd. (MonSalwa) | H34: Lahore | I34: 15.1 | J34: 15.1 | K34: 46296 | L34: 8.1 | M34: 0.35 | N34: Fail | O34: 3.9 | P34: Cross-functional leadership and procurement decision-making: Describes handling all plant purchasing single-handedly, acting as supply-chain and procurement department in-charge, serving as a key person for production and maintenance, and coordinating with distribution, cold store and administration. Supplier sourcing, relationship management and market intelligence: States direct access to manufacturers and importers, knowledge of Lahore and Faisalabad markets, sourcing links to Karachi, direct-source purchasing of construction materials, and responsibility for supplier accounts and payment settlements. | Q34: Minimum experience and manufacturing-domain relevance: The candidate has extensive procurement experience in food and manufacturing environments, but the mandatory five years of production management experience is not evidenced. Coordination with production is transferable but is not production management. Commercial negotiation, contracting and cost optimization: The CV shows exposure to commercial transactions and payment arrangements but does not explicitly evidence price negotiation, contract ownership, bulk-purchase terms, cost analysis or quantified savings. Inventory planning, replenishment and logistics coordination: Logistics and cross-functional material coordination are evident, but stock monitoring, reorder-point management, shortage prevention, overstock control and supplier-delivery performance ownership are not specifically described. | R34: Candidate assessed against 8 live ATS criteria. Weighted ATS Match: 35%. Must-Have Fit: Fail. The result is based on the stored Ref # criteria, weights, knockout rules and documented CV evidence. | S34: Reject | T34: Rejected | Z34: https://drive.google.com/file/d/1dJQh0JBWSXzS5N9Hc8INE8K3LRJEgIpa/view?usp=drivesdk | AA34: 46296.187
A35: CAND-034 | B35: 004 | C35: Muhammad Zohaib Manzoor | D35: 0321-6883884 | E35: mzohaib330@yahoo.com | F35: Assistant Manager | G35: Cakes and Bakes (Ajmair Foods Pvt. Limited) | H35: Lahore, Pakistan | I35: 16.7 | J35: 6.6 | K35: 46294 | L35: 7.7 | M35: 0.49 | N35: Fail | O35: 5.8 | P35: Supplier sourcing, relationship management and market intelligence: Current responsibilities explicitly include supplier relationship management, researching and evaluating prospective suppliers, identifying potential new suppliers, supplier follow-up and introducing new products and services. At Millat Tractors, responsibilities included collecting quotations and negotiating with suppliers. Commercial negotiation, contracting and cost optimization: The CV explicitly lists supplier negotiation at Cakes and Bakes and collection of quotations and negotiations at Millat Tractors. It also notes comparative-statement preparation, price committee meetings and issuance of cash and credit purchase orders. Procurement systems, reporting and audit-ready records: The candidate issued purchase orders and created new purchase part numbers in IFS at Millat Tractors. Other documented system use includes IFS for production records, work orders, shop orders and inspection-related transactions. Reporting experience includes stock, production, maintenance and project reports, comparative statements, approval letters and CEP documentation. Microsoft Office and MS Project are also listed. | Q35: Minimum experience and manufacturing-domain relevance: The candidate has substantial procurement experience and direct bakery/food-production exposure, plus earlier manufacturing experience. This is relevant but does not meet the JD's explicit requirement for at least five years of production management. Inventory planning, replenishment and logistics coordination: There is credible delivery and material coordination experience, but no clear ownership of stock-level monitoring, reorder points, replenishment planning, shortage prevention or overstock controls. Mandatory supply chain education: The mandatory requirement specifically calls for a completed bachelor's degree in Supply Chain Management. The short course and procurement experience do not satisfy the stated degree-level and field requirement. | R35: Candidate assessed against 8 live ATS criteria. Weighted ATS Match: 49%. Must-Have Fit: Fail. The result is based on the stored Ref # criteria, weights, knockout rules and documented CV evidence. | S35: Reject | T35: Rejected | AA35: 46293.959
A36: CAND-035 | B36: 001 | C36: Umair Hassan Ghori | D36: 0332-2267345 | E36: tcsumair@gmail.com.pk | F36: Logistics Operations Manager | G36: PacknGo | H36: Karachi, Pakistan | I36: 14.7 | J36: 0 | K36: 46295 | L36: 8.8 | M36: 0.31 | N36: Fail | O36: 6.2 | P36: Operations Management: As Logistics Operations Manager, led end-to-end home and corporate relocation projects, including data-center relocations, shipment processing and final-mile delivery. Also coordinated cross-functional teams, resolved service issues and supported process and cost improvements. Earlier roles included KPI, SOP, quality and escalation responsibilities. Client / Customer Management: Managed corporate-client relationships, customer meetings, surveys, quotations and commercial discussions. Held several customer-care roles covering difficult complaints, claims, legal notices, service recovery, refunds and root-cause investigation. Leadership & People Management: Led cross-functional relocation teams and coordinated packing teams, skilled staff and vehicles. As Acting Contact Center Supervisor, managed floor operations, schedules and breaks and supported skill assessments and development plans. | Q36: Direct LIMO / Chauffeur Service Management: The candidate has transferable logistics experience but no direct management of chauffeur or limo services. Generic logistics and relocation operations do not satisfy this knockout requirement. US Market / US Customer Exposure: No explicit US market or customer exposure is provided, so this knockout requirement is not met. Dispatch / Fleet Operations: The experience is transferable to dispatch and fleet coordination, but it relates to freight, relocation and delivery operations. Driver dispatch, passenger routing, scheduling and chauffeur fleet utilization are not evidenced. | R36: Candidate assessed against 7 live ATS criteria. Weighted ATS Match: 31%. Must-Have Fit: Fail. The result is based on the stored Ref # criteria, weights, knockout rules and documented CV evidence. | S36: Reject | T36: Rejected | AA36: 46295.176
A37: CAND-036 | B37: 001 | C37: Bilal Mustafa | F37: Sales and Dispatch Operations Manager | G37: Nationwide Chauffeured Services | H37: Lahore, Punjab, Pakistan | I37: 9.8 | J37: 9.8 | K37: 46296 | L37: 8.7 | M37: 0.82 | N37: Pass | O37: 7.2 | P37: Direct LIMO / Chauffeur Service Management: Sales and Dispatch Manager and former Sales and Dispatch Supervisor at Nationwide Chauffeured Services; Operations Manager at Dallas Limo & Black Car Service. The CV explicitly references limousine service, regional-fleet dispatch, premium corporate service, VIP transportation and large-scale transport coordination. US Market / US Customer Exposure: Nationwide Chauffeured Services role is listed in the United States; Dallas Limo & Black Car Service role is located in Dallas, Texas; National Sales Manager role at Dlbcs Transportation is also listed in the United States. The candidate led services for corporate and event clients across multiple locations. Operations Management: Managed daily dispatch operations for a regional fleet, reports 100% on-time service to corporate clients, serves as Operations Manager at Dallas Limo & Black Car Service, and coordinated large-scale logistics and VIP transport during ICC World Cup operations. | Q37: Systems / Technology: Operational systems usage is not evidenced. | R37: Candidate assessed against 7 live ATS criteria. Weighted ATS Match: 82%. Must-Have Fit: Pass. The result is based on the stored Ref # criteria, weights, knockout rules and documented CV evidence. | S37: Priority Shortlist | T37: Shortlisted | Z37: https://drive.google.com/file/d/1JZ7e9F2afTCc94g7Gbul3yIF50xpNixG/view?usp=drivesdk | AA37: 46296.157
A38: CAND-037 | B38: 004 | C38: Malik Muhammad Touseef | D38: 0334 4145271 | E38: touseef_malik65@yahoo.com | F38: Admin & Supply Chain Officer | G38: The Diabetes Center | H38: Lahore, Pakistan | I38: 31.3 | J38: 11.5 | K38: 46296 | L38: 8.1 | M38: 0.34 | N38: Fail | O38: 4.2 | P38: Supplier sourcing, relationship management and market intelligence: Repeated responsibility for dealing with vendors and suppliers at Shezan Bakers, Palace Furniture and Sizzlers Restaurant. At Palace Furniture, the candidate sourced new items and markets and bought handicraft items from multiple Pakistani locations. General Food Products duties included exploring new dealers and customers. Inventory planning, replenishment and logistics coordination: Current duties include store inventory. At Shezan Bakers, duties included issuing raw materials to bakery departments, issuing packaging materials to sales outlets, checking stores and preparing statements. At Al Basha Restaurant, the candidate maintained food-store stock and prepared monthly stock reports. Palace Furniture included export documentation and shipment handling. | Q38: Minimum experience and manufacturing-domain relevance: The CV provides substantial bakery and food-sector procurement/store exposure, but it does not evidence the mandatory five years of production management. Store, purchase and factory-checking duties cannot be treated as production-management experience. Commercial negotiation, contracting and cost optimization: Purchasing exposure is adjacent evidence, but negotiation authority and commercial outcomes cannot be inferred from general buying and vendor-dealing duties. Mandatory supply chain education: The completed bachelor's degree is unrelated to supply chain management and therefore does not satisfy the explicitly mandatory degree field. | R38: Candidate assessed against 8 live ATS criteria. Weighted ATS Match: 34%. Must-Have Fit: Fail. The result is based on the stored Ref # criteria, weights, knockout rules and documented CV evidence. | S38: Reject | T38: Rejected | Z38: https://drive.google.com/file/d/1wJRPYV-TCXeLgeEHgnb75yBQtAxHpjBx/view?usp=drivesdk | AA38: 46296.187
A39: CAND-038 | B39: 002 | C39: Khan Hassam Zain | D39: +966540245762 | E39: khanhassamzain50@gmail.com | F39: Assistant Production Manager | G39: Kufa Food Company | H39: Dammam, Saudi Arabia; permanent address listed in Gujranwala, Pakistan | I39: 8.3 | J39: 8 | K39: 46296 | L39: 7.3 | M39: 0.68 | N39: Pass | O39: 5.7 | P39: Quality control and health and safety compliance: Responsible for GMP and GHP verification, product inspection, quality, food safety, hygiene and regulatory standards; conducts food-safety and Halal audits; evaluates findings and implements corrective and preventive actions; develops and updates SOPs; conducts site inspections covering GHP, GMP and IPM; investigates complaints and non-conformances; organizes compliance training. Holds Lead Auditor FSSC 22000 V5 and Lead Auditor HALAL PS3733:2019 certifications. Relevant bachelor's degree: B.Sc. (Hons) Agriculture, Food Technology, PMAS-Arid Agriculture University Rawalpindi, 2014–2018; M.Phil. Food Science & Technology, University of Management & Technology Lahore, 2019–2021. Minimum five years of production management experience: Assistant Production Manager at Kufa Food Company from March 2022 to present; three years as Production Manager at Hafiz Sweets; two years as Production Executive at Gourmet Foods' bakery plant. Current responsibilities include shift planning, production-process supervision, plant staffing and production handover through a system. | Q39: Process improvement, waste reduction and production cost control: CAPA and SOP work provide limited adjacent evidence, but routine compliance activity cannot establish production-process improvement or cost ownership. No initiatives or quantified results are documented. Dispatch, finished-goods inventory and expiry management: Shelf-life and product-control exposure is relevant to expiry-sensitive food production, but direct responsibility for finished-goods stock and customer dispatch is not evidenced. Production systems, analytical reporting and decision support: Some operational system use is evidenced, but the system and level of hands-on use are unspecified. Analytical reporting, production MIS, performance analysis and decision-support outputs are not demonstrated. | R39: Candidate assessed against 9 live ATS criteria. Weighted ATS Match: 68%. Must-Have Fit: Pass. The result is based on the stored Ref # criteria, weights, knockout rules and documented CV evidence. | S39: Shortlist | T39: Shortlisted | Z39: https://drive.google.com/file/d/1ei0w2ebZzN31AnU7iYO3Kltjdg_RU6YA/view?usp=drivesdk | AA39: 46296.214
A40: CAND-039 | B40: 004 | C40: Farooq Haider | D40: +92-305-5997857; +92-316-5997857 | E40: farooqhaiderft@gmail.com | F40: Production Manager | G40: ATA Bakery Solutions (Pvt.) Ltd. (Bread and Beyond) | H40: Lahore, Pakistan | I40: 15 | J40: 15 | K40: 46296 | L40: 7.6 | M40: 0.44 | N40: Fail | O40: 3.4 | P40: Minimum experience and manufacturing-domain relevance: Continuous food-manufacturing career since July 2009, including Senior Production Officer at Continental Biscuit (2010–2013), Assistant Manager Production at Asian Foods/Mayfair (2013–2017), Operations Manager at Backersland (2017–2018), Manager Production at S.M Group companies (2018–2020), Plant Manager at The Snack Bites Company (2020–2022), and Production Manager at ATA Bakery Solutions from February 2022. Products include biscuits, cookies, crackers, cakes, bread, wafers, confectionery and snacks. Raw-material quality and food-safety compliance: At Gourmet Foods, inspected raw materials in the laboratory against established standards and handled QA/QC and hygiene compliance. At S.M Group, worked with purchasing staff to establish supplier safety, quality and legal requirements and was responsible for ISO, HACCP 22000:2005, Halal, hygiene and EHS implementation. Food-safety training includes CIEH Level 2, traceability, pest management and halal food production. | Q40: Supplier sourcing, relationship management and market intelligence: There is credible cross-functional interaction with purchasing and external suppliers, but evidence of direct end-to-end sourcing and supplier relationship ownership is incomplete. Commercial negotiation, contracting and cost optimization: The CV shows operational cost optimization, but this is adjacent to rather than direct evidence of procurement negotiation and contracting. Inventory planning, replenishment and logistics coordination: Manufacturing material-control experience is transferable, but the CV does not demonstrate direct replenishment or supplier-linked inventory planning. | R40: Candidate assessed against 8 live ATS criteria. Weighted ATS Match: 44%. Must-Have Fit: Fail. The result is based on the stored Ref # criteria, weights, knockout rules and documented CV evidence. | S40: Reject | T40: Rejected | Z40: https://drive.google.com/file/d/1o73RNoNdiRsx1EDA45sse7xd7FcStyad/view?usp=drivesdk | AA40: 46296.227
A41: CAND-031 | B41: 004 | C41: Husnain Raza Rahat | D41: 0304-0743974 | E41: husnainhadi899@gmail.com | F41: Assistant Manager (Production & Quality) | G41: Merit | H41: Mongi Bangla, Tehsil Gojra, District Toba Tek Singh, Pakistan | I41: 4 | J41: 4 | K41: 46296 | L41: 8.5 | M41: 0.2 | N41: Fail | O41: 1.8 | P41: No material strength was evidenced strongly enough to summarize. | Q41: Minimum experience and manufacturing-domain relevance: The candidate has directly relevant bakery and food-manufacturing exposure, but the CV does not establish at least five clearly dated years of production management. Only the 2021–2022 production role is explicitly dated as production management, while the current production and quality role lacks dates. Supplier sourcing, relationship management and market intelligence: Food-manufacturing and quality responsibilities are documented, but there is no usable evidence of supplier sourcing or strategic supplier management. Commercial negotiation, contracting and cost optimization: Waste reduction and production efficiency are adjacent to cost control, but they do not demonstrate procurement negotiation, contracting authority or commercial purchasing outcomes. | R41: Candidate assessed against 8 live ATS criteria. Weighted ATS Match: 20%. Must-Have Fit: Fail. The result is based on the stored Ref # criteria, weights, knockout rules and documented CV evidence. | S41: Reject | T41: Rejected | Z41: https://drive.google.com/file/d/1pQilDW7AzbuKklxsZ46MCAmYuTeaECVf/view?usp=drivesdk | AA41: 46296.228
A42: CAND-040 | B42: 004 | C42: Muhammad Waqas Naeem | D42: +923225908112 | E42: mwn.1583@gmail.com | F42: Production Manager | G42: Dawn Bread | H42: Lahore, Pakistan | K42: 46296 | L42: 8 | M42: 0.35 | N42: Fail | O42: 2.1 | P42: Minimum experience and manufacturing-domain relevance: Production Manager at Dawn Bread from 19 August 2019 to present; Production Supervisor with additional Quality Controller and Internal Auditor responsibilities at Al Jadeed Bakery from 26 March 2017 to 25 April 2019; Assistant Manager Production at Bunny's Limited from 1 January 2013 to 24 March 2017. The CV describes high-volume production of breads, buns, Arabic bread, cakes, biscuits, croissants and other bakery products and states more than 11 years of bakery/FMCG experience. | Q42: Supplier sourcing, relationship management and market intelligence: The documented career is focused on bakery production, process efficiency and quality. No direct sourcing or strategic supplier-management responsibilities are provided. Commercial negotiation, contracting and cost optimization: The candidate has adjacent operational cost-control exposure, but the CV does not establish procurement negotiation, contracting or commercial ownership. Inventory planning, replenishment and logistics coordination: Production planning is transferable, but it is not evidence of procurement inventory ownership or supplier-linked replenishment responsibility. | R42: Candidate assessed against 8 live ATS criteria. Weighted ATS Match: 35%. Must-Have Fit: Fail. The result is based on the stored Ref # criteria, weights, knockout rules and documented CV evidence. | S42: Reject | T42: Rejected | Z42: https://docs.google.com/document/d/1sv4_R7dWzqdEA8LNI1_9Il8oxPslXsCy/edit?usp=drivesdk&ouid=100269677063860344655&rtpof=true&sd=true | AA42: 46296.228
A43: CAND-041 | B43: 002 | C43: Muhammad Amir Sohail | D43: +92 303 6495591 | E43: amirsohailofficial5@gmail.com | F43: Assistant Manager Production and Quality (Export) | G43: Bundu Khan Foods | H43: Khanewal, Pakistan; currently employed in Lahore | K43: 46296 | L43: 9.1 | M43: 0.62 | N43: Partial | O43: 6.2 | P43: Relevant bachelor's degree: Completed B.Sc. (Hons.) Food Engineering at the University of Agriculture, Faisalabad, from 09/2014 to 08/2018, with CGPA 3.17. Also completed M.Sc. (Hons.) Food Science and Technology at the University of Poonch Rawalakot AJK from 09/2018 to 06/2022, with grade 3.66. Multi-category food, sweets and bakery manufacturing experience: Direct experience at Freshco Sweet and Bakers and Gourmet Foods. Product exposure includes sweets and bakery operations, fondant/icing sugar paste, mayonnaise, sauces, frozen bakery products and bakery products developed for export to the UK. The candidate also worked on shelf-life enhancement and new-product launches. Quality control and health and safety compliance: Current responsibilities include quality-control implementation, inspections and compliance with HACCP and ISO 22000 expectations. Gourmet Foods responsibilities include food-safety checklists, ISO 9001 compliance, work instructions and raw/packing-material inspection. Freshco experience includes GMPs, safety protocols and worker food-safety training. The Shezan internship covered FSSC 22000 audits, SOPs, QA check sheets, hazard identification and corrective measures. | Q43: Minimum five years of production management experience: The CV documents continuous food-production experience beginning in August 2020, but the ongoing role has no fixed end or CV assessment date. Approximately four years are established through the start of the current role, while management-titled experience from June 2021 through July 2024 is about 3.1 years plus an unquantifiable current period. Therefore, five full years of production-management ownership are not substantiated. Dispatch, finished-goods inventory and expiry management: The CV demonstrates finished-goods inventory exposure and coordination with shipping, but not full ownership of dispatch accuracy or timeliness. FEFO, batch-based expiry monitoring, near-expiry controls, returns and quantified stock-loss or wastage outcomes are not evidenced. | R43: Candidate assessed against 9 live ATS criteria. Weighted ATS Match: 62%. Must-Have Fit: Partial. The result is based on the stored Ref # criteria, weights, knockout rules and documented CV evidence. | S43: Hold | T43: Hold | Z43: https://drive.google.com/file/d/1iaS_IPREJRtxZES0zWkP7uXRkoZ8kn_t/view?usp=drivesdk | AA43: 46296.471 | AB43: [{"criterion":"Minimum five years of production management experience","evidenceStatus":"Partial","evidenceFound":"Production Executive at Freshco Sweet and Bakers from 08/2020 to 06/2021; Assistant Manager Production and R&D at Gourmet Foods from 06/2021 to 07/2024; Assistant Manager Production and Quality (Export) at Bundu Khan Foods from 08/2024 to Current. Responsibilities include production planning, production-team leadership, task assignment, workflow execution, resource coordination and production records.","knockout":"Yes","weight":20,"evidenceConfidence10":10,"score10":4,"assessmentRationale":"The CV documents continuous food-production experience beginning in August 2020, but the ongoing role has no fixed end or CV assessment date. Approximately four years are established through the start of the current role, while management-titled experience from June 2021 through July 2024 is about 3.1 years plus an unquantifiable current period. Therefore, five full years of production-management ownership are not substantiated."},{"criterion":"Multi-category food, sweets and bakery manufacturing experience","knockout":"Yes","evidenceFound":"Direct experience at Freshco Sweet and Bakers and Gourmet Foods. Product exposure includes sweets and bakery operations, fondant/icing sugar paste, mayonnaise, sauces, frozen bakery products and bakery products developed for export to the UK. The candidate also worked on shelf-life enhancement and new-product launches.","weight":15,"evidenceConfidence10":10,"evidenceStatus":"Pass","score10":8,"assessmentRationale":"Strong factory-based food and bakery experience across several recipe-based and perishable categories is explicit. Multiple product categories are demonstrated, although the scale and number of separately managed production lines or departments are not stated."},{"criterion":"Production planning, daily reporting and target delivery","score10":6,"evidenceFound":"At Bundu Khan Foods, assists with production planning and scheduling for export orders and deadlines and maintains production records. At Gourmet Foods, led production operations, production-plan execution and resource coordination. At Freshco, planned production based on demand and tracked production numbers.","assessmentRationale":"There is credible direct evidence of demand-based planning, scheduling, workflow execution and output recording. However, final accountability for targets, formal DPR preparation, variance analysis, capacity analysis and measurable schedule or throughput results are not evidenced.","evidenceConfidence10":8,"evidenceStatus":"Pass","knockout":"Yes","weight":14},{"evidenceConfidence10":8,"assessmentRationale":"The CV demonstrates finished-goods inventory exposure and coordination with shipping, but not full ownership of dispatch accuracy or timeliness. FEFO, batch-based expiry monitoring, near-expiry controls, returns and quantified stock-loss or wastage outcomes are not evidenced.","weight":10,"score10":4,"criterion":"Dispatch, finished-goods inventory and expiry management","knockout":"No","evidenceStatus":"Partial","evidenceFound":"Managed production-store stock at Gourmet Foods, including weekly, monthly and annual closing for finished and semi-finished goods. At Freshco, labeled finished and semi-finished goods and handed finished products to the shipping department. Shelf-life improvement work is also stated."},{"assessmentRationale":"Strong and detailed evidence covers operational quality checks, hygiene, food safety, SOPs, audits, inspections and corrective measures in food-manufacturing environments. Quantified defect, complaint or safety-incident improvements and formal certification credentials are not provided.","criterion":"Quality control and health and safety compliance","weight":15,"evidenceFound":"Current responsibilities include quality-control implementation, inspections and compliance with HACCP and ISO 22000 expectations. Gourmet Foods responsibilities include food-safety checklists, ISO 9001 compliance, work instructions and raw/packing-material inspection. Freshco experience includes GMPs, safety protocols and worker food-safety training. The Shezan internship covered FSSC 22000 audits, SOPs, QA check sheets, hazard identification and corrective measures.","evidenceConfidence10":10,"evidenceStatus":"Pass","score10":8,"knockout":"No"},{"evidenceFound":"Identifies and implements process improvements at Bundu Khan Foods. At Gourmet Foods, handled material and overhead-cost estimation, system implementation, recipe costing, ingredient pricing, cost analysis and overhead control. At Freshco, managed waste. Shelf-life enhancement and new-product development are also documented.","evidenceStatus":"Pass","criterion":"Process improvement, waste reduction and production cost control","assessmentRationale":"The candidate has credible involvement in process improvement, waste management and production-cost analysis. Evidence is not quantified, and the CV does not establish production-budget ownership or measured improvements in yield, throughput, waste, downtime or labor utilization.","evidenceConfidence10":8,"weight":10,"score10":6,"knockout":"No"},{"score10":6,"evidenceConfidence10":8,"evidenceStatus":"Pass","evidenceFound":"Supervises and trains production and quality-control staff at Bundu Khan Foods. At Gourmet Foods, assigned tasks to subordinate officers and laborers, led the production team and addressed employee concerns and complaints. At Freshco, trained and guided workers on food safety.","weight":5,"assessmentRationale":"Direct factory-workforce supervision, task assignment, training and employee-issue handling are evidenced. Team size, shift structure, number of departments, formal performance management and measurable workforce results are not stated.","knockout":"No","criterion":"Factory labor management and team leadership"},{"score10":10,"evidenceFound":"Completed B.Sc. (Hons.) Food Engineering at the University of Agriculture, Faisalabad, from 09/2014 to 08/2018, with CGPA 3.17. Also completed M.Sc. (Hons.) Food Science and Technology at the University of Poonch Rawalakot AJK from 09/2018 to 06/2022, with grade 3.66.","assessmentRationale":"The candidate has an explicitly completed, directly relevant bachelor's degree and an additional relevant master's degree from identified institutions.","evidenceStatus":"Pass","knockout":"Yes","evidenceConfidence10":10,"criterion":"Relevant bachelor's degree","weight":5},{"knockout":"No","assessmentRationale":"There is credible contextual use of enterprise software and production data for costing, inventory and operational records. The CV does not identify a specific ERP platform or demonstrate advanced spreadsheet analysis, dashboards, production MIS, variance reporting or decision-support outputs.","weight":6,"evidenceStatus":"Pass","evidenceConfidence10":8,"score10":6,"evidenceFound":"Digital skills include ERP software and Microsoft Office. At Gourmet Foods, the candidate implemented material and overhead-cost estimates in NRP, performed recipe costing, ingredient pricing, stock closings, cost analysis and overhead control. Production records and production numbers were maintained in other roles.","criterion":"Production systems, analytical reporting and decision support"}]
A44: CAND-042 | B44: 004 | C44: Abbas Raza Shafqat | D44: +92 3202270704 | E44: abbasrazashafqat@gmail.com | F44: Procurement Coordinator | G44: Action International Services L.L.C | H44: Lahore, Punjab, Pakistan | I44: 4.2 | J44: 3.6 | K44: 46297 | L44: 9.3 | M44: 0.6 | N44: Fail | O44: 7.4 | P44: Supplier sourcing, relationship management and market intelligence: At Action International Services, sourced materials from local and international markets, identified potential suppliers, evaluated price, quality, service, payment and delivery factors, managed supplier relationships and performance, requested quotations and compared transportation costs. At Hammé, researched suppliers and compared offers. At Cool Point, sought capable suppliers and assessed their quality and business suitability. Commercial negotiation, contracting and cost optimization: Negotiated price, quality/service, payment terms and delivery with suppliers at Action International Services and reported contract negotiation and cost-reduction responsibilities. At Hammé, negotiated contract terms and pricing. At Cool Point, implemented cost-optimization techniques across commodities and brands. Inventory planning, replenishment and logistics coordination: At Action International Services, prepared purchase orders using stock levels, shortages, forecasts and consumption needs; managed monthly demand forecasts; placed supplier orders; monitored stock movement and minimum levels; followed deliveries; planned logistics; and obtained transportation quotations. At Hammé, monitored stock, placed orders, maintained ERP/Excel inventory, applied FIFO, managed slow-moving inventory and coordinated materials for production. | Q44: Minimum experience and manufacturing-domain relevance: The CV does not evidence five years of production management. Direct production-management exposure is limited to a short Operations Manager role, while most relevant experience is in procurement, warehousing or supply-chain coordination. No sweets, bakery or clearly evidenced food-processing manufacturing experience is shown. Mandatory supply chain education: The candidate has a completed bachelor's degree with a Supply Chain Management specialization, providing closely related academic preparation. However, the degree itself is titled BBA Honours rather than a bachelor's degree specifically titled Supply Chain Management, so it does not meet the exact mandatory wording without recruiter approval. | R44: Candidate assessed against 8 live ATS criteria. Weighted ATS Match: 60%. Must-Have Fit: Fail. The result is based on the stored Ref # criteria, weights, knockout rules and documented CV evidence. | S44: Reject | T44: Rejected | Z44: https://drive.google.com/file/d/1Vp65sxiaKs7p1W4FcfYVa6xEN6bTr1k4/view?usp=drivesdk | AA44: 46296.526 | AB44: [{"criterion":"Mandatory supply chain education","assessmentRationale":"The candidate has a completed bachelor's degree with a Supply Chain Management specialization, providing closely related academic preparation. However, the degree itself is titled BBA Honours rather than a bachelor's degree specifically titled Supply Chain Management, so it does not meet the exact mandatory wording without recruiter approval.","evidenceConfidence10":10,"evidenceStatus":"Partial","knockout":"Yes","evidenceFound":"Completed Bachelor of Business Administration Honours (BBA Hons) at The University of Lahore from 25/08/2015 to 17/02/2020, with an explicitly stated specialization in Supply Chain Management.","score10":4,"weight":10},{"assessmentRationale":"The CV does not evidence five years of production management. Direct production-management exposure is limited to a short Operations Manager role, while most relevant experience is in procurement, warehousing or supply-chain coordination. No sweets, bakery or clearly evidenced food-processing manufacturing experience is shown.","evidenceFound":"Dated experience includes approximately five months as Operations Manager at manufacturing company Organo Pure, around three months as a Supply Chain Management Intern at Cool Point, around five months in warehouse/supply chain at Hammé, and approximately 2.5 years in construction procurement at Action International Services. The Operations Manager role included production KPI monitoring, quality controls, purchasing, inventory planning and warehouse oversight.","evidenceStatus":"Fail","knockout":"Yes","score10":2,"evidenceConfidence10":10,"criterion":"Minimum experience and manufacturing-domain relevance","weight":20},{"knockout":"No","evidenceFound":"At Action International Services, sourced materials from local and international markets, identified potential suppliers, evaluated price, quality, service, payment and delivery factors, managed supplier relationships and performance, requested quotations and compared transportation costs. At Hammé, researched suppliers and compared offers. At Cool Point, sought capable suppliers and assessed their quality and business suitability.","weight":18,"evidenceStatus":"Pass","assessmentRationale":"Strong direct evidence covers supplier identification, quotation comparison, evaluation, relationship management, performance monitoring and alternative-source development. The CV does not provide quantified supplier-performance or market-price improvements, preventing an exceptional score.","evidenceConfidence10":10,"score10":8,"criterion":"Supplier sourcing, relationship management and market intelligence"},{"evidenceFound":"Negotiated price, quality/service, payment terms and delivery with suppliers at Action International Services and reported contract negotiation and cost-reduction responsibilities. At Hammé, negotiated contract terms and pricing. At Cool Point, implemented cost-optimization techniques across commodities and brands.","assessmentRationale":"The candidate demonstrates direct involvement in supplier negotiations, commercial terms, contracts and cost optimization. No savings figures, percentages, bulk-purchase outcomes or specific long-term contract results are provided.","knockout":"No","score10":8,"evidenceConfidence10":8,"evidenceStatus":"Pass","weight":15,"criterion":"Commercial negotiation, contracting and cost optimization"},{"assessmentRationale":"Strong evidence demonstrates regular ownership of replenishment, forecasting, ordering, stock availability, delivery follow-up and logistics coordination. No quantified reduction in stockouts, inventory, lead time or freight cost is stated.","criterion":"Inventory planning, replenishment and logistics coordination","evidenceFound":"At Action International Services, prepared purchase orders using stock levels, shortages, forecasts and consumption needs; managed monthly demand forecasts; placed supplier orders; monitored stock movement and minimum levels; followed deliveries; planned logistics; and obtained transportation quotations. At Hammé, monitored stock, placed orders, maintained ERP/Excel inventory, applied FIFO, managed slow-moving inventory and coordinated materials for production.","knockout":"No","evidenceConfidence10":10,"evidenceStatus":"Pass","weight":15,"score10":8},{"knockout":"No","assessmentRationale":"The CV provides credible procurement-related quality-control and supplier-compliance experience, including certificates, audits and corrective actions. However, this evidence is from construction and non-food manufacturing, with no explicit food-safety, bakery raw-material or sustainable-sourcing experience.","evidenceStatus":"Pass","evidenceConfidence10":8,"weight":10,"score10":6,"evidenceFound":"At Action International Services, handled quality and quantity discrepancies, requested samples and quality-test certificates, and followed shipping documentation. At Cool Point, assessed suppliers against quality standards, supported supplier audits, ensured quality-management-system and regulatory compliance, and applied root-cause and corrective/preventive actions to supplier-process issues.","criterion":"Raw-material quality and food-safety compliance"},{"evidenceStatus":"Pass","weight":7,"criterion":"Procurement systems, reporting and audit-ready records","evidenceConfidence10":8,"knockout":"No","evidenceFound":"Prepared purchase orders, maintained product, contract, pricing and invoicing data, tracked supply-chain KPIs and consolidated reports at Action International Services. Used Excel/ERP for inventory transactions and records at Hammé, prepared inventory lists and assisted internal stock counts and quarterly external audits. SAP MM, Microsoft Excel and SPSS are listed as digital skills.","score10":6,"assessmentRationale":"There is credible operational use of Excel and an unnamed ERP, along with purchasing, inventory, KPI and audit documentation. SAP MM is listed but its use in a specific role is not described, and there is limited evidence of advanced procurement-system ownership."},{"criterion":"Cross-functional leadership and procurement decision-making","weight":5,"evidenceFound":"At Action International Services, independently coordinated suppliers, customers and multiple departments, managed competing priorities and resolved quality, quantity, pricing, production and documentation delays. At Cool Point, worked with buying, product development, warehouse, manufacturing and project-management teams. As Operations Manager, recruited, trained and supervised staff and managed operational objectives.","score10":6,"evidenceConfidence10":8,"evidenceStatus":"Pass","knockout":"No","assessmentRationale":"The candidate demonstrates independent cross-functional coordination, supply-problem resolution and some formal staff leadership. The CV does not provide clear outcomes from major procurement decisions or sustained leadership of complex cross-functional procurement initiatives."}]
S45: =IF($C45="","",IF(OR($M45="",$N45=""),'Lists & Settings'!$O$10,IF($N45="Fail",'Lists & Settings'!$O$9,IF($N45="Insufficient Evidence",'Lists & Settings'!$O$10,IF($N45="Pass",IF($M45>='Lists & Settings'!$N$2,'Lists & Settings'!$O$2,IF($M45>='Lists & Settings'!$N$3,'Lists & Settings'!$O$3,'Lists & Settings'!$O$4)),IF($N45="Partial",IF($M45>='Lists & Settings'!$N$6,'Lists & Settings'!$O$6,IF($M45>='Lists & Settings'!$N$7,'Lists & Settings'!$O$7,'Lists & Settings'!$O$8)),'Lists & Settings'!$O$10))))))
S46: =IF($C46="","",IF(OR($M46="",$N46=""),'Lists & Settings'!$O$10,IF($N46="Fail",'Lists & Settings'!$O$9,IF($N46="Insufficient Evidence",'Lists & Settings'!$O$10,IF($N46="Pass",IF($M46>='Lists & Settings'!$N$2,'Lists & Settings'!$O$2,IF($M46>='Lists & Settings'!$N$3,'Lists & Settings'!$O$3,'Lists & Settings'!$O$4)),IF($N46="Partial",IF($M46>='Lists & Settings'!$N$6,'Lists & Settings'!$O$6,IF($M46>='Lists & Settings'!$N$7,'Lists & Settings'!$O$7,'Lists & Settings'!$O$8)),'Lists & Settings'!$O$10))))))
S47: =IF($C47="","",IF(OR($M47="",$N47=""),'Lists & Settings'!$O$10,IF($N47="Fail",'Lists & Settings'!$O$9,IF($N47="Insufficient Evidence",'Lists & Settings'!$O$10,IF($N47="Pass",IF($M47>='Lists & Settings'!$N$2,'Lists & Settings'!$O$2,IF($M47>='Lists & Settings'!$N$3,'Lists & Settings'!$O$3,'Lists & Settings'!$O$4)),IF($N47="Partial",IF($M47>='Lists & Settings'!$N$6,'Lists & Settings'!$O$6,IF($M47>='Lists & Settings'!$N$7,'Lists & Settings'!$O$7,'Lists & Settings'!$O$8)),'Lists & Settings'!$O$10))))))
S48: =IF($C48="","",IF(OR($M48="",$N48=""),'Lists & Settings'!$O$10,IF($N48="Fail",'Lists & Settings'!$O$9,IF($N48="Insufficient Evidence",'Lists & Settings'!$O$10,IF($N48="Pass",IF($M48>='Lists & Settings'!$N$2,'Lists & Settings'!$O$2,IF($M48>='Lists & Settings'!$N$3,'Lists & Settings'!$O$3,'Lists & Settings'!$O$4)),IF($N48="Partial",IF($M48>='Lists & Settings'!$N$6,'Lists & Settings'!$O$6,IF($M48>='Lists & Settings'!$N$7,'Lists & Settings'!$O$7,'Lists & Settings'!$O$8)),'Lists & Settings'!$O$10))))))
S49: =IF($C49="","",IF(OR($M49="",$N49=""),'Lists & Settings'!$O$10,IF($N49="Fail",'Lists & Settings'!$O$9,IF($N49="Insufficient Evidence",'Lists & Settings'!$O$10,IF($N49="Pass",IF($M49>='Lists & Settings'!$N$2,'Lists & Settings'!$O$2,IF($M49>='Lists & Settings'!$N$3,'Lists & Settings'!$O$3,'Lists & Settings'!$O$4)),IF($N49="Partial",IF($M49>='Lists & Settings'!$N$6,'Lists & Settings'!$O$6,IF($M49>='Lists & Settings'!$N$7,'Lists & Settings'!$O$7,'Lists & Settings'!$O$8)),'Lists & Settings'!$O$10))))))
S50: =IF($C50="","",IF(OR($M50="",$N50=""),'Lists & Settings'!$O$10,IF($N50="Fail",'Lists & Settings'!$O$9,IF($N50="Insufficient Evidence",'Lists & Settings'!$O$10,IF($N50="Pass",IF($M50>='Lists & Settings'!$N$2,'Lists & Settings'!$O$2,IF($M50>='Lists & Settings'!$N$3,'Lists & Settings'!$O$3,'Lists & Settings'!$O$4)),IF($N50="Partial",IF($M50>='Lists & Settings'!$N$6,'Lists & Settings'!$O$6,IF($M50>='Lists & Settings'!$N$7,'Lists & Settings'!$O$7,'Lists & Settings'!$O$8)),'Lists & Settings'!$O$10))))))
S51: =IF($C51="","",IF(OR($M51="",$N51=""),'Lists & Settings'!$O$10,IF($N51="Fail",'Lists & Settings'!$O$9,IF($N51="Insufficient Evidence",'Lists & Settings'!$O$10,IF($N51="Pass",IF($M51>='Lists & Settings'!$N$2,'Lists & Settings'!$O$2,IF($M51>='Lists & Settings'!$N$3,'Lists & Settings'!$O$3,'Lists & Settings'!$O$4)),IF($N51="Partial",IF($M51>='Lists & Settings'!$N$6,'Lists & Settings'!$O$6,IF($M51>='Lists & Settings'!$N$7,'Lists & Settings'!$O$7,'Lists & Settings'!$O$8)),'Lists & Settings'!$O$10))))))
S52: =IF($C52="","",IF(OR($M52="",$N52=""),'Lists & Settings'!$O$10,IF($N52="Fail",'Lists & Settings'!$O$9,IF($N52="Insufficient Evidence",'Lists & Settings'!$O$10,IF($N52="Pass",IF($M52>='Lists & Settings'!$N$2,'Lists & Settings'!$O$2,IF($M52>='Lists & Settings'!$N$3,'Lists & Settings'!$O$3,'Lists & Settings'!$O$4)),IF($N52="Partial",IF($M52>='Lists & Settings'!$N$6,'Lists & Settings'!$O$6,IF($M52>='Lists & Settings'!$N$7,'Lists & Settings'!$O$7,'Lists & Settings'!$O$8)),'Lists & Settings'!$O$10))))))
S53: =IF($C53="","",IF(OR($M53="",$N53=""),'Lists & Settings'!$O$10,IF($N53="Fail",'Lists & Settings'!$O$9,IF($N53="Insufficient Evidence",'Lists & Settings'!$O$10,IF($N53="Pass",IF($M53>='Lists & Settings'!$N$2,'Lists & Settings'!$O$2,IF($M53>='Lists & Settings'!$N$3,'Lists & Settings'!$O$3,'Lists & Settings'!$O$4)),IF($N53="Partial",IF($M53>='Lists & Settings'!$N$6,'Lists & Settings'!$O$6,IF($M53>='Lists & Settings'!$N$7,'Lists & Settings'!$O$7,'Lists & Settings'!$O$8)),'Lists & Settings'!$O$10))))))
S54: =IF($C54="","",IF(OR($M54="",$N54=""),'Lists & Settings'!$O$10,IF($N54="Fail",'Lists & Settings'!$O$9,IF($N54="Insufficient Evidence",'Lists & Settings'!$O$10,IF($N54="Pass",IF($M54>='Lists & Settings'!$N$2,'Lists & Settings'!$O$2,IF($M54>='Lists & Settings'!$N$3,'Lists & Settings'!$O$3,'Lists & Settings'!$O$4)),IF($N54="Partial",IF($M54>='Lists & Settings'!$N$6,'Lists & Settings'!$O$6,IF($M54>='Lists & Settings'!$N$7,'Lists & Settings'!$O$7,'Lists & Settings'!$O$8)),'Lists & Settings'!$O$10))))))
S55: =IF($C55="","",IF(OR($M55="",$N55=""),'Lists & Settings'!$O$10,IF($N55="Fail",'Lists & Settings'!$O$9,IF($N55="Insufficient Evidence",'Lists & Settings'!$O$10,IF($N55="Pass",IF($M55>='Lists & Settings'!$N$2,'Lists & Settings'!$O$2,IF($M55>='Lists & Settings'!$N$3,'Lists & Settings'!$O$3,'Lists & Settings'!$O$4)),IF($N55="Partial",IF($M55>='Lists & Settings'!$N$6,'Lists & Settings'!$O$6,IF($M55>='Lists & Settings'!$N$7,'Lists & Settings'!$O$7,'Lists & Settings'!$O$8)),'Lists & Settings'!$O$10))))))
S56: =IF($C56="","",IF(OR($M56="",$N56=""),'Lists & Settings'!$O$10,IF($N56="Fail",'Lists & Settings'!$O$9,IF($N56="Insufficient Evidence",'Lists & Settings'!$O$10,IF($N56="Pass",IF($M56>='Lists & Settings'!$N$2,'Lists & Settings'!$O$2,IF($M56>='Lists & Settings'!$N$3,'Lists & Settings'!$O$3,'Lists & Settings'!$O$4)),IF($N56="Partial",IF($M56>='Lists & Settings'!$N$6,'Lists & Settings'!$O$6,IF($M56>='Lists & Settings'!$N$7,'Lists & Settings'!$O$7,'Lists & Settings'!$O$8)),'Lists & Settings'!$O$10))))))
... S2000: =IF($C2000="","",IF(OR($M2000="",$N2000=""),'Lists & Settings'!$O$10,IF($N2000="Fail",'Lists & Settings'!$O$9,IF($N2000="Insufficient Evidence",'Lists & Settings'!$O$10,IF($N2000="Pass",IF($M2000>='Lists & Settings'!$N$2,'Lists & Settings'!$O$2,IF($M2000>='Lists & Settings'!$N$3,'Lists & Settings'!$O$3,'Lists & Settings'!$O$4)),IF($N2000="Partial",IF($M2000>='Lists & Settings'!$N$6,'Lists & Settings'!$O$6,IF($M2000>='Lists & Settings'!$N$7,'Lists & Settings'!$O$7,'Lists & Settings'!$O$8)),'Lists & Settings'!$O$10))))))

Sheet JD Criteria
A1: Ref # | B1: Criterion | C1: Weight % | D1: Knockout? | E1: Evidence Expected | F1: Scoring Guidance | G1: Notes
A2: 001 | B2: Direct LIMO / Chauffeur Service Management | C2: 30 | D2: Yes | E2: Direct management of limo, executive chauffeur, black-car or similar premium passenger transport operations | F2: Score highly only where direct chauffeur/limo operations are clearly evidenced. | G2: Generic fleet/logistics alone is transferable, not equivalent. Knockout gate: if clearly absent, Must-Have Fit = Fail and Decision = Reject; if direct fit is plausible but needs validation, use Partial.
A3: 001 | B3: US Market / US Customer Exposure | C3: 20 | D3: Yes | E3: Experience supporting US customers, bookings, dispatch, service standards or operations | F3: Explicit US exposure scores materially higher than generic international exposure. | G3: Knockout gate: explicit US exposure is high-weight. If clearly absent, Must-Have Fit = Fail; if potentially present but not explicit, use Partial pending validation.
A4: 001 | B4: Operations Management | C4: 15 | D4: No | E4: End-to-end operations ownership, SOPs, KPIs, service delivery, escalation handling | F4: Assess scale, accountability and operational complexity.
A5: 001 | B5: Leadership & People Management | C5: 15 | D5: No | E5: Team leadership, supervisors, hiring, coaching, performance management | F5: Higher score for multi-team / cross-functional leadership.
A6: 001 | B6: Dispatch / Fleet Operations | C6: 10 | D6: No | E6: Dispatching, driver coordination, routing, scheduling, utilization, fleet control | F6: Direct chauffeur dispatch is stronger than freight/delivery dispatch.
A7: 001 | B7: Client / Customer Management | C7: 5 | D7: No | E7: Client servicing, complaints, service recovery, SLAs, customer communication | F7: Premium-service environment is preferred.
A8: 001 | B8: Systems / Technology | C8: 5 | D8: No | E8: Dispatch software, CRM, scheduling tools, reporting systems | F8: Score on demonstrated operational use, not keyword mention.
A9: 002 | B9: Minimum five years of production management experience | C9: 20 | D9: Yes | E9: At least five years in production or factory management roles with responsibility for manufacturing output, production teams, schedules, targets and operational performance. CV dates and role descriptions should substantiate the duration and management-level ownership. | F9: Strong evidence includes five or more recent years managing factory production with clear accountability for people, output and performance. Mid-level evidence includes the required duration but limited scale or partial ownership. Weak evidence includes supervisory-only work, project exposure without operational ownership, or less than five years of relevant management experience. | G9: Count production management experience, not total career length. General administration, retail operations, warehousing or quality-only roles are not equivalent unless the candidate also owned manufacturing production.
A10: 002 | B10: Multi-category food, sweets and bakery manufacturing experience | C10: 15 | D10: Yes | E10: Production experience in food manufacturing, ideally involving sweets, biscuits, cakes, bakery products, snacks, ice cream, pizza, fresh cream or other perishable food categories. Evidence of managing multiple production lines or departments is preferred. | F10: Highest scores require direct sweets or bakery factory experience across several product categories. Strong transferable evidence includes management of complex, perishable food or FMCG manufacturing. Lower scores apply to single-line food production or non-food manufacturing with limited relevance to hygiene, shelf life and recipe-based production. | G10: The JD states that sweets and bakery experience is preferred rather than mandatory. Food retail, restaurant or catering experience should not receive the same score as factory-based food manufacturing.
A11: 002 | B11: Production planning, daily reporting and target delivery | C11: 14 | D11: Yes | E11: Ownership of demand-based production planning, daily production schedules or DPRs, output monitoring, capacity or resource allocation, variance analysis and achievement of production targets. | F11: Strong evidence shows end-to-end planning and control, regular management reporting and measurable improvements in schedule adherence, throughput or target achievement. Moderate evidence shows participation in planning or report preparation without final accountability. Weak evidence consists of generic statements about meeting targets with no planning, reporting or analytical detail. | G11: DPR experience can be evidenced under another name, such as daily output reporting, production MIS or shift-performance reporting. Report preparation should involve analysis or decision support, not merely data entry.
A12: 002 | B12: Dispatch, finished-goods inventory and expiry management | C12: 10 | D12: No | E12: Responsibility for finished-goods dispatch accuracy and timeliness, stock coordination, shelf-life or batch controls, near-expiry monitoring, FEFO practices, and vendor returns or replacements where applicable. | F12: High scores require direct ownership of dispatch and expiry-sensitive finished goods, supported by service, accuracy, wastage or stock-loss results. Moderate scores apply to coordination with warehouse or logistics teams without full ownership. Low scores apply to generic inventory exposure without perishable-goods, dispatch or expiry controls. | G12: Raw-material inventory alone does not fully evidence this criterion. Generic logistics experience is transferable but is not equivalent to managing perishable finished goods and customer dispatches.
A13: 002 | B13: Quality control and health and safety compliance | C13: 15 | D13: No | E13: Implementation or oversight of product-quality controls, SOPs, hygiene or food-safety practices, non-conformance handling, inspections or audits, and workplace health and safety requirements within a factory. | F13: Strong evidence includes operational ownership of quality and safety systems, audit readiness, corrective actions and measurable reductions in defects, complaints or incidents. Moderate evidence includes consistent compliance responsibility under a separate QA or HSE function. Weak evidence includes only broad claims of maintaining quality or safety. | G13: Certifications such as HACCP, ISO 22000 or related standards are useful supporting evidence but are not specified as mandatory. A QA-only career should not substitute for production-management experience.
A14: 002 | B14: Process improvement, waste reduction and production cost control | C14: 10 | D14: No | E14: Examples of improving production processes, efficiency, yield, throughput, downtime, waste or manufacturing cost, plus involvement in production budgets or resource optimization. | F14: High scores require quantified results such as lower waste, reduced cost, improved yield, higher throughput or better labor utilization, preferably with budget accountability. Moderate scores reflect credible improvement initiatives without metrics or with shared ownership. Low scores reflect generic continuous-improvement language without actions or outcomes. | G14: Routine adherence to existing processes should not be treated as process improvement. Budget exposure should relate to production costs, labor, materials or factory resources.
A15: 002 | B15: Factory labor management and team leadership | C15: 5 | D15: No | E15: Leadership of production supervisors and workers, workforce planning, training, coaching, performance management, conflict or labor-issue resolution, and coordination across production departments. | F15: Strong evidence shows leadership of sizable or multi-shift teams, development of supervisors, resolution of labor issues and measurable improvements in attendance, productivity or team performance. Moderate evidence includes direct line management of a smaller team. Weak evidence includes informal mentoring or coordination without people-management authority. | G15: Team size, shift structure and number of departments should inform strength of evidence. Office-team leadership is less relevant than factory-workforce management.
A16: 002 | B16: Relevant bachelor's degree | C16: 5 | D16: Yes | E16: Completed bachelor's degree in Food Science, Production Management, Business Administration or a demonstrably related field from an identifiable institution. | F16: Full evidence is a completed relevant bachelor's or higher degree. A completed degree in a reasonably related discipline may receive partial-to-strong credit depending on relevance. Diplomas, short courses, incomplete degrees or unspecified qualifications do not satisfy the stated requirement. | G16: Do not infer degree completion from attendance dates alone when the CV indicates the qualification is ongoing or incomplete. Professional experience should not automatically replace the explicit degree requirement.
A17: 002 | B17: Production systems, analytical reporting and decision support | C17: 6 | D17: No | E17: Operational use of production management software, ERP or manufacturing modules, spreadsheets, MIS or reporting tools to record output, analyze performance, manage production data and support decisions. | F17: Strong evidence shows regular hands-on use of named systems or advanced reporting tools for planning, analysis and management decisions. Moderate evidence includes competent use of ERP or spreadsheets for routine production reporting. Weak evidence includes software names listed without context or only basic office-tool familiarity. | G17: Tool names should score only when operational use is evidenced. Specific software brands are not required by the JD.
A18: 003 | B18: Export management experience and end-to-end ownership | C18: 20 | D18: Yes | E18: At least five years of export management experience, with responsibility for international orders from buyer engagement and production coordination through documentation, customs clearance, shipment and delivery. CV should show role dates, level of ownership, export markets, shipment volume or value, and results where available. | F18: Strong evidence: 5+ recent years directly managing end-to-end exports at manager level, preferably for food or FMCG products, with measurable delivery, revenue or process results. Moderate evidence: 5+ years in export operations but with limited strategic or commercial ownership. Weak evidence: domestic logistics, import-only work, freight forwarding support or less than five years of relevant export experience. | G18: The JD explicitly requires a minimum of five years of enriched experience. Do not treat general supply chain, domestic sales or import experience as equivalent. The five-year threshold should be applied to substantively relevant export work, not merely the candidate's total career length.
A19: 003 | B19: Confectionery and perishable food export domain knowledge | C19: 15 | D19: Yes | E19: Experience or clearly demonstrated knowledge involving confectionery, sweets, bakery products or closely comparable perishable food items, including shelf-life constraints, food-safe handling, packaging, storage, labeling and export-market requirements. | F19: Strong evidence: direct export responsibility for confectionery, bakery or other shelf-life-sensitive foods across multiple markets. Moderate evidence: export experience in closely related packaged food, dairy, frozen or perishable categories with clear handling and food-safety exposure. Weak evidence: non-food exports or generic FMCG experience without evidence of perishable-product requirements. | G19: Generic FMCG exposure is not automatically equivalent to confectionery or perishable food knowledge. Closely related food categories may be accepted only where the CV demonstrates relevant shelf-life, handling, packaging or food-safety complexity.
A20: 003 | B20: International market development and export strategy | C20: 15 | D20: No | E20: Evidence of researching and selecting export markets, analyzing market trends, setting international sales targets, adapting product mix or route-to-market strategy, appointing distributors or agents, acquiring high-value clients, and entering new countries. International trade show participation and resulting leads or business should also count. | F20: Strong evidence: owned export strategy and delivered measurable entry into new markets, client acquisition or export sales growth. Moderate evidence: contributed to market research or distributor development but did not own targets or strategy. Weak evidence: generic international sales claims without named markets, strategic actions or outcomes. | G20: Existing export order handling alone does not demonstrate market-development capability. Trade show attendance should score meaningfully only when the candidate's commercial role or outcomes are evident.
... A42: 005 | B42: English fluency, independent working ability, and US-hours availability | C42: 10 | D42: Yes | E42: Evidence of professional English communication with US clients, independent remote or offshore sales execution, and willingness or prior experience working Monday–Friday during US business hours. | F42: Strong evidence includes regular English-language sales calls with US stakeholders and sustained work on a US-aligned shift. Moderate evidence includes strong international client communication but no explicit schedule information. Explicit inability to communicate professionally in English or work US hours fails the criterion. | G42: Absence of schedule information on a CV should be flagged for recruiter verification rather than treated as confirmed unwillingness. The knockout applies where the candidate explicitly cannot meet the US-hours requirement or lacks the necessary English sales communication capability.

Sheet Recruitment Pipeline
A1: Stage | B1: Candidate Count | C1: % of Screened
A2: Applied | B2: =COUNTIF(Candidates!$T$2:$T$2000,A2) -> 0 | C2: =IFERROR(B2/COUNTA(Candidates!$A$2:$A$2000),0) -> 0
A3: HR Screening | B3: =COUNTIF(Candidates!$T$2:$T$2000,A3) -> 0 | C3: =IFERROR(B3/COUNTA(Candidates!$A$2:$A$2000),0) -> 0
A4: Background Check | B4: =COUNTIF(Candidates!$T$2:$T$2000,A4) -> 0 | C4: =IFERROR(B4/COUNTA(Candidates!$A$2:$A$2000),0) -> 0
A5: Shortlisted | B5: =COUNTIF(Candidates!$T$2:$T$2000,A5) -> 5 | C5: =IFERROR(B5/COUNTA(Candidates!$A$2:$A$2000),0) -> 0.11627907
A6: Technical Interview | B6: =COUNTIF(Candidates!$T$2:$T$2000,A6) -> 0 | C6: =IFERROR(B6/COUNTA(Candidates!$A$2:$A$2000),0) -> 0
A7: Final Interview | B7: =COUNTIF(Candidates!$T$2:$T$2000,A7) -> 1 | C7: =IFERROR(B7/COUNTA(Candidates!$A$2:$A$2000),0) -> 0.023255814
A8: Client Interview | B8: =COUNTIF(Candidates!$T$2:$T$2000,A8) -> 0 | C8: =IFERROR(B8/COUNTA(Candidates!$A$2:$A$2000),0) -> 0
A9: Offer Sent | B9: =COUNTIF(Candidates!$T$2:$T$2000,A9) -> 0 | C9: =IFERROR(B9/COUNTA(Candidates!$A$2:$A$2000),0) -> 0
A10: Hired | B10: =COUNTIF(Candidates!$T$2:$T$2000,A10) -> 0 | C10: =IFERROR(B10/COUNTA(Candidates!$A$2:$A$2000),0) -> 0
A11: Hold | B11: =COUNTIF(Candidates!$T$2:$T$2000,A11) -> 2 | C11: =IFERROR(B11/COUNTA(Candidates!$A$2:$A$2000),0) -> 0.046511628
A12: Rejected | B12: =COUNTIF(Candidates!$T$2:$T$2000,A12) -> 35 | C12: =IFERROR(B12/COUNTA(Candidates!$A$2:$A$2000),0) -> 0.81395349

Sheet Dashboard
A1: OSYNIX ATS MASTER TRACKER | J1: TALENT POOL
J2: Total Profiles | K2: =COUNTA('Talent Pool Master'!$A$2:$A$2000) -> 42
A3: Selected Ref # | B3: 005 | D3: Position | E3: {=IFERROR(INDEX('Positions Master'!$C$2:$C$500,MATCH($B$3,'Positions Master'!$A$2:$A$500,0)),"")} -> B2B Sales Executive – US IT Staffing | J3: Active Profiles | K3: =COUNTIF('Talent Pool Master'!$Q$2:$Q$2000,"Active") -> 42
J4: Priority Talent | K4: =COUNTIF('Talent Pool Master'!$Q$2:$Q$2000,"Priority Talent") -> 0
A5: Profiles Screened | B5: =COUNTIF(Candidates!$B$2:$B$2000,$B$3) -> 0 | C5: Shortlisted | D5: =COUNTIFS(Candidates!$B$2:$B$2000,$B$3,Candidates!$S$2:$S$2000,"Priority Shortlist")+COUNTIFS(Candidates!$B$2:$B$2000,$B$3,Candidates!$S$2:$S$2000,"Shortlist") -> 0 | E5: Client Interviews | F5: =COUNTIFS(Candidates!$B$2:$B$2000,$B$3,Candidates!$T$2:$T$2000,"Client Interview") -> 0 | G5: Hired | H5: =COUNTIFS(Candidates!$B$2:$B$2000,$B$3,Candidates!$T$2:$T$2000,"Hired") -> 0 | J5: Placed | K5: =COUNTIF('Talent Pool Master'!$Q$2:$Q$2000,"Placed") -> 0
J6: Archived / DNC | K6: =COUNTIF('Talent Pool Master'!$Q$2:$Q$2000,"Archived")+COUNTIF('Talent Pool Master'!$Q$2:$Q$2000,"Do Not Contact") -> 0
A8: Avg. ATS Match | B8: =IFERROR(AVERAGEIF(Candidates!$B$2:$B$2000,$B$3,Candidates!$M$2:$M$2000),0) -> 0 | C8: On Hold | D8: =COUNTIFS(Candidates!$B$2:$B$2000,$B$3,Candidates!$S$2:$S$2000,"Hold") -> 0 | E8: Rejected | F8: =COUNTIFS(Candidates!$B$2:$B$2000,$B$3,Candidates!$S$2:$S$2000,"Reject") -> 0 | G8: Offers | H8: =COUNTIFS(Candidates!$B$2:$B$2000,$B$3,Candidates!$T$2:$T$2000,"Offer Sent") -> 0
A11: Position Summary
A12: Client | B12: {=IFERROR(INDEX('Positions Master'!$B$2:$B$500,MATCH($B$3,'Positions Master'!$A$2:$A$500,0)),"")} -> HR Ways | D12: Stage | E12: Count | F12: %
A13: Status | B13: {=IFERROR(INDEX('Positions Master'!$F$2:$F$500,MATCH($B$3,'Positions Master'!$A$2:$A$500,0)),"")} -> Active | D13: ='Recruitment Pipeline'!A2 -> Applied | E13: =COUNTIFS(Candidates!$B$2:$B$2000,$B$3,Candidates!$T$2:$T$2000,D13) -> 0 | F13: =IFERROR(E13/$B$5,0) -> 0
A14: Priority | B14: {=IFERROR(INDEX('Positions Master'!$G$2:$G$500,MATCH($B$3,'Positions Master'!$A$2:$A$500,0)),"")} -> High | D14: ='Recruitment Pipeline'!A3 -> HR Screening | E14: =COUNTIFS(Candidates!$B$2:$B$2000,$B$3,Candidates!$T$2:$T$2000,D14) -> 0 | F14: =IFERROR(E14/$B$5,0) -> 0
A15: Hiring Target | B15: {=IFERROR(INDEX('Positions Master'!$H$2:$H$500,MATCH($B$3,'Positions Master'!$A$2:$A$500,0)),"")} -> 1 | D15: ='Recruitment Pipeline'!A4 -> Background Check | E15: =COUNTIFS(Candidates!$B$2:$B$2000,$B$3,Candidates!$T$2:$T$2000,D15) -> 0 | F15: =IFERROR(E15/$B$5,0) -> 0
A16: Last Updated | B16: {=IFERROR(INDEX('Positions Master'!$R$2:$R$500,MATCH($B$3,'Positions Master'!$A$2:$A$500,0)),"")} -> 46295.182 | D16: ='Recruitment Pipeline'!A5 -> Shortlisted | E16: =COUNTIFS(Candidates!$B$2:$B$2000,$B$3,Candidates!$T$2:$T$2000,D16) -> 0 | F16: =IFERROR(E16/$B$5,0) -> 0
D17: ='Recruitment Pipeline'!A6 -> Technical Interview | E17: =COUNTIFS(Candidates!$B$2:$B$2000,$B$3,Candidates!$T$2:$T$2000,D17) -> 0 | F17: =IFERROR(E17/$B$5,0) -> 0
D18: ='Recruitment Pipeline'!A7 -> Final Interview | E18: =COUNTIFS(Candidates!$B$2:$B$2000,$B$3,Candidates!$T$2:$T$2000,D18) -> 0 | F18: =IFERROR(E18/$B$5,0) -> 0
D19: ='Recruitment Pipeline'!A8 -> Client Interview | E19: =COUNTIFS(Candidates!$B$2:$B$2000,$B$3,Candidates!$T$2:$T$2000,D19) -> 0 | F19: =IFERROR(E19/$B$5,0) -> 0
D20: ='Recruitment Pipeline'!A9 -> Offer Sent | E20: =COUNTIFS(Candidates!$B$2:$B$2000,$B$3,Candidates!$T$2:$T$2000,D20) -> 0 | F20: =IFERROR(E20/$B$5,0) -> 0
D21: ='Recruitment Pipeline'!A10 -> Hired | E21: =COUNTIFS(Candidates!$B$2:$B$2000,$B$3,Candidates!$T$2:$T$2000,D21) -> 0 | F21: =IFERROR(E21/$B$5,0) -> 0
D22: ='Recruitment Pipeline'!A11 -> Hold | E22: =COUNTIFS(Candidates!$B$2:$B$2000,$B$3,Candidates!$T$2:$T$2000,D22) -> 0 | F22: =IFERROR(E22/$B$5,0) -> 0
D23: ='Recruitment Pipeline'!A12 -> Rejected | E23: =COUNTIFS(Candidates!$B$2:$B$2000,$B$3,Candidates!$T$2:$T$2000,D23) -> 0 | F23: =IFERROR(E23/$B$5,0) -> 0

Sheet Talent Pool Master
A1: Candidate ID | B1: Candidate Name | C1: Mobile / Phone Number | D1: Email ID | E1: Location | F1: Current / Latest Designation | G1: Current / Latest Company | H1: Total Experience (Yrs) | I1: Primary Function | J1: Secondary Function / Specialization | K1: Industries / Domains | L1: Core Skills | M1: Seniority Level | N1: Systems / Tools | O1: Geographic / Market Exposure | P1: Career Profile Summary | Q1: Talent Pool Status | R1: First Screened Date | S1: Last Assessed Date | T1: Ref #s Assessed Against | U1: Assessment Count | V1: Latest Decision | W1: Latest Recruitment Stage | X1: Source CV / File | Y1: Talent Pool Notes | Z1: Last Updated | AA1: Professional Summary | AB1: Employment / Career History | AC1: Education
A2: CAND-001 | B2: Zain Abid | C2: +92 328 4582394 | D2: zain199819@gmail.com | E2: Lahore Cantt | F2: Freelance UX/UI Designer / Frontend | G2: Freelancer | I2: UX/UI Design & Frontend | J2: Creative / Digital Projects | K2: Technology / Digital | L2: UX/UI design; frontend development; graphic design; project coordination; marketing exposure | M2: Individual Contributor | P2: Creative/technical profile with UI/UX, frontend and some project/marketing exposure. | Q2: Active | R2: =IF($A2="","",IFERROR(MINIFS(Candidates!$K$2:$K$2000,Candidates!$A$2:$A$2000,$A2),"")) -> 46290 | S2: =IF($A2="","",IFERROR(MAXIFS(Candidates!$AA$2:$AA$2000,Candidates!$A$2:$A$2000,$A2),"")) -> 46291 | T2: =IFERROR(__xludf.DUMMYFUNCTION("IF($A2="""","""",IFERROR(TEXTJOIN("", "",TRUE,UNIQUE(FILTER(Candidates!$B$2:$B$2000,Candidates!$A$2:$A$2000=$A2))),""""))"),"001") -> 001 | U2: =IF($A2="","",COUNTIF(Candidates!$A$2:$A$2000,$A2)) -> 1 | V2: =IFERROR(__xludf.DUMMYFUNCTION("IF($A2="""","""",IFERROR(INDEX(FILTER(Candidates!$S$2:$S$2000,Candidates!$A$2:$A$2000=$A2),COUNTIF(Candidates!$A$2:$A$2000,$A2)),""""))"),"Reject") -> Reject | W2: =IFERROR(__xludf.DUMMYFUNCTION("IF($A2="""","""",IFERROR(INDEX(FILTER(Candidates!$T$2:$T$2000,Candidates!$A$2:$A$2000=$A2),COUNTIF(Candidates!$A$2:$A$2000,$A2)),""""))"),"Rejected") -> Rejected | Y2: Rejected for Ref #001 only; retain for future technology, design or digital roles. | Z2: 46291
A3: CAND-002 | B3: Sidra Azam | C3: +92 304 4889746 | D3: sidrafatima03044@gmail.com | E3: Lahore | F3: Senior Sales Executive | G3: Cresset Technologies | H3: 6 | I3: Sales / Business Development | J3: E-commerce / Account Growth | K3: Technology / E-commerce | L3: Sales; client acquisition; revenue growth; team leadership; multi-account operations | M3: Senior Professional | N3: Amazon; Walmart; Shopify; Etsy | P3: Commercial sales profile with e-commerce exposure, account growth and team leadership. | Q3: Active | R3: =IF($A3="","",IFERROR(MINIFS(Candidates!$K$2:$K$2000,Candidates!$A$2:$A$2000,$A3),"")) -> 46290 | S3: =IF($A3="","",IFERROR(MAXIFS(Candidates!$AA$2:$AA$2000,Candidates!$A$2:$A$2000,$A3),"")) -> 46291 | T3: =IFERROR(__xludf.DUMMYFUNCTION("IF($A3="""","""",IFERROR(TEXTJOIN("", "",TRUE,UNIQUE(FILTER(Candidates!$B$2:$B$2000,Candidates!$A$2:$A$2000=$A3))),""""))"),"001") -> 001 | U3: =IF($A3="","",COUNTIF(Candidates!$A$2:$A$2000,$A3)) -> 1 | V3: =IFERROR(__xludf.DUMMYFUNCTION("IF($A3="""","""",IFERROR(INDEX(FILTER(Candidates!$S$2:$S$2000,Candidates!$A$2:$A$2000=$A3),COUNTIF(Candidates!$A$2:$A$2000,$A3)),""""))"),"Reject") -> Reject | W3: =IFERROR(__xludf.DUMMYFUNCTION("IF($A3="""","""",IFERROR(INDEX(FILTER(Candidates!$T$2:$T$2000,Candidates!$A$2:$A$2000=$A3),COUNTIF(Candidates!$A$2:$A$2000,$A3)),""""))"),"Rejected") -> Rejected | Y3: Rejected for Ref #001 only; retain for sales, e-commerce and business development roles. | Z3: 46291
A4: CAND-003 | B4: Ejaz Mehmood | C4: +92 308 4196749 | D4: emahmood91@gmail.com | E4: Lahore | F4: Limousine Dispatcher & Operations Manager (Remote) | G4: Abiel Limo Worldwide | H4: 8 | I4: Transportation Operations | J4: Limo / Chauffeur Dispatch | K4: Limo / Chauffeur / Ground Transportation | L4: Limo dispatch; reservations; driver assignment; affiliate coordination; airport/corporate/VIP bookings; service recovery | M4: Manager | N4: Limo Anywhere | O4: USA / UK / Canada | P4: Direct limousine/chauffeur operations specialist with strong dispatch, reservations and affiliate-network experience. | Q4: Active | R4: =IF($A4="","",IFERROR(MINIFS(Candidates!$K$2:$K$2000,Candidates!$A$2:$A$2000,$A4),"")) -> 46290 | S4: =IF($A4="","",IFERROR(MAXIFS(Candidates!$AA$2:$AA$2000,Candidates!$A$2:$A$2000,$A4),"")) -> 46291 | T4: =IFERROR(__xludf.DUMMYFUNCTION("IF($A4="""","""",IFERROR(TEXTJOIN("", "",TRUE,UNIQUE(FILTER(Candidates!$B$2:$B$2000,Candidates!$A$2:$A$2000=$A4))),""""))"),"001") -> 001 | U4: =IF($A4="","",COUNTIF(Candidates!$A$2:$A$2000,$A4)) -> 1 | V4: =IFERROR(__xludf.DUMMYFUNCTION("IF($A4="""","""",IFERROR(INDEX(FILTER(Candidates!$S$2:$S$2000,Candidates!$A$2:$A$2000=$A4),COUNTIF(Candidates!$A$2:$A$2000,$A4)),""""))"),"Priority Shortlist") -> Priority Shortlist | W4: =IFERROR(__xludf.DUMMYFUNCTION("IF($A4="""","""",IFERROR(INDEX(FILTER(Candidates!$T$2:$T$2000,Candidates!$A$2:$A$2000=$A4),COUNTIF(Candidates!$A$2:$A$2000,$A4)),""""))"),"Final Interview") -> Final Interview | Y4: Currently shortlisted for Ref #001; also retain for future chauffeur, dispatch and ground-transport roles. | Z4: 46291
A5: CAND-004 | B5: Mansoor Ahmed Bajwa | C5: 0343-7709958 | D5: mansoorbajwa80@gmail.com | E5: Lahore | F5: Manager Administration Transport | G5: BIGWAY PVT LTD | H5: 26 | I5: Transport & Fleet Operations | J5: Administration / Logistics | K5: Transportation / Fleet / Logistics | L5: Route planning; scheduling; driver supervision; fleet maintenance; fuel control; budgets; logistics | M5: Manager | N5: GPS / transport software | O5: Pakistan | P5: Senior transport and fleet operations leader with large-team, driver and budget responsibility. | Q5: Active | R5: =IF($A5="","",IFERROR(MINIFS(Candidates!$K$2:$K$2000,Candidates!$A$2:$A$2000,$A5),"")) -> 46290 | S5: =IF($A5="","",IFERROR(MAXIFS(Candidates!$AA$2:$AA$2000,Candidates!$A$2:$A$2000,$A5),"")) -> 46291 | T5: =IFERROR(__xludf.DUMMYFUNCTION("IF($A5="""","""",IFERROR(TEXTJOIN("", "",TRUE,UNIQUE(FILTER(Candidates!$B$2:$B$2000,Candidates!$A$2:$A$2000=$A5))),""""))"),"001") -> 001 | U5: =IF($A5="","",COUNTIF(Candidates!$A$2:$A$2000,$A5)) -> 1 | V5: =IFERROR(__xludf.DUMMYFUNCTION("IF($A5="""","""",IFERROR(INDEX(FILTER(Candidates!$S$2:$S$2000,Candidates!$A$2:$A$2000=$A5),COUNTIF(Candidates!$A$2:$A$2000,$A5)),""""))"),"Reject") -> Reject | W5: =IFERROR(__xludf.DUMMYFUNCTION("IF($A5="""","""",IFERROR(INDEX(FILTER(Candidates!$T$2:$T$2000,Candidates!$A$2:$A$2000=$A5),COUNTIF(Candidates!$A$2:$A$2000,$A5)),""""))"),"Rejected") -> Rejected | Y5: Rejected for Ref #001 only; retain for fleet, transport, administration and logistics leadership roles. | Z5: 46291
A6: CAND-005 | B6: Fakhra Sikander | C6: +92 322 4720240 | D6: fakhramunir@hotmail.com | E6: Johar Town, Lahore | F6: Call Center Manager | G6: 3D Lifestyle | I6: Customer Service Operations | J6: Call Center Management | K6: Customer Service / Contact Center | L6: KPI leadership; CRM; QA; recruitment and training; escalations; service delivery | M6: Manager | N6: CRM | O6: Pakistan | P6: Customer-service operations manager with KPI, QA, training and escalation-management capability. | Q6: Active | R6: =IF($A6="","",IFERROR(MINIFS(Candidates!$K$2:$K$2000,Candidates!$A$2:$A$2000,$A6),"")) -> 46290 | S6: =IF($A6="","",IFERROR(MAXIFS(Candidates!$AA$2:$AA$2000,Candidates!$A$2:$A$2000,$A6),"")) -> 46291 | T6: =IFERROR(__xludf.DUMMYFUNCTION("IF($A6="""","""",IFERROR(TEXTJOIN("", "",TRUE,UNIQUE(FILTER(Candidates!$B$2:$B$2000,Candidates!$A$2:$A$2000=$A6))),""""))"),"001") -> 001 | U6: =IF($A6="","",COUNTIF(Candidates!$A$2:$A$2000,$A6)) -> 1 | V6: =IFERROR(__xludf.DUMMYFUNCTION("IF($A6="""","""",IFERROR(INDEX(FILTER(Candidates!$S$2:$S$2000,Candidates!$A$2:$A$2000=$A6),COUNTIF(Candidates!$A$2:$A$2000,$A6)),""""))"),"Reject") -> Reject | W6: =IFERROR(__xludf.DUMMYFUNCTION("IF($A6="""","""",IFERROR(INDEX(FILTER(Candidates!$T$2:$T$2000,Candidates!$A$2:$A$2000=$A6),COUNTIF(Candidates!$A$2:$A$2000,$A6)),""""))"),"Rejected") -> Rejected | Y6: Rejected for Ref #001 only; retain for contact-center and customer-operations roles. | Z6: 46291
A7: CAND-006 | B7: Qaisar Khalid | C7: 0321-6517101 | D7: qasir.khalid08@gmail.com | E7: Faisalabad | F7: Warehouse & Logistic Operation Lead | G7: SWAT Agro Chemicals | I7: Warehouse & Logistics | J7: Supply Chain Operations | K7: Warehousing / Logistics / Agrochemicals | L7: Inventory; warehouse operations; dispatch coordination; staff supervision; budgets; vendor coordination | M7: Team Lead / Supervisor | O7: Pakistan | P7: Warehouse and logistics lead with inventory, dispatch and team-supervision exposure. | Q7: Active | R7: =IF($A7="","",IFERROR(MINIFS(Candidates!$K$2:$K$2000,Candidates!$A$2:$A$2000,$A7),"")) -> 46290 | S7: =IF($A7="","",IFERROR(MAXIFS(Candidates!$AA$2:$AA$2000,Candidates!$A$2:$A$2000,$A7),"")) -> 46291 | T7: =IFERROR(__xludf.DUMMYFUNCTION("IF($A7="""","""",IFERROR(TEXTJOIN("", "",TRUE,UNIQUE(FILTER(Candidates!$B$2:$B$2000,Candidates!$A$2:$A$2000=$A7))),""""))"),"001") -> 001 | U7: =IF($A7="","",COUNTIF(Candidates!$A$2:$A$2000,$A7)) -> 1 | V7: =IFERROR(__xludf.DUMMYFUNCTION("IF($A7="""","""",IFERROR(INDEX(FILTER(Candidates!$S$2:$S$2000,Candidates!$A$2:$A$2000=$A7),COUNTIF(Candidates!$A$2:$A$2000,$A7)),""""))"),"Reject") -> Reject | W7: =IFERROR(__xludf.DUMMYFUNCTION("IF($A7="""","""",IFERROR(INDEX(FILTER(Candidates!$T$2:$T$2000,Candidates!$A$2:$A$2000=$A7),COUNTIF(Candidates!$A$2:$A$2000,$A7)),""""))"),"Rejected") -> Rejected | Y7: Rejected for Ref #001 only; retain for warehouse, logistics and supply-chain opportunities. | Z7: 46291
A8: CAND-007 | B8: Shahid Iqbal | C8: +92 345 4480810 / +92 315 9614787 | D8: shahed08@gmail.com | E8: Bahawalnagar | F8: Founder & Operations Manager | G8: Independent Retail & Production Unit | H8: 22 | I8: Operations Management | J8: Supply Chain / Manufacturing / Retail | K8: Manufacturing / Retail / Supply Chain | L8: P&L ownership; KPIs; vendor networks; multi-department operations; production and supply chain | M8: Founder / Owner | O8: Pakistan | P8: Senior operations leader with broad P&L, vendor, production, retail and supply-chain management experience. | Q8: Active | R8: =IF($A8="","",IFERROR(MINIFS(Candidates!$K$2:$K$2000,Candidates!$A$2:$A$2000,$A8),"")) -> 46290 | S8: =IF($A8="","",IFERROR(MAXIFS(Candidates!$AA$2:$AA$2000,Candidates!$A$2:$A$2000,$A8),"")) -> 46291 | T8: =IFERROR(__xludf.DUMMYFUNCTION("IF($A8="""","""",IFERROR(TEXTJOIN("", "",TRUE,UNIQUE(FILTER(Candidates!$B$2:$B$2000,Candidates!$A$2:$A$2000=$A8))),""""))"),"001") -> 001 | U8: =IF($A8="","",COUNTIF(Candidates!$A$2:$A$2000,$A8)) -> 1 | V8: =IFERROR(__xludf.DUMMYFUNCTION("IF($A8="""","""",IFERROR(INDEX(FILTER(Candidates!$S$2:$S$2000,Candidates!$A$2:$A$2000=$A8),COUNTIF(Candidates!$A$2:$A$2000,$A8)),""""))"),"Reject") -> Reject | W8: =IFERROR(__xludf.DUMMYFUNCTION("IF($A8="""","""",IFERROR(INDEX(FILTER(Candidates!$T$2:$T$2000,Candidates!$A$2:$A$2000=$A8),COUNTIF(Candidates!$A$2:$A$2000,$A8)),""""))"),"Rejected") -> Rejected | Y8: Rejected for Ref #001 only; retain for senior operations, manufacturing and supply-chain leadership roles. | Z8: 46291
A9: CAND-008 | B9: Ali Mahmood Qureshi | C9: +92 341 4333338 | D9: ali_mahmood22@hotmail.com | E9: Lahore | F9: Head of Customer Success | H9: 10 | I9: Customer Success | J9: SaaS / Enterprise Account Management | K9: SaaS / Technology | L9: B2B customer success; enterprise accounts; retention and revenue growth; SLA/KPI ownership; 50+ team leadership; escalations | M9: Head / Director | O9: USA / Canada / UK / Global B2B | P9: Senior customer-success leader with global enterprise SaaS exposure and large-team management experience. | Q9: Active | R9: =IF($A9="","",IFERROR(MINIFS(Candidates!$K$2:$K$2000,Candidates!$A$2:$A$2000,$A9),"")) -> 46290 | S9: =IF($A9="","",IFERROR(MAXIFS(Candidates!$AA$2:$AA$2000,Candidates!$A$2:$A$2000,$A9),"")) -> 46291 | T9: =IFERROR(__xludf.DUMMYFUNCTION("IF($A9="""","""",IFERROR(TEXTJOIN("", "",TRUE,UNIQUE(FILTER(Candidates!$B$2:$B$2000,Candidates!$A$2:$A$2000=$A9))),""""))"),"001") -> 001 | U9: =IF($A9="","",COUNTIF(Candidates!$A$2:$A$2000,$A9)) -> 1 | V9: =IFERROR(__xludf.DUMMYFUNCTION("IF($A9="""","""",IFERROR(INDEX(FILTER(Candidates!$S$2:$S$2000,Candidates!$A$2:$A$2000=$A9),COUNTIF(Candidates!$A$2:$A$2000,$A9)),""""))"),"Reject") -> Reject | W9: =IFERROR(__xludf.DUMMYFUNCTION("IF($A9="""","""",IFERROR(INDEX(FILTER(Candidates!$T$2:$T$2000,Candidates!$A$2:$A$2000=$A9),COUNTIF(Candidates!$A$2:$A$2000,$A9)),""""))"),"Rejected") -> Rejected | Y9: Rejected for Ref #001 only; retain for customer success, account management and SaaS leadership roles. | Z9: 46291
A10: CAND-009 | B10: Hira Iqbal Ghaznavi | C10: 0321-4076912 | D10: hiraiqbal657@gmail.com | F10: Senior Sales Consultant | G10: 60 Minute Limo | H10: 8 | I10: Ground Transportation Operations | J10: Limo / Chauffeur / Sales | K10: Premium Chauffeur / Ground Transportation / Car Rental | L10: Dispatch and logistics leadership; customer support; corporate accounts; vendor contracts; KPIs; sales and marketing | M10: Head / Director | N10: Limo Anywhere; Moovs; Santa Cruz; GNet; RideCo; Samsara; Podium; Dispatch Monitor; Holiday Taxis; Zendesk | O10: International / global partner exposure; US exposure to validate | P10: Ground-transportation leader with direct chauffeur-industry systems exposure and prior department-head responsibility. | Q10: Active | R10: =IF($A10="","",IFERROR(MINIFS(Candidates!$K$2:$K$2000,Candidates!$A$2:$A$2000,$A10),"")) -> 46290 | S10: =IF($A10="","",IFERROR(MAXIFS(Candidates!$AA$2:$AA$2000,Candidates!$A$2:$A$2000,$A10),"")) -> 46291 | T10: =IFERROR(__xludf.DUMMYFUNCTION("IF($A10="""","""",IFERROR(TEXTJOIN("", "",TRUE,UNIQUE(FILTER(Candidates!$B$2:$B$2000,Candidates!$A$2:$A$2000=$A10))),""""))"),"001") -> 001 | U10: =IF($A10="","",COUNTIF(Candidates!$A$2:$A$2000,$A10)) -> 1 | V10: =IFERROR(__xludf.DUMMYFUNCTION("IF($A10="""","""",IFERROR(INDEX(FILTER(Candidates!$S$2:$S$2000,Candidates!$A$2:$A$2000=$A10),COUNTIF(Candidates!$A$2:$A$2000,$A10)),""""))"),"Shortlist") -> Shortlist | W10: =IFERROR(__xludf.DUMMYFUNCTION("IF($A10="""","""",IFERROR(INDEX(FILTER(Candidates!$T$2:$T$2000,Candidates!$A$2:$A$2000=$A10),COUNTIF(Candidates!$A$2:$A$2000,$A10)),""""))"),"Shortlisted") -> Shortlisted | X10: Hira Iqbal Ghaznavi.pdf | Y10: Shortlisted for Ref #001. Strong premium chauffeur/ground-transportation, dispatch/logistics and leadership profile; explicit US-market exposure should be validated. Retain for chauffeur, fleet, dispatch, mobility and operations leadership roles. | Z10: 46291
A11: CAND-010 | B11: Ahmad Fraz | C11: +92 318 6088030 | D11: ahmadfraz090802@gmail.com | E11: Lahore | F11: Operations Associate | G11: EDKASA Pvt. Ltd. | H11: 5 | I11: Fleet & Logistics Operations | J11: Last-Mile / Delivery | K11: Logistics / Delivery | L11: Fleet dispatch; route optimization; driver incentives; vendor and maintenance coordination; KPI dashboards | M11: Senior Professional | O11: Pakistan | P11: Logistics and fleet-operations profile with hands-on dispatch, routing and driver-performance exposure. | Q11: Active | R11: =IF($A11="","",IFERROR(MINIFS(Candidates!$K$2:$K$2000,Candidates!$A$2:$A$2000,$A11),"")) -> 46290 | S11: =IF($A11="","",IFERROR(MAXIFS(Candidates!$AA$2:$AA$2000,Candidates!$A$2:$A$2000,$A11),"")) -> 46291 | T11: =IFERROR(__xludf.DUMMYFUNCTION("IF($A11="""","""",IFERROR(TEXTJOIN("", "",TRUE,UNIQUE(FILTER(Candidates!$B$2:$B$2000,Candidates!$A$2:$A$2000=$A11))),""""))"),"001") -> 001 | U11: =IF($A11="","",COUNTIF(Candidates!$A$2:$A$2000,$A11)) -> 1 | V11: =IFERROR(__xludf.DUMMYFUNCTION("IF($A11="""","""",IFERROR(INDEX(FILTER(Candidates!$S$2:$S$2000,Candidates!$A$2:$A$2000=$A11),COUNTIF(Candidates!$A$2:$A$2000,$A11)),""""))"),"Reject") -> Reject | W11: =IFERROR(__xludf.DUMMYFUNCTION("IF($A11="""","""",IFERROR(INDEX(FILTER(Candidates!$T$2:$T$2000,Candidates!$A$2:$A$2000=$A11),COUNTIF(Candidates!$A$2:$A$2000,$A11)),""""))"),"Rejected") -> Rejected | Y11: Rejected for Ref #001 only; retain for fleet, logistics and delivery-operations roles. | Z11: 46291
A12: CAND-011 | B12: Engr. Muhammad Arslan Ali | C12: +92-301-4387281 | D12: arslanalite20@gmail.com | E12: Lahore | F12: Logistics Manager (Logistics & Operations) | G12: Alfatah Shopping Mall - Warehouse Lahore | H12: 8 | I12: Public Transport & Fleet Operations | J12: Logistics / Passenger Transport | K12: Public Transit / Passenger Transport / Logistics | L12: Bus operations; fleet scheduling; SLA/KPI management; outsourced operators; safety; vendor coordination | M12: Manager | N12: ITS / fleet monitoring | O12: Pakistan | P12: Passenger-transport and logistics manager with public-transit, fleet, SLA and vendor-management experience. | Q12: Active | R12: =IF($A12="","",IFERROR(MINIFS(Candidates!$K$2:$K$2000,Candidates!$A$2:$A$2000,$A12),"")) -> 46290 | S12: =IF($A12="","",IFERROR(MAXIFS(Candidates!$AA$2:$AA$2000,Candidates!$A$2:$A$2000,$A12),"")) -> 46291 | T12: =IFERROR(__xludf.DUMMYFUNCTION("IF($A12="""","""",IFERROR(TEXTJOIN("", "",TRUE,UNIQUE(FILTER(Candidates!$B$2:$B$2000,Candidates!$A$2:$A$2000=$A12))),""""))"),"001") -> 001 | U12: =IF($A12="","",COUNTIF(Candidates!$A$2:$A$2000,$A12)) -> 1 | V12: =IFERROR(__xludf.DUMMYFUNCTION("IF($A12="""","""",IFERROR(INDEX(FILTER(Candidates!$S$2:$S$2000,Candidates!$A$2:$A$2000=$A12),COUNTIF(Candidates!$A$2:$A$2000,$A12)),""""))"),"Reject") -> Reject | W12: =IFERROR(__xludf.DUMMYFUNCTION("IF($A12="""","""",IFERROR(INDEX(FILTER(Candidates!$T$2:$T$2000,Candidates!$A$2:$A$2000=$A12),COUNTIF(Candidates!$A$2:$A$2000,$A12)),""""))"),"Rejected") -> Rejected | Y12: Rejected for Ref #001 only; retain for public transport, fleet and logistics management roles. | Z12: 46291
A13: CAND-012 | B13: Muhammad Ameer Hamza | C13: +92 3000987027 | D13: humzabutt419@yahoo.com | E13: Pakistan | F13: Retired Captain | G13: Pakistan Army (Retired) | H13: 8 | I13: Operations / Administration | J13: Military Logistics / Security | K13: Defense / Military Operations / Logistics | L13: Crisis response; workforce planning; logistics; administration; security; leadership of 700+ personnel | M13: Officer / Command | O13: Pakistan | P13: Former military officer with large-scale leadership, logistics, administration and crisis-management experience. | Q13: Active | R13: =IF($A13="","",IFERROR(MINIFS(Candidates!$K$2:$K$2000,Candidates!$A$2:$A$2000,$A13),"")) -> 46290 | S13: =IF($A13="","",IFERROR(MAXIFS(Candidates!$AA$2:$AA$2000,Candidates!$A$2:$A$2000,$A13),"")) -> 46291 | T13: =IFERROR(__xludf.DUMMYFUNCTION("IF($A13="""","""",IFERROR(TEXTJOIN("", "",TRUE,UNIQUE(FILTER(Candidates!$B$2:$B$2000,Candidates!$A$2:$A$2000=$A13))),""""))"),"001") -> 001 | U13: =IF($A13="","",COUNTIF(Candidates!$A$2:$A$2000,$A13)) -> 1 | V13: =IFERROR(__xludf.DUMMYFUNCTION("IF($A13="""","""",IFERROR(INDEX(FILTER(Candidates!$S$2:$S$2000,Candidates!$A$2:$A$2000=$A13),COUNTIF(Candidates!$A$2:$A$2000,$A13)),""""))"),"Reject") -> Reject | W13: =IFERROR(__xludf.DUMMYFUNCTION("IF($A13="""","""",IFERROR(INDEX(FILTER(Candidates!$T$2:$T$2000,Candidates!$A$2:$A$2000=$A13),COUNTIF(Candidates!$A$2:$A$2000,$A13)),""""))"),"Rejected") -> Rejected | Y13: Rejected for Ref #001 only; retain for administration, security, operations and logistics leadership roles. | Z13: 46291
A14: CAND-013 | B14: Muhammad Khalid | C14: 923006231094 | D14: khalidrafiq0088@gmail.com | E14: Chishtian, Bahawalnagar | F14: Factory Manager | G14: Dura Flow Pvt. Ltd. | I14: Manufacturing Operations | J14: Production / Factory Management | K14: Manufacturing / Auto Parts / Plastics | L14: Production planning; budgets; team management; cost control; quality; factory operations | M14: Manager | O14: Pakistan | P14: Manufacturing operations manager with production planning, budget, quality and factory-management experience. | Q14: Active | R14: =IF($A14="","",IFERROR(MINIFS(Candidates!$K$2:$K$2000,Candidates!$A$2:$A$2000,$A14),"")) -> 46290 | S14: =IF($A14="","",IFERROR(MAXIFS(Candidates!$AA$2:$AA$2000,Candidates!$A$2:$A$2000,$A14),"")) -> 46291 | T14: =IFERROR(__xludf.DUMMYFUNCTION("IF($A14="""","""",IFERROR(TEXTJOIN("", "",TRUE,UNIQUE(FILTER(Candidates!$B$2:$B$2000,Candidates!$A$2:$A$2000=$A14))),""""))"),"001") -> 001 | U14: =IF($A14="","",COUNTIF(Candidates!$A$2:$A$2000,$A14)) -> 1 | V14: =IFERROR(__xludf.DUMMYFUNCTION("IF($A14="""","""",IFERROR(INDEX(FILTER(Candidates!$S$2:$S$2000,Candidates!$A$2:$A$2000=$A14),COUNTIF(Candidates!$A$2:$A$2000,$A14)),""""))"),"Reject") -> Reject | W14: =IFERROR(__xludf.DUMMYFUNCTION("IF($A14="""","""",IFERROR(INDEX(FILTER(Candidates!$T$2:$T$2000,Candidates!$A$2:$A$2000=$A14),COUNTIF(Candidates!$A$2:$A$2000,$A14)),""""))"),"Rejected") -> Rejected | Y14: Rejected for Ref #001 only; retain for manufacturing, production and factory-management roles. | Z14: 46291
A15: CAND-014 | B15: Kumail Naqvi | C15: +92 312 044 1931 | D15: syedkaimy@gmail.com | F15: Business Development & Sales Operations Manager | H15: 10 | I15: Business Development & Sales Operations | J15: US Freight Dispatch | K15: Freight / Trucking / Logistics / SaaS | L15: Load booking; rate negotiation; driver scheduling; route planning; dispatcher supervision; business development | M15: Manager | N15: CRM; load boards; TMS | O15: USA (Houston / freight operations) | P15: Commercial and operations professional with direct US freight-dispatch experience and sales/business-development exposure. | Q15: Active | R15: =IF($A15="","",IFERROR(MINIFS(Candidates!$K$2:$K$2000,Candidates!$A$2:$A$2000,$A15),"")) -> 46290 | S15: =IF($A15="","",IFERROR(MAXIFS(Candidates!$AA$2:$AA$2000,Candidates!$A$2:$A$2000,$A15),"")) -> 46291 | T15: =IFERROR(__xludf.DUMMYFUNCTION("IF($A15="""","""",IFERROR(TEXTJOIN("", "",TRUE,UNIQUE(FILTER(Candidates!$B$2:$B$2000,Candidates!$A$2:$A$2000=$A15))),""""))"),"001") -> 001 | U15: =IF($A15="","",COUNTIF(Candidates!$A$2:$A$2000,$A15)) -> 1 | V15: =IFERROR(__xludf.DUMMYFUNCTION("IF($A15="""","""",IFERROR(INDEX(FILTER(Candidates!$S$2:$S$2000,Candidates!$A$2:$A$2000=$A15),COUNTIF(Candidates!$A$2:$A$2000,$A15)),""""))"),"Reject") -> Reject | W15: =IFERROR(__xludf.DUMMYFUNCTION("IF($A15="""","""",IFERROR(INDEX(FILTER(Candidates!$T$2:$T$2000,Candidates!$A$2:$A$2000=$A15),COUNTIF(Candidates!$A$2:$A$2000,$A15)),""""))"),"Rejected") -> Rejected | Y15: Rejected for Ref #001 only; retain for US logistics, freight dispatch, sales operations and business-development roles. | Z15: 46291
A16: CAND-015 | B16: Rana Rashid Ali Sadiq | C16: 03207789165 | D16: rashidrana165@gmail.com | E16: Township, Lahore | F16: Assistant Manager Workshop | G16: Veda Transit Solution (Metro Bus Service) | I16: Fleet & Workshop Management | J16: Maintenance / Public Transport / Aviation | K16: Public Transit / Aviation / Fleet Maintenance | L16: Workshop operations; fleet readiness; route and transport management; maintenance strategy; driver performance | M16: Manager | O16: Pakistan / Saudi Arabia | P16: Fleet and workshop professional with public-transport and aviation maintenance exposure. | Q16: Active | R16: =IF($A16="","",IFERROR(MINIFS(Candidates!$K$2:$K$2000,Candidates!$A$2:$A$2000,$A16),"")) -> 46291 | S16: =IF($A16="","",IFERROR(MAXIFS(Candidates!$AA$2:$AA$2000,Candidates!$A$2:$A$2000,$A16),"")) -> 46291 | T16: =IFERROR(__xludf.DUMMYFUNCTION("IF($A16="""","""",IFERROR(TEXTJOIN("", "",TRUE,UNIQUE(FILTER(Candidates!$B$2:$B$2000,Candidates!$A$2:$A$2000=$A16))),""""))"),"001") -> 001 | U16: =IF($A16="","",COUNTIF(Candidates!$A$2:$A$2000,$A16)) -> 1 | V16: =IFERROR(__xludf.DUMMYFUNCTION("IF($A16="""","""",IFERROR(INDEX(FILTER(Candidates!$S$2:$S$2000,Candidates!$A$2:$A$2000=$A16),COUNTIF(Candidates!$A$2:$A$2000,$A16)),""""))"),"Reject") -> Reject | W16: =IFERROR(__xludf.DUMMYFUNCTION("IF($A16="""","""",IFERROR(INDEX(FILTER(Candidates!$T$2:$T$2000,Candidates!$A$2:$A$2000=$A16),COUNTIF(Candidates!$A$2:$A$2000,$A16)),""""))"),"Rejected") -> Rejected | Y16: Rejected for Ref #001 only; retain for fleet maintenance, workshop and transport-management roles. | Z16: 46291
A17: CAND-016 | B17: Iftikhar Ahmed | C17: +92 321 2886797 | D17: iftikharahmed0670@gmail.com | E17: Lahore | F17: Operations Excellence Manager | G17: Orange Line Metro Rail Transit System | H17: 23 | I17: Operations Excellence | J17: Metro / Fleet / Workshop Operations | K17: Public Transit / Metro Rail / Military Engineering | L17: KPI systems; SLA and service quality; fleet/workshop operations; audits; safety; vendors; RCA; continuous improvement | M17: Manager | N17: CMMS; SAP | O17: Pakistan | P17: Senior operations-excellence professional with metro, workshop, fleet, safety and continuous-improvement experience. | Q17: Active | R17: =IF($A17="","",IFERROR(MINIFS(Candidates!$K$2:$K$2000,Candidates!$A$2:$A$2000,$A17),"")) -> 46291 | S17: =IF($A17="","",IFERROR(MAXIFS(Candidates!$AA$2:$AA$2000,Candidates!$A$2:$A$2000,$A17),"")) -> 46291 | T17: =IFERROR(__xludf.DUMMYFUNCTION("IF($A17="""","""",IFERROR(TEXTJOIN("", "",TRUE,UNIQUE(FILTER(Candidates!$B$2:$B$2000,Candidates!$A$2:$A$2000=$A17))),""""))"),"001") -> 001 | U17: =IF($A17="","",COUNTIF(Candidates!$A$2:$A$2000,$A17)) -> 1 | V17: =IFERROR(__xludf.DUMMYFUNCTION("IF($A17="""","""",IFERROR(INDEX(FILTER(Candidates!$S$2:$S$2000,Candidates!$A$2:$A$2000=$A17),COUNTIF(Candidates!$A$2:$A$2000,$A17)),""""))"),"Reject") -> Reject | W17: =IFERROR(__xludf.DUMMYFUNCTION("IF($A17="""","""",IFERROR(INDEX(FILTER(Candidates!$T$2:$T$2000,Candidates!$A$2:$A$2000=$A17),COUNTIF(Candidates!$A$2:$A$2000,$A17)),""""))"),"Rejected") -> Rejected | Y17: Rejected for Ref #001 only; retain for operations excellence, public transit and asset/fleet leadership roles. | Z17: 46291
A18: CAND-017 | B18: Muhammad Kashif Iqbal | C18: +92 317 7184901 | D18: Kashif.iqbal5987@gmail.com | E18: Gujranwala | F18: Manager Operations | G18: Imperial Venture | I18: Field Operations | J18: Waste Logistics / HSE | K18: Waste Management / Environmental Services | L18: Route management; driver productivity; SOPs; HSE; reporting; waste transport | M18: Manager | O18: Pakistan | P18: Field-operations manager with route, driver, safety and environmental-services experience. | Q18: Active | R18: =IF($A18="","",IFERROR(MINIFS(Candidates!$K$2:$K$2000,Candidates!$A$2:$A$2000,$A18),"")) -> 46291 | S18: =IF($A18="","",IFERROR(MAXIFS(Candidates!$AA$2:$AA$2000,Candidates!$A$2:$A$2000,$A18),"")) -> 46291 | T18: =IFERROR(__xludf.DUMMYFUNCTION("IF($A18="""","""",IFERROR(TEXTJOIN("", "",TRUE,UNIQUE(FILTER(Candidates!$B$2:$B$2000,Candidates!$A$2:$A$2000=$A18))),""""))"),"001") -> 001 | U18: =IF($A18="","",COUNTIF(Candidates!$A$2:$A$2000,$A18)) -> 1 | V18: =IFERROR(__xludf.DUMMYFUNCTION("IF($A18="""","""",IFERROR(INDEX(FILTER(Candidates!$S$2:$S$2000,Candidates!$A$2:$A$2000=$A18),COUNTIF(Candidates!$A$2:$A$2000,$A18)),""""))"),"Reject") -> Reject | W18: =IFERROR(__xludf.DUMMYFUNCTION("IF($A18="""","""",IFERROR(INDEX(FILTER(Candidates!$T$2:$T$2000,Candidates!$A$2:$A$2000=$A18),COUNTIF(Candidates!$A$2:$A$2000,$A18)),""""))"),"Rejected") -> Rejected | Y18: Rejected for Ref #001 only; retain for field operations, waste-management and HSE-linked roles. | Z18: 46291
A19: CAND-018 | B19: Nauman Atique | C19: +92 305 8215553 / +92 326 0590127 | D19: rananaumanatique@gmail.com | E19: Lahore | F19: DM Operations | G19: Sindh Solid Waste Management Board | Endurance Environment | H19: 10 | I19: Fleet & Operations Management | J19: Waste / Environmental Services | K19: Municipal Waste / Healthcare Waste / Environmental Services | L19: Route planning; vehicle deployment; maintenance; vendors; cost control; field-team leadership | M19: Manager | O19: Pakistan | P19: Fleet and operations manager with municipal/environmental-services, route and vendor-management experience. | Q19: Active | R19: =IF($A19="","",IFERROR(MINIFS(Candidates!$K$2:$K$2000,Candidates!$A$2:$A$2000,$A19),"")) -> 46291 | S19: =IF($A19="","",IFERROR(MAXIFS(Candidates!$AA$2:$AA$2000,Candidates!$A$2:$A$2000,$A19),"")) -> 46291 | T19: =IFERROR(__xludf.DUMMYFUNCTION("IF($A19="""","""",IFERROR(TEXTJOIN("", "",TRUE,UNIQUE(FILTER(Candidates!$B$2:$B$2000,Candidates!$A$2:$A$2000=$A19))),""""))"),"001") -> 001 | U19: =IF($A19="","",COUNTIF(Candidates!$A$2:$A$2000,$A19)) -> 1 | V19: =IFERROR(__xludf.DUMMYFUNCTION("IF($A19="""","""",IFERROR(INDEX(FILTER(Candidates!$S$2:$S$2000,Candidates!$A$2:$A$2000=$A19),COUNTIF(Candidates!$A$2:$A$2000,$A19)),""""))"),"Reject") -> Reject | W19: =IFERROR(__xludf.DUMMYFUNCTION("IF($A19="""","""",IFERROR(INDEX(FILTER(Candidates!$T$2:$T$2000,Candidates!$A$2:$A$2000=$A19),COUNTIF(Candidates!$A$2:$A$2000,$A19)),""""))"),"Rejected") -> Rejected | Y19: Rejected for Ref #001 only; retain for fleet, field operations and environmental-services roles. | Z19: 46291
A20: CAND-019 | B20: Razi Abbas | C20: +92-311-7365492 | D20: raziabbas7212@gmail.com | E20: Multan | F20: Branch Manager | G20: Food Panda | I20: Branch / Last-Mile Operations | J20: E-commerce / Food Delivery | K20: Food Delivery / E-commerce / Last Mile | L20: Rider operations; hub dispatch; KPIs; inventory; customer complaints; delivery coordination | M20: Manager | O20: Pakistan | P20: Branch and last-mile operations profile with rider, hub, dispatch and KPI-management experience. | Q20: Active | R20: =IF($A20="","",IFERROR(MINIFS(Candidates!$K$2:$K$2000,Candidates!$A$2:$A$2000,$A20),"")) -> 46291 | S20: =IF($A20="","",IFERROR(MAXIFS(Candidates!$AA$2:$AA$2000,Candidates!$A$2:$A$2000,$A20),"")) -> 46291 | T20: =IFERROR(__xludf.DUMMYFUNCTION("IF($A20="""","""",IFERROR(TEXTJOIN("", "",TRUE,UNIQUE(FILTER(Candidates!$B$2:$B$2000,Candidates!$A$2:$A$2000=$A20))),""""))"),"001") -> 001 | U20: =IF($A20="","",COUNTIF(Candidates!$A$2:$A$2000,$A20)) -> 1 | V20: =IFERROR(__xludf.DUMMYFUNCTION("IF($A20="""","""",IFERROR(INDEX(FILTER(Candidates!$S$2:$S$2000,Candidates!$A$2:$A$2000=$A20),COUNTIF(Candidates!$A$2:$A$2000,$A20)),""""))"),"Reject") -> Reject | W20: =IFERROR(__xludf.DUMMYFUNCTION("IF($A20="""","""",IFERROR(INDEX(FILTER(Candidates!$T$2:$T$2000,Candidates!$A$2:$A$2000=$A20),COUNTIF(Candidates!$A$2:$A$2000,$A20)),""""))"),"Rejected") -> Rejected | Y20: Rejected for Ref #001 only; retain for e-commerce, food-delivery and last-mile operations roles. | Z20: 46291
A21: CAND-020 | B21: Salman Khan Magsi | C21: 0300-4337261 | D21: salmanmagsi38@gmail.com | E21: Bahria Town, Lahore | F21: Senior Manager Operations | G21: Secure Logistics Group | H21: 23 | I21: Transport & Logistics Operations | J21: Courier / Line-Haul / Fleet | K21: Courier / Logistics / Transportation / Warehousing | L21: Centralized dispatch; booking and forwarding; fleet outsourcing; multi-branch operations; cost control; team leadership | M21: Senior Manager | O21: Pakistan | P21: Senior logistics leader with extensive courier, transport, fleet, dispatch and multi-branch operations experience. | Q21: Active | R21: =IF($A21="","",IFERROR(MINIFS(Candidates!$K$2:$K$2000,Candidates!$A$2:$A$2000,$A21),"")) -> 46291 | S21: =IF($A21="","",IFERROR(MAXIFS(Candidates!$AA$2:$AA$2000,Candidates!$A$2:$A$2000,$A21),"")) -> 46291 | T21: =IFERROR(__xludf.DUMMYFUNCTION("IF($A21="""","""",IFERROR(TEXTJOIN("", "",TRUE,UNIQUE(FILTER(Candidates!$B$2:$B$2000,Candidates!$A$2:$A$2000=$A21))),""""))"),"001") -> 001 | U21: =IF($A21="","",COUNTIF(Candidates!$A$2:$A$2000,$A21)) -> 1 | V21: =IFERROR(__xludf.DUMMYFUNCTION("IF($A21="""","""",IFERROR(INDEX(FILTER(Candidates!$S$2:$S$2000,Candidates!$A$2:$A$2000=$A21),COUNTIF(Candidates!$A$2:$A$2000,$A21)),""""))"),"Reject") -> Reject | W21: =IFERROR(__xludf.DUMMYFUNCTION("IF($A21="""","""",IFERROR(INDEX(FILTER(Candidates!$T$2:$T$2000,Candidates!$A$2:$A$2000=$A21),COUNTIF(Candidates!$A$2:$A$2000,$A21)),""""))"),"Rejected") -> Rejected | Y21: Rejected for Ref #001 only; retain for senior logistics, transport, courier and fleet-management roles. | Z21: 46291
A22: CAND-021 | B22: Raza Shahzad | C22: +92-3214007507 | D22: razashahzad52@gmail.com | I22: Operations Management | J22: Property / Sales / Maintenance | K22: Property / Leasing / Operations | L22: Vendor and contractor management; multi-region teams; sales support; maintenance; quotes and invoices; insurance claims | M22: Manager | N22: CRM | P22: General operations manager with vendor, maintenance, sales-support and multi-region team exposure. | Q22: Active | R22: =IF($A22="","",IFERROR(MINIFS(Candidates!$K$2:$K$2000,Candidates!$A$2:$A$2000,$A22),"")) -> 46291 | S22: =IF($A22="","",IFERROR(MAXIFS(Candidates!$AA$2:$AA$2000,Candidates!$A$2:$A$2000,$A22),"")) -> 46291 | T22: =IFERROR(__xludf.DUMMYFUNCTION("IF($A22="""","""",IFERROR(TEXTJOIN("", "",TRUE,UNIQUE(FILTER(Candidates!$B$2:$B$2000,Candidates!$A$2:$A$2000=$A22))),""""))"),"001") -> 001 | U22: =IF($A22="","",COUNTIF(Candidates!$A$2:$A$2000,$A22)) -> 1 | V22: =IFERROR(__xludf.DUMMYFUNCTION("IF($A22="""","""",IFERROR(INDEX(FILTER(Candidates!$S$2:$S$2000,Candidates!$A$2:$A$2000=$A22),COUNTIF(Candidates!$A$2:$A$2000,$A22)),""""))"),"Reject") -> Reject | W22: =IFERROR(__xludf.DUMMYFUNCTION("IF($A22="""","""",IFERROR(INDEX(FILTER(Candidates!$T$2:$T$2000,Candidates!$A$2:$A$2000=$A22),COUNTIF(Candidates!$A$2:$A$2000,$A22)),""""))"),"Rejected") -> Rejected | Y22: Rejected for Ref #001 only; retain for operations, property, facilities and service-management roles. | Z22: 46291
A23: CAND-022 | B23: Alam Fazal | C23: +92-321-9886773 | D23: alam.fazal@yahoo.com | E23: Bahria Orchard, Lahore | F23: Incharge Fleet Operations, Maintenance & Logistics | G23: Daewoo Express Bus Service Pakistan | I23: Fleet Operations | J23: Passenger Transport / Maintenance / Logistics | K23: Passenger Transport / Bus / Fleet Maintenance | L23: Fleet operations; depot operations; 90+ staff leadership; vendors; KPIs; maintenance budgets; procurement coordination | M23: Manager | N23: SAP MM; MS Office | O23: Pakistan | P23: Passenger-transport fleet leader with depot, maintenance, vendor, budget and large-team responsibility. | Q23: Active | R23: =IF($A23="","",IFERROR(MINIFS(Candidates!$K$2:$K$2000,Candidates!$A$2:$A$2000,$A23),"")) -> 46291 | S23: =IF($A23="","",IFERROR(MAXIFS(Candidates!$AA$2:$AA$2000,Candidates!$A$2:$A$2000,$A23),"")) -> 46291 | T23: =IFERROR(__xludf.DUMMYFUNCTION("IF($A23="""","""",IFERROR(TEXTJOIN("", "",TRUE,UNIQUE(FILTER(Candidates!$B$2:$B$2000,Candidates!$A$2:$A$2000=$A23))),""""))"),"001") -> 001 | U23: =IF($A23="","",COUNTIF(Candidates!$A$2:$A$2000,$A23)) -> 1 | V23: =IFERROR(__xludf.DUMMYFUNCTION("IF($A23="""","""",IFERROR(INDEX(FILTER(Candidates!$S$2:$S$2000,Candidates!$A$2:$A$2000=$A23),COUNTIF(Candidates!$A$2:$A$2000,$A23)),""""))"),"Reject") -> Reject | W23: =IFERROR(__xludf.DUMMYFUNCTION("IF($A23="""","""",IFERROR(INDEX(FILTER(Candidates!$T$2:$T$2000,Candidates!$A$2:$A$2000=$A23),COUNTIF(Candidates!$A$2:$A$2000,$A23)),""""))"),"Rejected") -> Rejected | Y23: Rejected for Ref #001 only; retain for passenger transport, fleet, maintenance and depot-management roles. | Z23: 46291
A24: CAND-023 | B24: Rizwan Khan Bangash | C24: +92 300 6665444 | D24: rizwan6665444@gmail.com | E24: Karachi | F24: Centralized Warehouse & Inventory Control Manager | G24: AGI Denim | H24: 20 | I24: Supply Chain & Warehouse Operations | J24: Inventory / Production Planning / Lean | K24: Textile / Apparel / Manufacturing | L24: Warehouse operations; inventory; production planning; lean improvement; process re-engineering; ISO 9001; buyer audits | M24: Manager | N24: Scanning-based inventory systems; FoxPro | O24: Pakistan; global buyer coordination | P24: Supply-chain and warehouse leader with 20+ years across inventory, production planning, lean and operational excellence. | Q24: Active | R24: =IF($A24="","",IFERROR(MINIFS(Candidates!$K$2:$K$2000,Candidates!$A$2:$A$2000,$A24),"")) -> 46291 | S24: =IF($A24="","",IFERROR(MAXIFS(Candidates!$AA$2:$AA$2000,Candidates!$A$2:$A$2000,$A24),"")) -> 46291 | T24: =IFERROR(__xludf.DUMMYFUNCTION("IF($A24="""","""",IFERROR(TEXTJOIN("", "",TRUE,UNIQUE(FILTER(Candidates!$B$2:$B$2000,Candidates!$A$2:$A$2000=$A24))),""""))"),"001") -> 001 | U24: =IF($A24="","",COUNTIF(Candidates!$A$2:$A$2000,$A24)) -> 1 | V24: =IFERROR(__xludf.DUMMYFUNCTION("IF($A24="""","""",IFERROR(INDEX(FILTER(Candidates!$S$2:$S$2000,Candidates!$A$2:$A$2000=$A24),COUNTIF(Candidates!$A$2:$A$2000,$A24)),""""))"),"Reject") -> Reject | W24: =IFERROR(__xludf.DUMMYFUNCTION("IF($A24="""","""",IFERROR(INDEX(FILTER(Candidates!$T$2:$T$2000,Candidates!$A$2:$A$2000=$A24),COUNTIF(Candidates!$A$2:$A$2000,$A24)),""""))"),"Rejected") -> Rejected | X24: Rizwan Khan Bangash Resume.pdf | Y24: Rejected for Ref #001 only; retain for supply-chain, warehouse, inventory and manufacturing roles. | Z24: 46291
A25: CAND-024 | B25: Waqas Ali | C25: +92 306 7307079 | D25: waqasalisidhu06@gmail.com | E25: Bahawalpur | F25: Deputy Manager Operations | G25: Faisal Movers Express – Orange Line Metro Bus Project | H25: 10 | I25: Public Transport Operations | J25: Fleet / Dispatch / ITS | K25: Public Transit / Metro Bus | L25: Dispatch; route optimization; fleet scheduling; ITS; crisis response; stakeholder management; large-workforce supervision | M25: Manager | N25: ITS; CCTV; AVL; fleet tracking | O25: Pakistan | P25: Public-transport operations manager with 10+ years in fleet, dispatch, ITS and large-workforce management. | Q25: Active | R25: =IF($A25="","",IFERROR(MINIFS(Candidates!$K$2:$K$2000,Candidates!$A$2:$A$2000,$A25),"")) -> 46291 | S25: =IF($A25="","",IFERROR(MAXIFS(Candidates!$AA$2:$AA$2000,Candidates!$A$2:$A$2000,$A25),"")) -> 46291 | T25: =IFERROR(__xludf.DUMMYFUNCTION("IF($A25="""","""",IFERROR(TEXTJOIN("", "",TRUE,UNIQUE(FILTER(Candidates!$B$2:$B$2000,Candidates!$A$2:$A$2000=$A25))),""""))"),"001") -> 001 | U25: =IF($A25="","",COUNTIF(Candidates!$A$2:$A$2000,$A25)) -> 1 | V25: =IFERROR(__xludf.DUMMYFUNCTION("IF($A25="""","""",IFERROR(INDEX(FILTER(Candidates!$S$2:$S$2000,Candidates!$A$2:$A$2000=$A25),COUNTIF(Candidates!$A$2:$A$2000,$A25)),""""))"),"Reject") -> Reject | W25: =IFERROR(__xludf.DUMMYFUNCTION("IF($A25="""","""",IFERROR(INDEX(FILTER(Candidates!$T$2:$T$2000,Candidates!$A$2:$A$2000=$A25),COUNTIF(Candidates!$A$2:$A$2000,$A25)),""""))"),"Rejected") -> Rejected | X25: Waqas Ali CV.pdf | Y25: Rejected for Ref #001 only; retain for public transit, fleet, dispatch and transport-operations roles. | Z25: 46291
A26: CAND-025 | B26: M. Sohail Shahid | C26: +966 554513158 / +92 307 6261861 | D26: msohailshahid79@gmail.com | E26: Riyadh, Saudi Arabia | F26: Electronics Engineer | G26: Prince Sultan Military Medical City via Binjarallah Group | I26: Electronics Engineering | J26: Metro Operations / BMS / PTS | K26: Healthcare Engineering / Metro Rail / Building Automation | L26: Station operations; control room; incident response; CBTC/ATS; BMS/HVAC; PTS; troubleshooting | M26: Senior Professional | N26: Aerocom/AC3000; Sumetzberger; BMS/HMI/BAS; CBTC; ATS; HVAC controls | O26: Pakistan / Saudi Arabia | P26: Electronics engineer with five years of metro operations plus current building/medical transport-system engineering exposure. | Q26: Active | R26: =IF($A26="","",IFERROR(MINIFS(Candidates!$K$2:$K$2000,Candidates!$A$2:$A$2000,$A26),"")) -> 46291 | S26: =IF($A26="","",IFERROR(MAXIFS(Candidates!$AA$2:$AA$2000,Candidates!$A$2:$A$2000,$A26),"")) -> 46291 | T26: =IFERROR(__xludf.DUMMYFUNCTION("IF($A26="""","""",IFERROR(TEXTJOIN("", "",TRUE,UNIQUE(FILTER(Candidates!$B$2:$B$2000,Candidates!$A$2:$A$2000=$A26))),""""))"),"001") -> 001 | U26: =IF($A26="","",COUNTIF(Candidates!$A$2:$A$2000,$A26)) -> 1 | V26: =IFERROR(__xludf.DUMMYFUNCTION("IF($A26="""","""",IFERROR(INDEX(FILTER(Candidates!$S$2:$S$2000,Candidates!$A$2:$A$2000=$A26),COUNTIF(Candidates!$A$2:$A$2000,$A26)),""""))"),"Reject") -> Reject | W26: =IFERROR(__xludf.DUMMYFUNCTION("IF($A26="""","""",IFERROR(INDEX(FILTER(Candidates!$T$2:$T$2000,Candidates!$A$2:$A$2000=$A26),COUNTIF(Candidates!$A$2:$A$2000,$A26)),""""))"),"Rejected") -> Rejected | X26: Sohail_Shahid_Resume.pdf | Y26: Rejected for Ref #001 only; retain for engineering, metro operations, BMS/HVAC and control-room roles. | Z26: 46291
A27: CAND-026 | B27: Inam Ur Rehman | C27: 0307-0150150 | D27: inamu9581@gmail.com | E27: Lahore | F27: Supply Chain Executive (Logistics) | G27: Gourmet Foods Pakistan (Head Office) | H27: 8.6 | I27: Supply Chain & Logistics | J27: Warehouse / Dispatch / 3PL | K27: FMCG / Beverage / Warehousing / Distribution | L27: Logistics; dispatch; vehicle allocation; route scheduling; 3PL; inventory; warehouse operations; KPIs; cost optimization | M27: Senior Professional | N27: SAP ERP (MM/WM/EWM); WMS; PACE | O27: Pakistan | P27: Supply-chain and logistics professional with FMCG dispatch, 3PL/transporter, warehouse and SAP/WMS exposure. | Q27: Active | R27: =IF($A27="","",IFERROR(MINIFS(Candidates!$K$2:$K$2000,Candidates!$A$2:$A$2000,$A27),"")) -> 46291 | S27: =IF($A27="","",IFERROR(MAXIFS(Candidates!$AA$2:$AA$2000,Candidates!$A$2:$A$2000,$A27),"")) -> 46291 | T27: =IFERROR(__xludf.DUMMYFUNCTION("IF($A27="""","""",IFERROR(TEXTJOIN("", "",TRUE,UNIQUE(FILTER(Candidates!$B$2:$B$2000,Candidates!$A$2:$A$2000=$A27))),""""))"),"001") -> 001 | U27: =IF($A27="","",COUNTIF(Candidates!$A$2:$A$2000,$A27)) -> 1 | V27: =IFERROR(__xludf.DUMMYFUNCTION("IF($A27="""","""",IFERROR(INDEX(FILTER(Candidates!$S$2:$S$2000,Candidates!$A$2:$A$2000=$A27),COUNTIF(Candidates!$A$2:$A$2000,$A27)),""""))"),"Reject") -> Reject | W27: =IFERROR(__xludf.DUMMYFUNCTION("IF($A27="""","""",IFERROR(INDEX(FILTER(Candidates!$T$2:$T$2000,Candidates!$A$2:$A$2000=$A27),COUNTIF(Candidates!$A$2:$A$2000,$A27)),""""))"),"Rejected") -> Rejected | X27: Inam Ur Rehman.pdf | Y27: Rejected for Ref #001 only; retain for supply-chain, logistics, warehouse and distribution roles. | Z27: 46291
A28: CAND-027 | B28: Habab Bin Ayyaz | C28: +92 (323) 471-7225 | D28: hababbinayyaz@gmail.com | E28: Lahore, Pakistan | F28: Assistant Operations Manager | G28: Elite Chauffeured Service Inc. | H28: 4 | I28: Ground Transportation Operations | J28: Limo / Chauffeur Dispatch & Operations | K28: Limo / Chauffeur / Luxury Ground Transportation | L28: Chauffeur operations; limo dispatch; trip assignment and confirmation; passenger requirements; corporate accounts; travel agencies; DMCs; hotels; affiliate networks; service-issue monitoring | M28: Manager | N28: Limo Anywhere; Moovs; GNet; Crewslink | O28: USA (Washington D.C. / New York) / Canada | P28: Luxury ground-transportation professional with direct US chauffeur operations, lead-dispatch experience, affiliate-network exposure and hands-on limo-platform expertise. | Q28: Active | R28: =IF($A28="","",IFERROR(MINIFS(Candidates!$K$2:$K$2000,Candidates!$A$2:$A$2000,$A28),"")) -> 46291 | S28: =IF($A28="","",IFERROR(MAXIFS(Candidates!$AA$2:$AA$2000,Candidates!$A$2:$A$2000,$A28),"")) -> 46291 | T28: =IFERROR(__xludf.DUMMYFUNCTION("IF($A28="""","""",IFERROR(TEXTJOIN("", "",TRUE,UNIQUE(FILTER(Candidates!$B$2:$B$2000,Candidates!$A$2:$A$2000=$A28))),""""))"),"001") -> 001 | U28: =IF($A28="","",COUNTIF(Candidates!$A$2:$A$2000,$A28)) -> 1 | V28: =IFERROR(__xludf.DUMMYFUNCTION("IF($A28="""","""",IFERROR(INDEX(FILTER(Candidates!$S$2:$S$2000,Candidates!$A$2:$A$2000=$A28),COUNTIF(Candidates!$A$2:$A$2000,$A28)),""""))"),"Priority Shortlist") -> Priority Shortlist | W28: =IFERROR(__xludf.DUMMYFUNCTION("IF($A28="""","""",IFERROR(INDEX(FILTER(Candidates!$T$2:$T$2000,Candidates!$A$2:$A$2000=$A28),COUNTIF(Candidates!$A$2:$A$2000,$A28)),""""))"),"Shortlisted") -> Shortlisted | X28: Habab Ayyaz.pdf | Y28: Priority Shortlist for Ref #001. Retain for future limo/chauffeur, dispatch, mobility and premium ground-transportation roles. | Z28: 46291
A29: CAND-028 | B29: Jaffir Iqbal | C29: +92302-9113015 | D29: jaffiriqbal@gmail.com | E29: Tehsil Kabirwala, District Khanewal, Pakistan | F29: Assistant Manager Production | G29: Cakes & Bakes Private Limited | H29: 9 | I29: Food Manufacturing Production and Operations | J29: Bakery production, food quality assurance, food safety and process control | K29: Bakery, biscuits, confectionery, snacks, sauces, jams, frozen foods, beverages and agricultural raw-material quality | L29: Production planning, daily production reporting, target delivery, multi-category batch manufacturing, recipe standardization, quality control, GMP, GHP, HACCP coordination, ISO 9001:2015 documentation, Halal compliance, hygiene management, worker training, waste reduction, root-cause investigation, export-order fulfillment and new-product development | M29: Manager | N29: ERP, advanced Microsoft Excel, Microsoft Word, Outlook and PowerPoint | O29: Pakistan-based manufacturing experience in Lahore and Multan, with responsibility for fulfilling export-order production demand | P29: Food technologist and production professional with approximately nine years of food-industry experience across bakery, confectionery, snacks, sauces, frozen products and agricultural raw-material quality. Currently leads production activities at Cakes & Bakes, covering planning, reporting, target delivery, product quality, food-safety compliance, workforce training, waste control and multi-category manufacturing. Holds BS and M.Sc. qualifications in Food Science and Food Technology. | Q29: Active | R29: 46292 | S29: 46292 | T29: 002 | U29: 1 | V29: Priority Shortlist | W29: Shortlisted | Y29: Priority Shortlist for Ref #002. Retain for future Food Manufacturing Production and Operations roles. | Z29: 46292.096
A30: CAND-029 | B30: Jawad Ahmed | C30: +92 314-8002002 | D30: jawad4157@yahoo.com | E30: Karachi, Sindh, Pakistan | F30: Manager – Export Sales and Marketing | G30: International Steels Limited | H30: 16.6 | I30: Export Sales and International Business Development | J30: Steel manufacturing operations, production planning and cross-functional export fulfillment | K30: Flat steel manufacturing, cold rolling, industrial engineering, manufacturing operations and international B2B/B2C sales | L30: Export strategy, international market development, key-account management, contract and pricing negotiation, budgeting, revenue forecasting, production coordination, process optimization, lean manufacturing, quality control, regulatory compliance, project management and team leadership | M30: Manager | N30: Oracle ERP, AutoCAD, SolidWorks, MATLAB and Microsoft Project | O30: Pakistan, Afghanistan, Sri Lanka, UAE, Oman, Qatar, Jordan, Australia, Saudi Arabia, Kuwait, and North, South, East and Central African markets | P30: Mechanical engineer and Executive MBA professional with more than 16 years of experience spanning manufacturing operations, production leadership, engineering projects and export sales. Progressed within International Steels Limited from operations engineering and production management into export sales leadership, delivering measurable export revenue growth, new-market entry and stronger export contribution while coordinating commercial requirements with production, planning, logistics, supply chain and finance. | Q30: Active | R30: 46292 | S30: 46292 | T30: 003 | U30: 1 | V30: Reject | W30: Rejected | Y30: Rejected for Ref #003 only; retain for future Export Sales and International Business Development roles. | Z30: 46292.282
A31: CAND-030 | B31: Muhammad Taskeen | C31: +92 300 6676139 / +92 333 6676139 | D31: muhammadtaskeen@gmai.com / muhammadtaskeen@outlool.com | E31: Faisalabad, Pakistan | F31: Security Supervisor | G31: Marine Security Service (Pvt) | H31: 27.4 | I31: Transport and Fleet Operations | J31: Mechanical transport supervision, fleet maintenance coordination, driver administration, road safety, and private security supervision | K31: Pakistan Air Force and military transport operations; fleet administration; vehicle operations and maintenance coordination; private security services | L31: Fleet management, daily transport operations, driver coordination, duty rostering, vehicle inspections, preventive maintenance scheduling, fuel monitoring, incident investigation, transport documentation, road safety, defensive-driving instruction, personnel discipline, and training | M31: Officer / Command | N31: Vehicle Management Systems (VMS), Microsoft Word, Excel, PowerPoint and Outlook, Google Docs, Sheets and Drive, digital record-keeping tools, email and internet applications | O31: Pakistan-based experience, principally in Pakistan Air Force operations and private security; no international market exposure evidenced | P31: Transport and fleet operations professional with approximately 23 years of Pakistan Air Force service, specializing in mechanical transport operations, fleet readiness, driver supervision, preventive maintenance coordination, fuel control, safety, and operational documentation. Currently works as a Security Supervisor in the private sector. Holds an MSc in Mass Communication, an HTV driving licence, and military training in transport instruction, leadership, vehicle management systems, mechanical transport driving, and VIP staff-car driving. | Q31: Active | R31: 46292 | S31: 46292 | T31: 001 | U31: 1 | V31: Reject | W31: Rejected | Y31: Rejected for Ref #001 only; retain for future Transport and Fleet Operations roles. | Z31: 46292.494
A32: CAND-031 | B32: Husnain Raza Rahat | C32: 0304-0743974 | D32: husnainhadi899@gmail.com | E32: Mongi Bangla, Tehsil Gojra, District Toba Tek Singh, Pakistan | F32: Assistant Manager (Production & Quality) | G32: Merit | H32: 4 | I32: Food Manufacturing Production and Quality Management | J32: Food Safety, Quality Assurance and Bakery Production Operations | K32: Food processing, bakery manufacturing, bread and baked goods, sweets and burgers, perishable/FMCG manufacturing | L32: Production monitoring and planning; bakery-line control; production efficiency; waste reduction; root-cause problem-solving; preventive maintenance coordination; raw-material and finished-goods testing; food-safety and quality enforcement; GMP and Halal training; quality and food-safety audits; sanitation and hygiene inspection; regulatory compliance; IPM protocol; complaint handling; shelf-life studies; worker training and team leadership | M32: Manager | N32: SAP S/4HANA; quality reports and controlled documentation | O32: Pakistan; employment and residence exposure in Punjab, including Gojra/Toba Tek Singh. No international market exposure evidenced. | P32: Food science professional with documented progression through quality assurance, food safety, production shift supervision and assistant management in Pakistani bakery and food-manufacturing organizations. Experience covers production-line monitoring, product quality, efficiency improvement, waste control, machinery and maintenance oversight, food-safety auditing, regulatory implementation and workforce training. | Q32: Active | R32: 46293 | S32: 46296 | T32: 002, 004 | U32: 2 | V32: Reject | W32: Rejected | X32: https://drive.google.com/file/d/1pQilDW7AzbuKklxsZ46MCAmYuTeaECVf/view?usp=drivesdk | Y32: Rejected for Ref #004 only; retain for future Food Manufacturing Production and Quality Management roles. | Z32: 46296.228
A33: CAND-032 | B33: Zeeshan Tarar | C33: 0345-4914004 | D33: zeeshan_tarar36@yahoo.com | F33: Assistant Manager Procurement | G33: Ajmair Foods | H33: 10 | I33: Procurement and strategic sourcing | J33: Food and raw-material procurement, supplier management, commercial negotiation and procurement reporting | K33: Food products, fruit procurement, raw-material sourcing and industrial procurement | L33: Strategic sourcing, supplier identification and evaluation, vendor relationship management, contract negotiation, cost analysis, procurement strategy, purchase-order management, supplier-performance reporting, logistics coordination, budget monitoring and supply-issue resolution | M33: Head / Director | N33: ERP training; unnamed procurement software; purchase-order tracking; procurement data analysis and management reporting | O33: Domestic supplier and vendor-market exposure; specific geographic coverage is not evidenced | P33: Procurement professional with approximately 10 years of experience across food and raw-material purchasing. Career progression includes Procurement and Research Officer, Fruit Procurement Head and Assistant Manager Procurement roles, with responsibility for supplier evaluation, negotiation, contracts, purchase orders, cost optimization, reporting, logistics coordination and cross-functional stakeholder management. | Q33: Active | R33: 46293 | S33: 46296 | T33: 004 | U33: 1 | V33: Reject | W33: Rejected | X33: https://drive.google.com/file/d/1kZbWCNdECoiACxOlAyOQNhp19dExclI2/view?usp=drivesdk | Y33: Rejected for Ref #004 only; retain for future Procurement and strategic sourcing roles. | Z33: 46296.187
A34: CAND-033 | B34: Abdul Ghaffar | C34: +92 305 4942108 | D34: agmohsinbutt5cwak_5hk@indeedemail.com | E34: Lahore | F34: Sr. Executive Supply Chain | G34: Quick Food Industries Pvt. Ltd. (MonSalwa) | H34: 15.1 | I34: Procurement and Supply Chain | J34: Plant purchasing, industrial materials sourcing, supplier coordination and distribution | K34: Food processing, FMCG manufacturing, export manufacturing, industrial materials, construction materials and distribution | L34: Plant procurement; sourcing from manufacturers and importers; food ingredients and packaging purchasing; electrical, mechanical, fabrication, lubricants and construction-material purchasing; supplier account handling; payment coordination; distribution and cold-store coordination; local market sourcing | M34: Manager | N34: Basic Microsoft Office, internet browsing and general computer use; no ERP or dedicated procurement system specified | O34: Lahore market, Faisalabad second-hand market and sourcing connections to Karachi, Pakistan | P34: Procurement and supply-chain professional with approximately 15 years of documented experience, including more than 11 years at K&N's Foods. Experienced in independently managing plant purchasing across food ingredients, packaging, electrical, mechanical, fabrication, lubricants and construction categories, with additional exposure to distribution, cold stores, supplier payments and local market sourcing. | Q34: Active | R34: 46294 | S34: 46296 | T34: 004 | U34: 1 | V34: Reject | W34: Rejected | X34: https://drive.google.com/file/d/1dJQh0JBWSXzS5N9Hc8INE8K3LRJEgIpa/view?usp=drivesdk | Y34: Rejected for Ref #004 only; retain for future Procurement and Supply Chain roles. | Z34: 46296.187
A35: CAND-034 | B35: Muhammad Zohaib Manzoor | C35: 0321-6883884 | D35: mzohaib330@yahoo.com | E35: Lahore, Pakistan | F35: Assistant Manager | G35: Cakes and Bakes (Ajmair Foods Pvt. Limited) | H35: 16.7 | I35: Procurement and Purchasing | J35: Technical, general and raw-material sourcing; supplier management; purchasing coordination | K35: Bakery and food production, automotive and tractor manufacturing, industrial manufacturing, textile manufacturing, maintenance and engineering projects | L35: End-to-end purchasing, supplier sourcing and evaluation, supplier relationship management, quotation collection, commercial negotiation, purchase-order administration, comparative statements, raw-material procurement, technical procurement, material requisitions, BOQ preparation, delivery follow-up and cross-functional coordination | M35: Manager | N35: IFS ERP, Microsoft Word, Excel and PowerPoint, MS Project, MS Visio; exposure to production, work-order, shop-order and purchase-part records | O35: Pakistan, primarily Lahore-based operations; no international market exposure evidenced | P35: Procurement professional with experience in bakery and food-production purchasing, automotive manufacturing, industrial projects and production-support operations. Currently handles end-to-end technical, general and raw-material procurement as an Assistant Manager, with responsibilities spanning supplier sourcing, evaluation, negotiation, purchase orders and delivery coordination. Earlier experience includes general purchasing, project coordination, ERP-based manufacturing records, production reporting and personnel administration. | Q35: Active | R35: 46294 | S35: 46294 | T35: 004 | U35: 1 | V35: Reject | W35: Rejected | Y35: Rejected for Ref #004 only; retain for future Procurement and Purchasing roles. | Z35: 46293.959
A36: CAND-035 | B36: Umair Hassan Ghori | C36: 0332-2267345 | D36: tcsumair@gmail.com.pk | E36: Karachi, Pakistan | F36: Logistics Operations Manager | G36: PacknGo | H36: 14.7 | I36: Logistics and Operations Management | J36: Relocation operations, corporate customer service, quality assurance, claims and service recovery | K36: Express logistics, home and corporate relocation, final-mile delivery, contact centers, customer service, IT support and media production | L36: End-to-end shipment and relocation coordination, corporate account management, surveys, costing, quotations, packing and transport coordination, vendor negotiation, claims handling, complaint resolution, QA, KPI and SOP monitoring, master data, barcode processing, reporting and MIS | M36: Manager | N36: Microsoft Office, reporting and MIS tools, SQL, HTML, MikroTik, ISA Server, Windows Server, computer hardware and software troubleshooting, networking, barcode and master-data processes, AI productivity tools | O36: Pakistan market exposure, primarily Karachi; no explicit international or US market exposure stated | P36: Logistics and customer-service professional with approximately 14+ years of experience spanning express logistics, relocation operations, corporate accounts, shipment coordination, final-mile delivery, claims, complaint resolution, quality assurance, contact-center operations, reporting and IT support. Progressed from customer-service and supervisory roles into relationship and logistics operations management. | Q36: Active | R36: 46295 | S36: 46295 | T36: 001 | U36: 1 | V36: Reject | W36: Rejected | Y36: Rejected for Ref #001 only; retain for future Logistics and Operations Management roles. | Z36: 46295.176
A37: CAND-036 | B37: Bilal Mustafa | E37: Lahore, Punjab, Pakistan | F37: Sales and Dispatch Operations Manager | G37: Nationwide Chauffeured Services | H37: 9.8 | I37: Sales and Operations Management | J37: Chauffeured transportation dispatch, fleet operations and revenue development | K37: Limousine and black-car services, chauffeured passenger transportation, logistics, real estate sales, healthcare and clinical nutrition | L37: End-to-end sales pipeline management, lead generation, deal closure, dispatch operations, fleet coordination, logistics optimization, VIP transportation, team leadership, KPI management, telesales, corporate client servicing and relationship management | M37: Manager | N37: No specific systems or software evidenced | O37: Pakistan, United States and United Arab Emirates; experience serving corporate, event, international-investor, high-net-worth and VIP client segments | P37: Sales and dispatch operations manager with approximately 9.8 years of experience spanning chauffeured transportation, limousine and black-car operations, sales leadership and logistics coordination. Has managed regional-fleet dispatch, corporate and event transportation, cross-functional teams and KPI-driven service delivery, including USD 4 million in reported transportation sales during ICC World Cup operations. Also brings Dubai real estate sales exposure and an academic and professional background in clinical nutrition. | Q37: Active | R37: 46296 | S37: 46296 | T37: 001 | U37: 1 | V37: Priority Shortlist | W37: Shortlisted | X37: https://drive.google.com/file/d/1JZ7e9F2afTCc94g7Gbul3yIF50xpNixG/view?usp=drivesdk | Y37: Priority Shortlist for Ref #001. Retain for future Sales and Operations Management roles. | Z37: 46296.157
A38: CAND-037 | B38: Malik Muhammad Touseef | C38: 0334 4145271 | D38: touseef_malik65@yahoo.com | E38: Lahore, Pakistan | F38: Admin & Supply Chain Officer | G38: The Diabetes Center | H38: 31.3 | I38: Procurement, supply chain and store operations | J38: Administration, inventory control, vendor coordination and purchasing | K38: Bakery and confectionery, restaurants and hospitality, healthcare/clinical services, furniture manufacturing and export, food products, software back-office services, trading and government taxation | L38: Raw-material purchasing, vendor and supplier dealing, store management, inventory monitoring, stock reporting, material issuance, sourcing, administration, employee and vendor records, export documentation, sales, public dealing and branch operations | M38: Officer / Command | N38: No named ERP, procurement, inventory or office software evidenced; experience includes stock reports, store statements, vendor records, business reports, tenders and export documentation | O38: Primarily Lahore and Pakistan; domestic sourcing from Chiniot and other Pakistani areas, plus export-shipment documentation for a UK-based furniture company | P38: Operations professional with more than three decades of stated experience across purchasing, stores, administration, sales and branch management. Career experience includes long-term bakery raw-material procurement and inventory responsibility, restaurant purchasing and stock control, furniture sourcing and export documentation, and current administration and supply-chain duties in a diabetes clinic. | Q38: Active | R38: 46296 | S38: 46296 | T38: 004 | U38: 1 | V38: Reject | W38: Rejected | X38: https://drive.google.com/file/d/1wJRPYV-TCXeLgeEHgnb75yBQtAxHpjBx/view?usp=drivesdk | Y38: Rejected for Ref #004 only; retain for future Procurement, supply chain and store operations roles. | Z38: 46296.187
A39: CAND-038 | B39: Khan Hassam Zain | C39: +966540245762 | D39: khanhassamzain50@gmail.com | E39: Dammam, Saudi Arabia; permanent address listed in Gujranwala, Pakistan | F39: Assistant Production Manager | G39: Kufa Food Company | H39: 8.3 | I39: Food Manufacturing Production Management | J39: Bakery and sweets production, food safety, quality compliance and plant operations | K39: Food manufacturing; bakery; sweets and confectionery; pizza; perishable food production; food safety and Halal compliance | L39: Production and shift planning, production-process supervision, plant workforce administration, GMP, GHP, food hygiene, product inspection, retention samples, shelf-life records, food-safety and Halal audits, corrective and preventive actions, SOP development, IPM inspections, complaint and non-conformance investigation, and employee training | M39: Individual Contributor | N39: Operational production system mentioned but not named; production and shelf-life record maintenance. No specific ERP, MIS, spreadsheet or reporting platform documented. | O39: Pakistan and Saudi Arabia; employment experience documented in Lahore and Dammam, with education and training in Lahore, Rawalpindi and Islamabad | P39: Food-production professional with experience progressing from Production Executive to Production Manager and Assistant Production Manager. Career exposure covers bakery, sweets, pizza and broader food-company operations, supported by postgraduate food-science education and lead-auditor certifications in FSSC 22000 and Halal standards. | Q39: Active | R39: 46296 | S39: 46296 | T39: 002 | U39: 1 | V39: Shortlist | W39: Shortlisted | X39: https://drive.google.com/file/d/1ei0w2ebZzN31AnU7iYO3Kltjdg_RU6YA/view?usp=drivesdk | Y39: Shortlist for Ref #002. Retain for future Food Manufacturing Production Management roles. | Z39: 46296.214 | AA39: Food Science and Technology professional with approximately eight years of documented food-production experience. Experienced in production supervision, shift planning, plant staffing, hygiene and food-safety controls, audits, CAPA, SOP management, complaint investigation and workforce training. Holds an M.Phil. in Food Science & Technology, a B.Sc. (Hons) in Agriculture and Food Technology, and lead-auditor certifications in FSSC 22000 V5 and HALAL PS3733:2019. | AB39: Kufa Food Company, Dammam — Assistant Production Manager, March 2022–present. Manages shift plans, supervises production processes and plant personnel, verifies GMP/GHP, maintains retention and shelf-life records, conducts inspections and audits, implements CAPA, develops SOPs, investigates complaints and provides compliance training. Hafiz Sweets, Lahore — Production Manager, 3 years; involved in Laraib Bakers & Sweets, Hafiz Sweets Live Pizza and Laraib Live Pizza projects. Gourmet Foods, Lahore, Bakery Plant — Production Executive, 2 years. NARC, Islamabad — Intern, 3 months. | AC39: M.Phil. Food Science & Technology, University of Management & Technology, Lahore, 2019–2021. B.Sc. (Hons) Agriculture, Food Technology, PMAS-Arid Agriculture University Rawalpindi, 2014–2018. F.Sc. Pre-Medical, BISE Gujranwala, 2012–2014. Matriculation in Science, BISE Gujranwala. Professional certifications: Lead Auditor FSSC 22000 V5 and Lead Auditor HALAL PS3733:2019.
A40: CAND-039 | B40: Farooq Haider | C40: +92-305-5997857; +92-316-5997857 | D40: farooqhaiderft@gmail.com | E40: Lahore, Pakistan | F40: Production Manager | G40: ATA Bakery Solutions (Pvt.) Ltd. (Bread and Beyond) | H40: 15 | I40: Food Manufacturing Operations and Production Management | J40: Bakery Process Technology, New Product Development, Quality Assurance and Plant Operations | K40: Bakery, biscuits, cookies, crackers, bread, cakes, muffins, tortillas, wafers, confectionery, chocolate, snacks and broader food processing | L40: Production planning and control; plant operations; process troubleshooting; baking science and technology; bakery product development; R&D; quality assurance; food safety; ISO and HACCP implementation; Halal compliance; waste and yield reduction; preventive maintenance coordination; workforce leadership; KPI management; process improvement; raw-material inspection; EHS; documentation and reporting | M40: Senior Professional | N40: SAP S/4HANA; SAP ERP Central Component (ECC); Microsoft Word; Microsoft Excel; Microsoft PowerPoint; Windows; email and internet tools | O40: Pakistan and Dubai, United Arab Emirates | P40: Food-industry professional with a continuous career spanning quality assurance, production supervision, R&D, operations management, plant management and production management. Experience is concentrated in bakery, biscuits, cakes, wafers, confectionery and snacks, with responsibility for production, quality, R&D, maintenance coordination, food-safety compliance and workforce performance. | Q40: Active | R40: 46296 | S40: 46296 | T40: 004 | U40: 1 | V40: Reject | W40: Rejected | X40: https://drive.google.com/file/d/1o73RNoNdiRsx1EDA45sse7xd7FcStyad/view?usp=drivesdk | Y40: Rejected for Ref #004 only; retain for future Food Manufacturing Operations and Production Management roles. | Z40: 46296.227 | AA40: Food technologist and manufacturing leader with approximately 15 years of experience across bakery and food-processing operations in Pakistan and the UAE. Has managed production, QA, R&D and maintenance teams and worked on process control, line efficiency, waste reduction, food-safety systems and bakery product development. Product exposure includes biscuits, cookies, crackers, bread, cakes, muffins, tortillas, wafers, confectionery, chocolate and snacks. | AB40: ATA Bakery Solutions (Pvt.) Ltd. / Bread and Beyond — Production Manager, Feb 2022–present: Oversees plant production, QA, R&D and maintenance personnel, production and quality records, safety standards and operational planning. The Snack Bites Company / Snacks & Co. — Plant Manager, Jul 2020–Feb 2022: Responsible for production, QA, R&D and maintenance operations. Silver Lake Foods Ltd., S.M Foods Makers Ltd. and Volka Foods International — Manager Production, May 2018–Jul 2020: Led production and maintenance activities; supported supplier quality requirements, ISO/HACCP/Halal compliance, hygiene, EHS, maintenance planning, staffing and management reporting. Backersland / M.A Foods — Operations Manager, Aug 2017–May 2018: Managed production, QA, R&D and maintenance; improved line efficiency, controlled waste and material variances, and supported biscuit product development and cost reduction. Signature Snacks, Dubai, UAE — Research and Development Officer, Mar 2017–Aug 2017: Supported R&D programs, product and process introduction, and product/process cost improvement. Asian Foods / Mayfair Pvt. Ltd. — Assistant Manager Production, Aug 2013–Feb 2017: Managed production lines, KPIs, workforce utilization, raw-material efficiency, waste, yield, product quality and SAP production data. Continental Biscuit Ltd. — Senior Production Officer, Mar 2010–Aug 2013: Managed manufacturing staff, workflow, production schedules, process controls, systems, safety and product integrity. Gourmet Foods — Quality Assurance Executive, Jul 2009–Mar 2010: Conducted QA/QC compliance, finished-product inspection, hygiene monitoring and laboratory inspection of raw materials. Haleeb Foods — Intern, Quality and Production Department, 2008: Completed a 14-week internship in quality assurance. | AC40: MSc (Hons) Food Technology, University of Agriculture Faisalabad, 2008–2010; research project: Development, Characterization and Shelf Life Study of Date Buns. BSc (Hons) Agriculture, University of Agriculture Faisalabad, 2004–2008. FSc Pre-Medical, BISE Bahawalpur, 2002–2004. Matriculation, BISE Bahawalpur, 2000–2002. Six-month Diploma in Meat Production and Processing, National Vocational & Technical Education Commission / University of Agriculture Faisalabad, 2007–2008. Member, Board of Study, Department of Human Nutrition and Food Technology, Faculty of Allied Health Sciences, Superior University Lahore, 2023–present.
A41: CAND-040 | B41: Muhammad Waqas Naeem | C41: +923225908112 | D41: mwn.1583@gmail.com | E41: Lahore, Pakistan | F41: Production Manager | G41: Dawn Bread | I41: Production and Manufacturing Operations | J41: Industrial bakery production, process optimization, food quality and food-safety management | K41: Industrial bakery, food manufacturing, FMCG and beverage manufacturing exposure | L41: High-speed bakery operations; production planning; process efficiency; capacity utilization; product troubleshooting; waste and production-loss reduction; product-quality improvement; new product development; GMP; HACCP; internal and external audits; corrective actions; production-team and labor management; staff training; problem-solving | M41: Manager | N41: SAP S/4HANA Production Planning module as Business Process Owner; Oracle system software; Bunny's management system | O41: Pakistan and United Arab Emirates; bakery production experience supporting operations in Pakistan and the UAE | P41: Food technologist and bakery manufacturing professional with documented experience progressing from Assistant Manager Production to Production Supervisor and Production Manager. Career exposure covers high-volume breads, buns, Arabic bread, croissants, biscuits, cakes, muffins, rusks and related bakery products, with responsibility for production targets, process efficiency, quality, food safety, audits and team management. | Q41: Active | R41: 46296 | S41: 46296 | T41: 004 | U41: 1 | V41: Reject | W41: Rejected | X41: https://docs.google.com/document/d/1sv4_R7dWzqdEA8LNI1_9Il8oxPslXsCy/edit?usp=drivesdk&ouid=100269677063860344655&rtpof=true&sd=true | Y41: Rejected for Ref #004 only; retain for future Production and Manufacturing Operations roles. | Z41: 46296.228 | AA41: Bakery production professional with more than 11 years of stated FMCG and industrial bakery experience. Experienced in managing high-speed production lines, capacity utilization, downtime, waste reduction, product troubleshooting, quality improvement, HACCP, GMP, internal audits and production teams. Holds postgraduate and undergraduate qualifications in Food Technology and has worked in Pakistan and the UAE. | AB41: Dawn Bread — Production Manager, 19 August 2019–present: Leads bakery production operations with responsibility for targets, process efficiency, capacity utilization, production losses, product quality, continuous improvement, production staff, food-safety systems and corrective actions. Al Jadeed Bakery L.L.C., UAE — Production Supervisor; additional charge as Quality Controller and Internal Auditor, 26 March 2017–25 April 2019: Industrial production exposure across loaf bread, buns, croissants, Arabic bread, biscuits, cakes, muffins, rusks, traditional roti and Danish pastry. Bunny's Limited, Lahore — Assistant Manager Production, 1 January 2013–24 March 2017: High-volume automated production of breads, buns, burgers, rusks, cakes, biscuits, croissants and confectionery products. Pepsi Plant, Lahore — Intern, 3 March 2010–15 May 2010. | AC41: M.Sc. (Hons.) Food Technology, University of Agriculture, Faisalabad, Pakistan, 2010–2012. B.Sc. (Hons.) Agriculture (Food Technology), University of Agriculture, Faisalabad, Pakistan, 2006–2010. Intermediate in Physics, Chemistry and Biology, F.G. Inter College Mangla Cantt, 2004–2006. Matriculation in Science Subjects, F.G. Public School Mangla Cantt, 2001–2003. Additional training: Highfield Awarding Body for Compliance UK PIC Level 3 passed with merit; Food Safety Levels 3 and 4; fire safety; basic food hygiene.
A42: CAND-041 | B42: Muhammad Amir Sohail | C42: +92 303 6495591 | D42: amirsohailofficial5@gmail.com | E42: Khanewal, Pakistan; currently employed in Lahore | F42: Assistant Manager Production and Quality (Export) | G42: Bundu Khan Foods | I42: Food Manufacturing Production and Operations | J42: Production Quality, Food Safety, Export Operations and Product R&D | K42: Food manufacturing; bakery and sweets; sauces and mayonnaise; frozen bakery products; export food production; quality assurance and food safety | L42: Production planning and scheduling, demand-based production planning, production-team supervision, quality control, food-safety implementation, HACCP and ISO compliance, GMPs, inspections, SOP and checklist development, product R&D, shelf-life enhancement, recipe costing, material and overhead-cost analysis, inventory control, waste management, export documentation and staff training | M42: Manager | N42: ERP software, NRP as stated in the CV, Microsoft Office, Google Drive and production/quality-control records | O42: Pakistan-based experience in Lahore and Multan; project leadership for bakery products exported to the UK; current export-production responsibilities | P42: Food-production professional who progressed from Production Executive to Assistant Manager roles spanning production, R&D, quality and export operations. Experience covers bakery, sweets, sauces, frozen products, food-safety systems, production costing, inventory and workforce supervision. | Q42: Active | R42: 46296 | S42: 46296 | T42: 002 | U42: 1 | V42: Hold | W42: Hold | X42: https://drive.google.com/file/d/1iaS_IPREJRtxZES0zWkP7uXRkoZ8kn_t/view?usp=drivesdk | Y42: On hold for Ref #002; retain for future Food Manufacturing Production and Operations roles. | Z42: 46296.471
A43: CAND-042 | B43: Abbas Raza Shafqat | C43: +92 3202270704 | D43: abbasrazashafqat@gmail.com | E43: Lahore, Punjab, Pakistan | F43: Procurement Coordinator | G43: Action International Services L.L.C | H43: 4.2 | I43: Procurement and Supply Chain Management | J43: Supplier sourcing, inventory planning, warehouse coordination and purchasing operations | K43: Construction services, manufacturing, health and beauty products, HVAC/electrical equipment, warehousing and customer service | L43: Local and international sourcing, supplier identification and evaluation, quotation comparison, commercial negotiation, contract coordination, purchase-order processing, demand forecasting, inventory control, replenishment, logistics planning, supplier performance monitoring, KPI reporting, supplier quality coordination, audit support and customer service | M43: Individual Contributor | N43: Microsoft Excel, Word, Access, PowerPoint and Outlook; ERP inventory systems; SAP MM; SPSS; Adobe Photoshop, Illustrator and InDesign; Microsoft Teams, Zoom, Google Meet and Skype | O43: Professional experience in Lahore, Pakistan and Dubai, United Arab Emirates, including sourcing from local and international markets | P43: Career progression from customer service into supply-chain internships, manufacturing operations, warehouse management and procurement coordination. Experience spans Pakistan and the UAE, with the longest role focused on construction-sector procurement, supplier coordination, inventory planning and logistics. | Q43: Active | R43: 46297 | S43: 46297 | T43: 004 | U43: 1 | V43: Reject | W43: Rejected | X43: https://drive.google.com/file/d/1Vp65sxiaKs7p1W4FcfYVa6xEN6bTr1k4/view?usp=drivesdk | Y43: Rejected for Ref #004 only; retain for future Procurement and Supply Chain Management roles. | Z43: 46296.526 | AA43: Procurement and supply-chain professional with experience in local and international sourcing, supplier evaluation, commercial negotiation, purchase-order administration, demand forecasting, inventory control, logistics coordination and KPI reporting. Holds a BBA Honours with a specialization in Supply Chain Management and has worked across construction services, manufacturing, health and beauty, HVAC/electrical equipment and customer service environments in Pakistan and the UAE. | AB43: [{"end_date":"12/07/2024","location":"Dubai, United Arab Emirates","designation":"Procurement Coordinator","start_date":"10/01/2022","company_name":"Action International Services L.L.C"},{"designation":"Warehouse Assistant (Supply Chain)","location":"Lahore, Pakistan","end_date":"06/05/2021","start_date":"22/11/2020","company_name":"Hammé (Anfaa Health & Beauty) (Boss Group of Companies)"},{"start_date":"02/02/2020","company_name":"Organo Pure (Pvt) Limited","designation":"Operations Manager","location":"Lahore, Pakistan","end_date":"29/06/2020"},{"designation":"Supply Chain Management Intern","company_name":"Cool Point (Pvt) Limited","start_date":"31/05/2019","location":"Lahore, Pakistan","end_date":"30/08/2019"},{"designation":"Domestic Customer Service Executive","start_date":"01/11/2016","location":"Lahore, Pakistan","company_name":"TRG (IBEX-Global)","end_date":"28/05/2017"}] | AC43: [{"qualification":"Bachelor of Business Administration Honours (BBA Hons), Specialization in Supply Chain Management","institution":"The University of Lahore","location":"Lahore, Pakistan","end_date":"17/02/2020","start_date":"25/08/2015"},{"institution":"Islamia Boys High Collage Quetta","start_date":"13/11/2013","qualification":"Intermediate (Pre-Engineering)","location":"Quetta, Pakistan","end_date":"26/07/2015"},{"start_date":"01/03/1998","location":"Quetta, Pakistan","qualification":"Matriculation (Computer Science)","institution":"ST. Francis Grammar High School","end_date":"28/06/2013"}]
R44: =IF($A44="","",IFERROR(MINIFS(Candidates!$K$2:$K$2000,Candidates!$A$2:$A$2000,$A44),"")) | S44: =IF($A44="","",IFERROR(MAXIFS(Candidates!$AA$2:$AA$2000,Candidates!$A$2:$A$2000,$A44),"")) | T44: =IFERROR(__xludf.DUMMYFUNCTION("IF($A44="""","""",IFERROR(TEXTJOIN("", "",TRUE,UNIQUE(FILTER(Candidates!$B$2:$B$2000,Candidates!$A$2:$A$2000=$A44))),""""))"),"") | U44: =IF($A44="","",COUNTIF(Candidates!$A$2:$A$2000,$A44)) | V44: =IFERROR(__xludf.DUMMYFUNCTION("IF($A44="""","""",IFERROR(INDEX(FILTER(Candidates!$S$2:$S$2000,Candidates!$A$2:$A$2000=$A44),COUNTIF(Candidates!$A$2:$A$2000,$A44)),""""))"),"") | W44: =IFERROR(__xludf.DUMMYFUNCTION("IF($A44="""","""",IFERROR(INDEX(FILTER(Candidates!$T$2:$T$2000,Candidates!$A$2:$A$2000=$A44),COUNTIF(Candidates!$A$2:$A$2000,$A44)),""""))"),"")
R45: =IF($A45="","",IFERROR(MINIFS(Candidates!$K$2:$K$2000,Candidates!$A$2:$A$2000,$A45),"")) | S45: =IF($A45="","",IFERROR(MAXIFS(Candidates!$AA$2:$AA$2000,Candidates!$A$2:$A$2000,$A45),"")) | T45: =IFERROR(__xludf.DUMMYFUNCTION("IF($A45="""","""",IFERROR(TEXTJOIN("", "",TRUE,UNIQUE(FILTER(Candidates!$B$2:$B$2000,Candidates!$A$2:$A$2000=$A45))),""""))"),"") | U45: =IF($A45="","",COUNTIF(Candidates!$A$2:$A$2000,$A45)) | V45: =IFERROR(__xludf.DUMMYFUNCTION("IF($A45="""","""",IFERROR(INDEX(FILTER(Candidates!$S$2:$S$2000,Candidates!$A$2:$A$2000=$A45),COUNTIF(Candidates!$A$2:$A$2000,$A45)),""""))"),"") | W45: =IFERROR(__xludf.DUMMYFUNCTION("IF($A45="""","""",IFERROR(INDEX(FILTER(Candidates!$T$2:$T$2000,Candidates!$A$2:$A$2000=$A45),COUNTIF(Candidates!$A$2:$A$2000,$A45)),""""))"),"")
R46: =IF($A46="","",IFERROR(MINIFS(Candidates!$K$2:$K$2000,Candidates!$A$2:$A$2000,$A46),"")) | S46: =IF($A46="","",IFERROR(MAXIFS(Candidates!$AA$2:$AA$2000,Candidates!$A$2:$A$2000,$A46),"")) | T46: =IFERROR(__xludf.DUMMYFUNCTION("IF($A46="""","""",IFERROR(TEXTJOIN("", "",TRUE,UNIQUE(FILTER(Candidates!$B$2:$B$2000,Candidates!$A$2:$A$2000=$A46))),""""))"),"") | U46: =IF($A46="","",COUNTIF(Candidates!$A$2:$A$2000,$A46)) | V46: =IFERROR(__xludf.DUMMYFUNCTION("IF($A46="""","""",IFERROR(INDEX(FILTER(Candidates!$S$2:$S$2000,Candidates!$A$2:$A$2000=$A46),COUNTIF(Candidates!$A$2:$A$2000,$A46)),""""))"),"") | W46: =IFERROR(__xludf.DUMMYFUNCTION("IF($A46="""","""",IFERROR(INDEX(FILTER(Candidates!$T$2:$T$2000,Candidates!$A$2:$A$2000=$A46),COUNTIF(Candidates!$A$2:$A$2000,$A46)),""""))"),"")
